{
  "books": [
  {
    "author": "",
    "info": "‌ಈ ಪುಸ್ತಕವನ್ನು  ಸಂಚಿ ಫೌಂಡೇಶನ್ (https://sanchifoundation.org) ಹಾಗೂ ಸಂಚಯದ (https://sanchaya.org) ವತಿಯಿಂದ ಇಂಡಿಯನ್ ಅಕಾಡೆಮಿ ಆಫ್ ಸೈನ್ಸ್ಸ್, ಬೆಂಗಳೂರಿನಲ್ಲಿ ಜ್ಞಾನದ ಸೇವಕರು (Servants Of Knowledge) ಸಮುದಾಯ ಸಹಭಾಗಿತ್ವದ ಕೆಲಸದಡಿಯಲ್ಲಿ ಡಿಜಿಟಲೀಕರಿಸಲಾಗಿರುತ್ತದೆ.",
    "identifier": "unset0000unse_j4l8",
    "title": "ಯಕ್ಷಗಾನ ಸೇತುಬಂಧನ",
    "publisher": "",
    "tags": "",
    "level": "Yakshagana;Yakshagana Prasanga;ಯಕ್ಷಗಾನ;ಯಕ್ಷಗಾನ ಪ್ರಸಂಗ;ಕನ್ನಡ ಸಾಹಿತ್ಯ",
    "authorUrl": "https://archive.org/search.php?query=creator%3A",
    "url": "https://archive.org/details/unset0000unse_j4l8",
    "cover": "https://archive.org/services/img/unset0000unse_j4l8"
  },
  {
    "author": "ಯಂ. ವೆಂಕಟ ರಾವ್",
    "info": "‌ಈ ಪುಸ್ತಕವನ್ನು  ಸಂಚಿ ಫೌಂಡೇಶನ್ (https://sanchifoundation.org) ಹಾಗೂ ಸಂಚಯದ (https://sanchaya.org) ವತಿಯಿಂದ ಇಂಡಿಯನ್ ಅಕಾಡೆಮಿ ಆಫ್ ಸೈನ್ಸ್ಸ್, ಬೆಂಗಳೂರಿನಲ್ಲಿ ಜ್ಞಾನದ ಸೇವಕರು (Servants Of Knowledge) ಸಮುದಾಯ ಸಹಭಾಗಿತ್ವದ ಕೆಲಸದಡಿಯಲ್ಲಿ ಡಿಜಿಟಲೀಕರಿಸಲಾಗಿರುತ್ತದೆ.",
    "identifier": "unset0000unse_k7h0",
    "title": "ಅಂಗದ ಸಂಧಾನ",
    "publisher": "ಶ್ರೀ ನಿತ್ಯಾನಂದ ಗ್ರಂಥಾಲಯ",
    "tags": "",
    "level": "Yakshagana;Yakshagana Prasanga;ಯಕ್ಷಗಾನ;ಯಕ್ಷಗಾನ ಪ್ರಸಂಗ;ಕನ್ನಡ ಸಾಹಿತ್ಯ",
    "authorUrl": "https://archive.org/search.php?query=creator%3Aಯಂ. ವೆಂಕಟ ರಾವ್",
    "url": "https://archive.org/details/unset0000unse_k7h0",
    "cover": "https://archive.org/services/img/unset0000unse_k7h0"
  },
  {
    "author": "ಎಂ. ಪ್ರಭಾಕರ ಜೋಶಿ",
    "info": "‌ಈ ಪುಸ್ತಕವನ್ನು  ಸಂಚಿ ಫೌಂಡೇಶನ್ (https://sanchifoundation.org) ಹಾಗೂ ಸಂಚಯದ (https://sanchaya.org) ವತಿಯಿಂದ ಇಂಡಿಯನ್ ಅಕಾಡೆಮಿ ಆಫ್ ಸೈನ್ಸ್ಸ್, ಬೆಂಗಳೂರಿನಲ್ಲಿ ಜ್ಞಾನದ ಸೇವಕರು (Servants Of Knowledge) ಸಮುದಾಯ ಸಹಭಾಗಿತ್ವದ ಕೆಲಸದಡಿಯಲ್ಲಿ ಡಿಜಿಟಲೀಕರಿಸಲಾಗಿರುತ್ತದೆ.",
    "identifier": "unset0000unse_e3a1",
    "title": "ಅಂಗದ ಸಂಧಾನ",
    "publisher": "ನಿತ್ಯಾನಂದ ಗ್ರಂಥಾಲಯ",
    "tags": "",
    "level": "Yakshagana;Yakshagana Prasanga;ಯಕ್ಷಗಾನ;ಯಕ್ಷಗಾನ ಪ್ರಸಂಗ;ಕನ್ನಡ ಸಾಹಿತ್ಯ",
    "authorUrl": "https://archive.org/search.php?query=creator%3Aಎಂ. ಪ್ರಭಾಕರ ಜೋಶಿ",
    "url": "https://archive.org/details/unset0000unse_e3a1",
    "cover": "https://archive.org/services/img/unset0000unse_e3a1"
  },
  {
    "author": "ಅಮೃತ್ ಸೋಮೇಶ್ವರ",
    "info": "‌ಈ ಪುಸ್ತಕವನ್ನು  ಸಂಚಿ ಫೌಂಡೇಶನ್ (https://sanchifoundation.org) ಹಾಗೂ ಸಂಚಯದ (https://sanchaya.org) ವತಿಯಿಂದ ಇಂಡಿಯನ್ ಅಕಾಡೆಮಿ ಆಫ್ ಸೈನ್ಸ್ಸ್, ಬೆಂಗಳೂರಿನಲ್ಲಿ ಜ್ಞಾನದ ಸೇವಕರು (Servants Of Knowledge) ಸಮುದಾಯ ಸಹಭಾಗಿತ್ವದ ಕೆಲಸದಡಿಯಲ್ಲಿ ಡಿಜಿಟಲೀಕರಿಸಲಾಗಿರುತ್ತದೆ.",
    "identifier": "unset0000unse_m4v2",
    "title": "ಅಂಧಕ ಮೋಕ್ಷ",
    "publisher": "ಪ್ರಾಕ್ರಿತಿ ಪ್ರಕಾಶನ",
    "tags": "",
    "level": "Yakshagana;Yakshagana Prasanga;ಯಕ್ಷಗಾನ;ಯಕ್ಷಗಾನ ಪ್ರಸಂಗ;ಕನ್ನಡ ಸಾಹಿತ್ಯ",
    "authorUrl": "https://archive.org/search.php?query=creator%3Aಅಮೃತ್ ಸೋಮೇಶ್ವರ",
    "url": "https://archive.org/details/unset0000unse_m4v2",
    "cover": "https://archive.org/services/img/unset0000unse_m4v2"
  },
  {
    "author": "",
    "info": "‌ಈ ಪುಸ್ತಕವನ್ನು  ಸಂಚಿ ಫೌಂಡೇಶನ್ (https://sanchifoundation.org) ಹಾಗೂ ಸಂಚಯದ (https://sanchaya.org) ವತಿಯಿಂದ ಇಂಡಿಯನ್ ಅಕಾಡೆಮಿ ಆಫ್ ಸೈನ್ಸ್ಸ್, ಬೆಂಗಳೂರಿನಲ್ಲಿ ಜ್ಞಾನದ ಸೇವಕರು (Servants Of Knowledge) ಸಮುದಾಯ ಸಹಭಾಗಿತ್ವದ ಕೆಲಸದಡಿಯಲ್ಲಿ ಡಿಜಿಟಲೀಕರಿಸಲಾಗಿರುತ್ತದೆ.",
    "identifier": "unset0000unse_f6w2",
    "title": "ಅನಂತನವ್ರತ ಮಹಾತ್ಮೆ",
    "publisher": "ಪಾವಂಜೆ ಗುರುರಾವ್",
    "tags": "",
    "level": "Yakshagana;Yakshagana Prasanga;ಯಕ್ಷಗಾನ;ಯಕ್ಷಗಾನ ಪ್ರಸಂಗ;ಕನ್ನಡ ಸಾಹಿತ್ಯ",
    "authorUrl": "https://archive.org/search.php?query=creator%3A",
    "url": "https://archive.org/details/unset0000unse_f6w2",
    "cover": "https://archive.org/services/img/unset0000unse_f6w2"
  },
  {
    "author": "",
    "info": "‌ಈ ಪುಸ್ತಕವನ್ನು  ಸಂಚಿ ಫೌಂಡೇಶನ್ (https://sanchifoundation.org) ಹಾಗೂ ಸಂಚಯದ (https://sanchaya.org) ವತಿಯಿಂದ ಇಂಡಿಯನ್ ಅಕಾಡೆಮಿ ಆಫ್ ಸೈನ್ಸ್ಸ್, ಬೆಂಗಳೂರಿನಲ್ಲಿ ಜ್ಞಾನದ ಸೇವಕರು (Servants Of Knowledge) ಸಮುದಾಯ ಸಹಭಾಗಿತ್ವದ ಕೆಲಸದಡಿಯಲ್ಲಿ ಡಿಜಿಟಲೀಕರಿಸಲಾಗಿರುತ್ತದೆ.",
    "identifier": "unset0000unse_a5d1",
    "title": "ಅಭಿಮನ್ಯುಕಾಳಗ ಮತ್ತು ಸೈಂಧವನ ವಧೆ",
    "publisher": "ಪಾವಂಜೆ ಗುರುರಾವ್",
    "tags": "",
    "level": "Yakshagana;Yakshagana Prasanga;ಯಕ್ಷಗಾನ;ಯಕ್ಷಗಾನ ಪ್ರಸಂಗ;ಕನ್ನಡ ಸಾಹಿತ್ಯ",
    "authorUrl": "https://archive.org/search.php?query=creator%3A",
    "url": "https://archive.org/details/unset0000unse_a5d1",
    "cover": "https://archive.org/services/img/unset0000unse_a5d1"
  },
  {
    "author": "ಕೀರಿಕ್ಕಾಡು ಮಾಸ್ತರ್ ವಿಷ್ಣು ಭಟ್",
    "info": "‌ಈ ಪುಸ್ತಕವನ್ನು  ಸಂಚಿ ಫೌಂಡೇಶನ್ (https://sanchifoundation.org) ಹಾಗೂ ಸಂಚಯದ (https://sanchaya.org) ವತಿಯಿಂದ ಇಂಡಿಯನ್ ಅಕಾಡೆಮಿ ಆಫ್ ಸೈನ್ಸ್ಸ್, ಬೆಂಗಳೂರಿನಲ್ಲಿ ಜ್ಞಾನದ ಸೇವಕರು (Servants Of Knowledge) ಸಮುದಾಯ ಸಹಭಾಗಿತ್ವದ ಕೆಲಸದಡಿಯಲ್ಲಿ ಡಿಜಿಟಲೀಕರಿಸಲಾಗಿರುತ್ತದೆ.",
    "identifier": "unset0000unse_y0w8",
    "title": "ಅಮೋಘವರ್ಷ ನೃಪತುಂಗ",
    "publisher": "ಶ್ರೀ ಗೋಪಾಲಕೃಷ್ಣ ಪ್ರಕಾಶನ",
    "tags": "",
    "level": "Yakshagana;Yakshagana Prasanga;ಯಕ್ಷಗಾನ;ಯಕ್ಷಗಾನ ಪ್ರಸಂಗ;ಕನ್ನಡ ಸಾಹಿತ್ಯ",
    "authorUrl": "https://archive.org/search.php?query=creator%3Aಕೀರಿಕ್ಕಾಡು ಮಾಸ್ತರ್ ವಿಷ್ಣು ಭಟ್",
    "url": "https://archive.org/details/unset0000unse_y0w8",
    "cover": "https://archive.org/services/img/unset0000unse_y0w8"
  },
  {
    "author": "ಡಿ. ವಿ. ಹೊಳ್ಳ, ವಿದ್ವಾನ್",
    "info": "‌ಈ ಪುಸ್ತಕವನ್ನು  ಸಂಚಿ ಫೌಂಡೇಶನ್ (https://sanchifoundation.org) ಹಾಗೂ ಸಂಚಯದ (https://sanchaya.org) ವತಿಯಿಂದ ಇಂಡಿಯನ್ ಅಕಾಡೆಮಿ ಆಫ್ ಸೈನ್ಸ್ಸ್, ಬೆಂಗಳೂರಿನಲ್ಲಿ ಜ್ಞಾನದ ಸೇವಕರು (Servants Of Knowledge) ಸಮುದಾಯ ಸಹಭಾಗಿತ್ವದ ಕೆಲಸದಡಿಯಲ್ಲಿ ಡಿಜಿಟಲೀಕರಿಸಲಾಗಿರುತ್ತದೆ.",
    "identifier": "unset0000unse_l5r7",
    "title": "ಅಂಶುಮತಿ ಕಲ್ಯಾಣ",
    "publisher": "ಡಿ. ವಿ. ಹೊಳ್ಳ, ವಿದ್ವಾನ್",
    "tags": "",
    "level": "Yakshagana;Yakshagana Prasanga;ಯಕ್ಷಗಾನ;ಯಕ್ಷಗಾನ ಪ್ರಸಂಗ;ಕನ್ನಡ ಸಾಹಿತ್ಯ",
    "authorUrl": "https://archive.org/search.php?query=creator%3Aಡಿ. ವಿ. ಹೊಳ್ಳ, ವಿದ್ವಾನ್",
    "url": "https://archive.org/details/unset0000unse_l5r7",
    "cover": "https://archive.org/services/img/unset0000unse_l5r7"
  },
  {
    "author": "ಕೀರಿಕ್ಕಾಡು ಮಾಸ್ತರ್ ವಿಷ್ಣು ಭಟ್",
    "info": "‌ಈ ಪುಸ್ತಕವನ್ನು  ಸಂಚಿ ಫೌಂಡೇಶನ್ (https://sanchifoundation.org) ಹಾಗೂ ಸಂಚಯದ (https://sanchaya.org) ವತಿಯಿಂದ ಇಂಡಿಯನ್ ಅಕಾಡೆಮಿ ಆಫ್ ಸೈನ್ಸ್ಸ್, ಬೆಂಗಳೂರಿನಲ್ಲಿ ಜ್ಞಾನದ ಸೇವಕರು (Servants Of Knowledge) ಸಮುದಾಯ ಸಹಭಾಗಿತ್ವದ ಕೆಲಸದಡಿಯಲ್ಲಿ ಡಿಜಿಟಲೀಕರಿಸಲಾಗಿರುತ್ತದೆ.",
    "identifier": "unset0000unse_s1r7",
    "title": "ಊರ್ವಶಿ ಪುರೂರವ",
    "publisher": "ಶ್ರೀ ಗೋಪಾಲಕೃಷ್ಣ ಪ್ರಕಾಶನ",
    "tags": "",
    "level": "Yakshagana;Yakshagana Prasanga;ಯಕ್ಷಗಾನ;ಯಕ್ಷಗಾನ ಪ್ರಸಂಗ;ಕನ್ನಡ ಸಾಹಿತ್ಯ",
    "authorUrl": "https://archive.org/search.php?query=creator%3Aಕೀರಿಕ್ಕಾಡು ಮಾಸ್ತರ್ ವಿಷ್ಣು ಭಟ್",
    "url": "https://archive.org/details/unset0000unse_s1r7",
    "cover": "https://archive.org/services/img/unset0000unse_s1r7"
  },
  {
    "author": "ಮಧುಕುಮಾರ್",
    "info": "‌ಈ ಪುಸ್ತಕವನ್ನು  ಸಂಚಿ ಫೌಂಡೇಶನ್ (https://sanchifoundation.org) ಹಾಗೂ ಸಂಚಯದ (https://sanchaya.org) ವತಿಯಿಂದ ಇಂಡಿಯನ್ ಅಕಾಡೆಮಿ ಆಫ್ ಸೈನ್ಸ್ಸ್, ಬೆಂಗಳೂರಿನಲ್ಲಿ ಜ್ಞಾನದ ಸೇವಕರು (Servants Of Knowledge) ಸಮುದಾಯ ಸಹಭಾಗಿತ್ವದ ಕೆಲಸದಡಿಯಲ್ಲಿ ಡಿಜಿಟಲೀಕರಿಸಲಾಗಿರುತ್ತದೆ.",
    "identifier": "unset0000unse_i9i7",
    "title": "ಏಕಾದಶಿ ದೇವಿ ಮಹಾತ್ಮೆ ಮುರಾಸುರ ವಧೆ",
    "publisher": "ಯು. ಶ್ಯಾಮ ಸುಂದರ ನೃತ್ಯಗಾರ",
    "tags": "",
    "level": "Yakshagana;Yakshagana Prasanga;ಯಕ್ಷಗಾನ;ಯಕ್ಷಗಾನ ಪ್ರಸಂಗ;ಕನ್ನಡ ಸಾಹಿತ್ಯ",
    "authorUrl": "https://archive.org/search.php?query=creator%3Aಮಧುಕುಮಾರ್",
    "url": "https://archive.org/details/unset0000unse_i9i7",
    "cover": "https://archive.org/services/img/unset0000unse_i9i7"
  },
  {
    "author": "G.N. Ananthavardhana",
    "info": "‌ಈ ಪುಸ್ತಕವನ್ನು  ಸಂಚಿ ಫೌಂಡೇಶನ್ (https://sanchifoundation.org) ಹಾಗೂ ಸಂಚಯದ (https://sanchaya.org) ವತಿಯಿಂದ ಇಂಡಿಯನ್ ಅಕಾಡೆಮಿ ಆಫ್ ಸೈನ್ಸ್ಸ್, ಬೆಂಗಳೂರಿನಲ್ಲಿ ಜ್ಞಾನದ ಸೇವಕರು (Servants Of Knowledge) ಸಮುದಾಯ ಸಹಭಾಗಿತ್ವದ ಕೆಲಸದಡಿಯಲ್ಲಿ ಡಿಜಿಟಲೀಕರಿಸಲಾಗಿರುತ್ತದೆ.",
    "identifier": "unset0000unse_g6j1",
    "title": "ಏಳು ಯಕ್ಷಗಾನ ಪೌರಾಣಿಕ ಪ್ರಸಂಗಗಳು",
    "publisher": "Navabharathi Prakashana",
    "tags": "",
    "level": "Yakshagana;Yakshagana Prasanga;ಯಕ್ಷಗಾನ;ಯಕ್ಷಗಾನ ಪ್ರಸಂಗ;ಕನ್ನಡ ಸಾಹಿತ್ಯ",
    "authorUrl": "https://archive.org/search.php?query=creator%3AG.N. Ananthavardhana",
    "url": "https://archive.org/details/unset0000unse_g6j1",
    "cover": "https://archive.org/services/img/unset0000unse_g6j1"
  },
  {
    "author": "Kirikakdu Mastar Vishnu Bhatta",
    "info": "‌ಈ ಪುಸ್ತಕವನ್ನು  ಸಂಚಿ ಫೌಂಡೇಶನ್ (https://sanchifoundation.org) ಹಾಗೂ ಸಂಚಯದ (https://sanchaya.org) ವತಿಯಿಂದ ಇಂಡಿಯನ್ ಅಕಾಡೆಮಿ ಆಫ್ ಸೈನ್ಸ್ಸ್, ಬೆಂಗಳೂರಿನಲ್ಲಿ ಜ್ಞಾನದ ಸೇವಕರು (Servants Of Knowledge) ಸಮುದಾಯ ಸಹಭಾಗಿತ್ವದ ಕೆಲಸದಡಿಯಲ್ಲಿ ಡಿಜಿಟಲೀಕರಿಸಲಾಗಿರುತ್ತದೆ.",
    "identifier": "unset0000unse_v4p0",
    "title": "ಕಂಜಾಕ್ಷಿ ಕಲ್ಯಾಣ",
    "publisher": "ಶ್ರೀ ಗೋಪಾಲಕೃಷ್ಣ ಪ್ರಕಾಶನ",
    "tags": "",
    "level": "Yakshagana;Yakshagana Prasanga;ಯಕ್ಷಗಾನ;ಯಕ್ಷಗಾನ ಪ್ರಸಂಗ;ಕನ್ನಡ ಸಾಹಿತ್ಯ",
    "authorUrl": "https://archive.org/search.php?query=creator%3AKirikakdu Mastar Vishnu Bhatta",
    "url": "https://archive.org/details/unset0000unse_v4p0",
    "cover": "https://archive.org/services/img/unset0000unse_v4p0"
  },
  {
    "author": "ಕೀರಿಕ್ಕಾಡು ಮಾಸ್ತರ್ ವಿಷ್ಣು ಭಟ್",
    "info": "‌ಈ ಪುಸ್ತಕವನ್ನು  ಸಂಚಿ ಫೌಂಡೇಶನ್ (https://sanchifoundation.org) ಹಾಗೂ ಸಂಚಯದ (https://sanchaya.org) ವತಿಯಿಂದ ಇಂಡಿಯನ್ ಅಕಾಡೆಮಿ ಆಫ್ ಸೈನ್ಸ್ಸ್, ಬೆಂಗಳೂರಿನಲ್ಲಿ ಜ್ಞಾನದ ಸೇವಕರು (Servants Of Knowledge) ಸಮುದಾಯ ಸಹಭಾಗಿತ್ವದ ಕೆಲಸದಡಿಯಲ್ಲಿ ಡಿಜಿಟಲೀಕರಿಸಲಾಗಿರುತ್ತದೆ.",
    "identifier": "unset0000unse_o9h5",
    "title": "ಕನಕ ಲೇಖ",
    "publisher": "Kiran Printers",
    "tags": "",
    "level": "Yakshagana;Yakshagana Prasanga;ಯಕ್ಷಗಾನ;ಯಕ್ಷಗಾನ ಪ್ರಸಂಗ;ಕನ್ನಡ ಸಾಹಿತ್ಯ",
    "authorUrl": "https://archive.org/search.php?query=creator%3Aಕೀರಿಕ್ಕಾಡು ಮಾಸ್ತರ್ ವಿಷ್ಣು ಭಟ್",
    "url": "https://archive.org/details/unset0000unse_o9h5",
    "cover": "https://archive.org/services/img/unset0000unse_o9h5"
  },
  {
    "author": "ಮವ್ವಾರು ಕಿಟ್ಟಣ್ಣ ಭಾಗವತ",
    "info": "‌ಈ ಪುಸ್ತಕವನ್ನು  ಸಂಚಿ ಫೌಂಡೇಶನ್ (https://sanchifoundation.org) ಹಾಗೂ ಸಂಚಯದ (https://sanchaya.org) ವತಿಯಿಂದ ಇಂಡಿಯನ್ ಅಕಾಡೆಮಿ ಆಫ್ ಸೈನ್ಸ್ಸ್, ಬೆಂಗಳೂರಿನಲ್ಲಿ ಜ್ಞಾನದ ಸೇವಕರು (Servants Of Knowledge) ಸಮುದಾಯ ಸಹಭಾಗಿತ್ವದ ಕೆಲಸದಡಿಯಲ್ಲಿ ಡಿಜಿಟಲೀಕರಿಸಲಾಗಿರುತ್ತದೆ.",
    "identifier": "unset0000unse_k8t8",
    "title": "ಕನಕಮಾಲಿನಿ ಪರಿಣಯ",
    "publisher": "ಮವ್ವಾರು ಕಿಟ್ಟಣ್ಣ ಭಾಗವತ",
    "tags": "",
    "level": "Yakshagana;Yakshagana Prasanga;ಯಕ್ಷಗಾನ;ಯಕ್ಷಗಾನ ಪ್ರಸಂಗ;ಕನ್ನಡ ಸಾಹಿತ್ಯ",
    "authorUrl": "https://archive.org/search.php?query=creator%3Aಮವ್ವಾರು ಕಿಟ್ಟಣ್ಣ ಭಾಗವತ",
    "url": "https://archive.org/details/unset0000unse_k8t8",
    "cover": "https://archive.org/services/img/unset0000unse_k8t8"
  },
  {
    "author": "ಕೀರಿಕ್ಕಾಡು ಮಾಸ್ತರ್ ವಿಷ್ಣು ಭಟ್",
    "info": "‌ಈ ಪುಸ್ತಕವನ್ನು  ಸಂಚಿ ಫೌಂಡೇಶನ್ (https://sanchifoundation.org) ಹಾಗೂ ಸಂಚಯದ (https://sanchaya.org) ವತಿಯಿಂದ ಇಂಡಿಯನ್ ಅಕಾಡೆಮಿ ಆಫ್ ಸೈನ್ಸ್ಸ್, ಬೆಂಗಳೂರಿನಲ್ಲಿ ಜ್ಞಾನದ ಸೇವಕರು (Servants Of Knowledge) ಸಮುದಾಯ ಸಹಭಾಗಿತ್ವದ ಕೆಲಸದಡಿಯಲ್ಲಿ ಡಿಜಿಟಲೀಕರಿಸಲಾಗಿರುತ್ತದೆ.",
    "identifier": "unset0000unse_m2z8",
    "title": "ಕರಸುರ ವಧೆ",
    "publisher": "ಶ್ರೀ ಗೋಪಾಲಕೃಷ್ಣ ಪ್ರಕಾಶನ",
    "tags": "",
    "level": "Yakshagana;Yakshagana Prasanga;ಯಕ್ಷಗಾನ;ಯಕ್ಷಗಾನ ಪ್ರಸಂಗ;ಕನ್ನಡ ಸಾಹಿತ್ಯ",
    "authorUrl": "https://archive.org/search.php?query=creator%3Aಕೀರಿಕ್ಕಾಡು ಮಾಸ್ತರ್ ವಿಷ್ಣು ಭಟ್",
    "url": "https://archive.org/details/unset0000unse_m2z8",
    "cover": "https://archive.org/services/img/unset0000unse_m2z8"
  },
  {
    "author": "",
    "info": "‌ಈ ಪುಸ್ತಕವನ್ನು  ಸಂಚಿ ಫೌಂಡೇಶನ್ (https://sanchifoundation.org) ಹಾಗೂ ಸಂಚಯದ (https://sanchaya.org) ವತಿಯಿಂದ ಇಂಡಿಯನ್ ಅಕಾಡೆಮಿ ಆಫ್ ಸೈನ್ಸ್ಸ್, ಬೆಂಗಳೂರಿನಲ್ಲಿ ಜ್ಞಾನದ ಸೇವಕರು (Servants Of Knowledge) ಸಮುದಾಯ ಸಹಭಾಗಿತ್ವದ ಕೆಲಸದಡಿಯಲ್ಲಿ ಡಿಜಿಟಲೀಕರಿಸಲಾಗಿರುತ್ತದೆ.",
    "identifier": "unset0000unse_d2h1",
    "title": "ಕರ್ಣಪರ್ವ ಪ್ರಸಂಗ",
    "publisher": "ಪಾವಂಜೆ ಗುರುರಾವ್",
    "tags": "",
    "level": "Yakshagana;Yakshagana Prasanga;ಯಕ್ಷಗಾನ;ಯಕ್ಷಗಾನ ಪ್ರಸಂಗ;ಕನ್ನಡ ಸಾಹಿತ್ಯ",
    "authorUrl": "https://archive.org/search.php?query=creator%3A",
    "url": "https://archive.org/details/unset0000unse_d2h1",
    "cover": "https://archive.org/services/img/unset0000unse_d2h1"
  },
  {
    "author": "ಕೀರಿಕ್ಕಾಡು ಮಾಸ್ತರ್ ವಿಷ್ಣು ಭಟ್",
    "info": "‌ಈ ಪುಸ್ತಕವನ್ನು  ಸಂಚಿ ಫೌಂಡೇಶನ್ (https://sanchifoundation.org) ಹಾಗೂ ಸಂಚಯದ (https://sanchaya.org) ವತಿಯಿಂದ ಇಂಡಿಯನ್ ಅಕಾಡೆಮಿ ಆಫ್ ಸೈನ್ಸ್ಸ್, ಬೆಂಗಳೂರಿನಲ್ಲಿ ಜ್ಞಾನದ ಸೇವಕರು (Servants Of Knowledge) ಸಮುದಾಯ ಸಹಭಾಗಿತ್ವದ ಕೆಲಸದಡಿಯಲ್ಲಿ ಡಿಜಿಟಲೀಕರಿಸಲಾಗಿರುತ್ತದೆ.",
    "identifier": "unset0000unse_y2s7",
    "title": "ಕಲ್ಪಸುಂದರಿ ಕಲ್ಯಾಣ",
    "publisher": "ಶ್ರೀ ಗೋಪಾಲಕೃಷ್ಣ ಪ್ರಕಾಶನ",
    "tags": "",
    "level": "Yakshagana;Yakshagana Prasanga;ಯಕ್ಷಗಾನ;ಯಕ್ಷಗಾನ ಪ್ರಸಂಗ;ಕನ್ನಡ ಸಾಹಿತ್ಯ",
    "authorUrl": "https://archive.org/search.php?query=creator%3Aಕೀರಿಕ್ಕಾಡು ಮಾಸ್ತರ್ ವಿಷ್ಣು ಭಟ್",
    "url": "https://archive.org/details/unset0000unse_y2s7",
    "cover": "https://archive.org/services/img/unset0000unse_y2s7"
  },
  {
    "author": "",
    "info": "‌ಈ ಪುಸ್ತಕವನ್ನು  ಸಂಚಿ ಫೌಂಡೇಶನ್ (https://sanchifoundation.org) ಹಾಗೂ ಸಂಚಯದ (https://sanchaya.org) ವತಿಯಿಂದ ಇಂಡಿಯನ್ ಅಕಾಡೆಮಿ ಆಫ್ ಸೈನ್ಸ್ಸ್, ಬೆಂಗಳೂರಿನಲ್ಲಿ ಜ್ಞಾನದ ಸೇವಕರು (Servants Of Knowledge) ಸಮುದಾಯ ಸಹಭಾಗಿತ್ವದ ಕೆಲಸದಡಿಯಲ್ಲಿ ಡಿಜಿಟಲೀಕರಿಸಲಾಗಿರುತ್ತದೆ.",
    "identifier": "unset0000unse_w2a0",
    "title": "ಕಾಲನೇಮಿ ಕಾಳಗ",
    "publisher": "ಪಾವಂಜೆ ಗುರುರಾವ್",
    "tags": "",
    "level": "Yakshagana;Yakshagana Prasanga;ಯಕ್ಷಗಾನ;ಯಕ್ಷಗಾನ ಪ್ರಸಂಗ;ಕನ್ನಡ ಸಾಹಿತ್ಯ",
    "authorUrl": "https://archive.org/search.php?query=creator%3A",
    "url": "https://archive.org/details/unset0000unse_w2a0",
    "cover": "https://archive.org/services/img/unset0000unse_w2a0"
  },
  {
    "author": "",
    "info": "‌ಈ ಪುಸ್ತಕವನ್ನು  ಸಂಚಿ ಫೌಂಡೇಶನ್ (https://sanchifoundation.org) ಹಾಗೂ ಸಂಚಯದ (https://sanchaya.org) ವತಿಯಿಂದ ಇಂಡಿಯನ್ ಅಕಾಡೆಮಿ ಆಫ್ ಸೈನ್ಸ್ಸ್, ಬೆಂಗಳೂರಿನಲ್ಲಿ ಜ್ಞಾನದ ಸೇವಕರು (Servants Of Knowledge) ಸಮುದಾಯ ಸಹಭಾಗಿತ್ವದ ಕೆಲಸದಡಿಯಲ್ಲಿ ಡಿಜಿಟಲೀಕರಿಸಲಾಗಿರುತ್ತದೆ.",
    "identifier": "unset0000unse_x9e7",
    "title": "ಕುಂಬಕರ್ಣ ಕಾಳಗವನು",
    "publisher": "",
    "tags": "",
    "level": "Yakshagana;Yakshagana Prasanga;ಯಕ್ಷಗಾನ;ಯಕ್ಷಗಾನ ಪ್ರಸಂಗ;ಕನ್ನಡ ಸಾಹಿತ್ಯ",
    "authorUrl": "https://archive.org/search.php?query=creator%3A",
    "url": "https://archive.org/details/unset0000unse_x9e7",
    "cover": "https://archive.org/services/img/unset0000unse_x9e7"
  },
  {
    "author": "Chavarkadu Shambu Johisaru",
    "info": "‌ಈ ಪುಸ್ತಕವನ್ನು  ಸಂಚಿ ಫೌಂಡೇಶನ್ (https://sanchifoundation.org) ಹಾಗೂ ಸಂಚಯದ (https://sanchaya.org) ವತಿಯಿಂದ ಇಂಡಿಯನ್ ಅಕಾಡೆಮಿ ಆಫ್ ಸೈನ್ಸ್ಸ್, ಬೆಂಗಳೂರಿನಲ್ಲಿ ಜ್ಞಾನದ ಸೇವಕರು (Servants Of Knowledge) ಸಮುದಾಯ ಸಹಭಾಗಿತ್ವದ ಕೆಲಸದಡಿಯಲ್ಲಿ ಡಿಜಿಟಲೀಕರಿಸಲಾಗಿರುತ್ತದೆ.",
    "identifier": "unset0000unse_y0v7",
    "title": "ಕುಮುದಾಕ್ಷಿ ಕಲ್ಯಾಣ",
    "publisher": "ಪಾವಂಜೆ ಗುರುರಾವ್",
    "tags": "",
    "level": "Yakshagana;Yakshagana Prasanga;ಯಕ್ಷಗಾನ;ಯಕ್ಷಗಾನ ಪ್ರಸಂಗ;ಕನ್ನಡ ಸಾಹಿತ್ಯ",
    "authorUrl": "https://archive.org/search.php?query=creator%3AChavarkadu Shambu Johisaru",
    "url": "https://archive.org/details/unset0000unse_y0v7",
    "cover": "https://archive.org/services/img/unset0000unse_y0v7"
  },
  {
    "author": "ಹಲಸಿನಹಳ್ಳಿ ನರಸಿಂಹಶಾಸ್ತ್ರಿಗಳು",
    "info": "‌ಈ ಪುಸ್ತಕವನ್ನು  ಸಂಚಿ ಫೌಂಡೇಶನ್ (https://sanchifoundation.org) ಹಾಗೂ ಸಂಚಯದ (https://sanchaya.org) ವತಿಯಿಂದ ಇಂಡಿಯನ್ ಅಕಾಡೆಮಿ ಆಫ್ ಸೈನ್ಸ್ಸ್, ಬೆಂಗಳೂರಿನಲ್ಲಿ ಜ್ಞಾನದ ಸೇವಕರು (Servants Of Knowledge) ಸಮುದಾಯ ಸಹಭಾಗಿತ್ವದ ಕೆಲಸದಡಿಯಲ್ಲಿ ಡಿಜಿಟಲೀಕರಿಸಲಾಗಿರುತ್ತದೆ.",
    "identifier": "unset0000unse_p9s2",
    "title": "ಕುಮುದ್ವತಿ ಕಲ್ಯಾಣ",
    "publisher": "ರಾಧಾಕೃಷ್ಣ ಪ್ರಿಂಟಿಂಗ್ ಪ್ರೆಸ್",
    "tags": "",
    "level": "Yakshagana;Yakshagana Prasanga;ಯಕ್ಷಗಾನ;ಯಕ್ಷಗಾನ ಪ್ರಸಂಗ;ಕನ್ನಡ ಸಾಹಿತ್ಯ",
    "authorUrl": "https://archive.org/search.php?query=creator%3Aಹಲಸಿನಹಳ್ಳಿ ನರಸಿಂಹಶಾಸ್ತ್ರಿಗಳು",
    "url": "https://archive.org/details/unset0000unse_p9s2",
    "cover": "https://archive.org/services/img/unset0000unse_p9s2"
  },
  {
    "author": "Sankayya Bagavatharu",
    "info": "‌ಈ ಪುಸ್ತಕವನ್ನು  ಸಂಚಿ ಫೌಂಡೇಶನ್ (https://sanchifoundation.org) ಹಾಗೂ ಸಂಚಯದ (https://sanchaya.org) ವತಿಯಿಂದ ಇಂಡಿಯನ್ ಅಕಾಡೆಮಿ ಆಫ್ ಸೈನ್ಸ್ಸ್, ಬೆಂಗಳೂರಿನಲ್ಲಿ ಜ್ಞಾನದ ಸೇವಕರು (Servants Of Knowledge) ಸಮುದಾಯ ಸಹಭಾಗಿತ್ವದ ಕೆಲಸದಡಿಯಲ್ಲಿ ಡಿಜಿಟಲೀಕರಿಸಲಾಗಿರುತ್ತದೆ.",
    "identifier": "unset0000unse_c0g4",
    "title": "ಕೃಷ್ಣಾರ್ಜುನರ ಕಾಳಗ",
    "publisher": "Yakshagana Sangatana Samithi",
    "tags": "",
    "level": "Yakshagana;Yakshagana Prasanga;ಯಕ್ಷಗಾನ;ಯಕ್ಷಗಾನ ಪ್ರಸಂಗ;ಕನ್ನಡ ಸಾಹಿತ್ಯ",
    "authorUrl": "https://archive.org/search.php?query=creator%3ASankayya Bagavatharu",
    "url": "https://archive.org/details/unset0000unse_c0g4",
    "cover": "https://archive.org/services/img/unset0000unse_c0g4"
  },
  {
    "author": "ಕೆ. ಅನಂತರಾಮ ಬಂಗಾಡಿ",
    "info": "‌ಈ ಪುಸ್ತಕವನ್ನು  ಸಂಚಿ ಫೌಂಡೇಶನ್ (https://sanchifoundation.org) ಹಾಗೂ ಸಂಚಯದ (https://sanchaya.org) ವತಿಯಿಂದ ಇಂಡಿಯನ್ ಅಕಾಡೆಮಿ ಆಫ್ ಸೈನ್ಸ್ಸ್, ಬೆಂಗಳೂರಿನಲ್ಲಿ ಜ್ಞಾನದ ಸೇವಕರು (Servants Of Knowledge) ಸಮುದಾಯ ಸಹಭಾಗಿತ್ವದ ಕೆಲಸದಡಿಯಲ್ಲಿ ಡಿಜಿಟಲೀಕರಿಸಲಾಗಿರುತ್ತದೆ.",
    "identifier": "unset0000unse_g1m3",
    "title": "ಕೇಕಯ ನಂದಿನಿ ಅಥವಾ ಕೈಕೇಯಿ",
    "publisher": "ಶ್ರೀ ನಿತ್ಯಾನಂದ ಗ್ರಂಥಾಲಯ",
    "tags": "",
    "level": "Yakshagana;Yakshagana Prasanga;ಯಕ್ಷಗಾನ;ಯಕ್ಷಗಾನ ಪ್ರಸಂಗ;ಕನ್ನಡ ಸಾಹಿತ್ಯ",
    "authorUrl": "https://archive.org/search.php?query=creator%3Aಕೆ. ಅನಂತರಾಮ ಬಂಗಾಡಿ",
    "url": "https://archive.org/details/unset0000unse_g1m3",
    "cover": "https://archive.org/services/img/unset0000unse_g1m3"
  },
  {
    "author": "ಡಿ. ವಿ. ಹೊಳ್ಳ, ವಿದ್ವಾನ್",
    "info": "‌ಈ ಪುಸ್ತಕವನ್ನು  ಸಂಚಿ ಫೌಂಡೇಶನ್ (https://sanchifoundation.org) ಹಾಗೂ ಸಂಚಯದ (https://sanchaya.org) ವತಿಯಿಂದ ಇಂಡಿಯನ್ ಅಕಾಡೆಮಿ ಆಫ್ ಸೈನ್ಸ್ಸ್, ಬೆಂಗಳೂರಿನಲ್ಲಿ ಜ್ಞಾನದ ಸೇವಕರು (Servants Of Knowledge) ಸಮುದಾಯ ಸಹಭಾಗಿತ್ವದ ಕೆಲಸದಡಿಯಲ್ಲಿ ಡಿಜಿಟಲೀಕರಿಸಲಾಗಿರುತ್ತದೆ.",
    "identifier": "unset0000unse_v6b5",
    "title": "ಕೌಸಲ್ಯ ಪರಿಣಯ",
    "publisher": "ದಿನೇಶ್ ಪ್ರಿಂಟರ್ಸ್, ಬ್ರಹ್ಮಾವರ",
    "tags": "",
    "level": "Yakshagana;Yakshagana Prasanga;ಯಕ್ಷಗಾನ;ಯಕ್ಷಗಾನ ಪ್ರಸಂಗ;ಕನ್ನಡ ಸಾಹಿತ್ಯ",
    "authorUrl": "https://archive.org/search.php?query=creator%3Aಡಿ. ವಿ. ಹೊಳ್ಳ, ವಿದ್ವಾನ್",
    "url": "https://archive.org/details/unset0000unse_v6b5",
    "cover": "https://archive.org/services/img/unset0000unse_v6b5"
  },
  {
    "author": "Narahari Keshawa Bhatta",
    "info": "‌ಈ ಪುಸ್ತಕವನ್ನು  ಸಂಚಿ ಫೌಂಡೇಶನ್ (https://sanchifoundation.org) ಹಾಗೂ ಸಂಚಯದ (https://sanchaya.org) ವತಿಯಿಂದ ಇಂಡಿಯನ್ ಅಕಾಡೆಮಿ ಆಫ್ ಸೈನ್ಸ್ಸ್, ಬೆಂಗಳೂರಿನಲ್ಲಿ ಜ್ಞಾನದ ಸೇವಕರು (Servants Of Knowledge) ಸಮುದಾಯ ಸಹಭಾಗಿತ್ವದ ಕೆಲಸದಡಿಯಲ್ಲಿ ಡಿಜಿಟಲೀಕರಿಸಲಾಗಿರುತ್ತದೆ.",
    "identifier": "unset0000unse_q8l4",
    "title": "ಕ್ರೌಂಚ ಶಂಬೂಕ",
    "publisher": "Narahari Keshawa Bhatta",
    "tags": "",
    "level": "Yakshagana;Yakshagana Prasanga;ಯಕ್ಷಗಾನ;ಯಕ್ಷಗಾನ ಪ್ರಸಂಗ;ಕನ್ನಡ ಸಾಹಿತ್ಯ",
    "authorUrl": "https://archive.org/search.php?query=creator%3ANarahari Keshawa Bhatta",
    "url": "https://archive.org/details/unset0000unse_q8l4",
    "cover": "https://archive.org/services/img/unset0000unse_q8l4"
  },
  {
    "author": "Ujjre Vasudeva Nayaka",
    "info": "‌ಈ ಪುಸ್ತಕವನ್ನು  ಸಂಚಿ ಫೌಂಡೇಶನ್ (https://sanchifoundation.org) ಹಾಗೂ ಸಂಚಯದ (https://sanchaya.org) ವತಿಯಿಂದ ಇಂಡಿಯನ್ ಅಕಾಡೆಮಿ ಆಫ್ ಸೈನ್ಸ್ಸ್, ಬೆಂಗಳೂರಿನಲ್ಲಿ ಜ್ಞಾನದ ಸೇವಕರು (Servants Of Knowledge) ಸಮುದಾಯ ಸಹಭಾಗಿತ್ವದ ಕೆಲಸದಡಿಯಲ್ಲಿ ಡಿಜಿಟಲೀಕರಿಸಲಾಗಿರುತ್ತದೆ.",
    "identifier": "unset0000unse_x0v3",
    "title": "ಗಣಪತಿ ಪ್ರತಾಪ",
    "publisher": "ಆರ್. ವೆಂಕಟಪ್ಪ ಶಣೈ & ಸನ್ಸ್",
    "tags": "",
    "level": "Yakshagana;Yakshagana Prasanga;ಯಕ್ಷಗಾನ;ಯಕ್ಷಗಾನ ಪ್ರಸಂಗ;ಕನ್ನಡ ಸಾಹಿತ್ಯ",
    "authorUrl": "https://archive.org/search.php?query=creator%3AUjjre Vasudeva Nayaka",
    "url": "https://archive.org/details/unset0000unse_x0v3",
    "cover": "https://archive.org/services/img/unset0000unse_x0v3"
  },
  {
    "author": "",
    "info": "‌ಈ ಪುಸ್ತಕವನ್ನು  ಸಂಚಿ ಫೌಂಡೇಶನ್ (https://sanchifoundation.org) ಹಾಗೂ ಸಂಚಯದ (https://sanchaya.org) ವತಿಯಿಂದ ಇಂಡಿಯನ್ ಅಕಾಡೆಮಿ ಆಫ್ ಸೈನ್ಸ್ಸ್, ಬೆಂಗಳೂರಿನಲ್ಲಿ ಜ್ಞಾನದ ಸೇವಕರು (Servants Of Knowledge) ಸಮುದಾಯ ಸಹಭಾಗಿತ್ವದ ಕೆಲಸದಡಿಯಲ್ಲಿ ಡಿಜಿಟಲೀಕರಿಸಲಾಗಿರುತ್ತದೆ.",
    "identifier": "unset0000unse_y2l9",
    "title": "ಗದಾ ಪರ್ವವು",
    "publisher": "ಪಾವಂಜೆ ಗುರುರಾವ್",
    "tags": "",
    "level": "Yakshagana;Yakshagana Prasanga;ಯಕ್ಷಗಾನ;ಯಕ್ಷಗಾನ ಪ್ರಸಂಗ;ಕನ್ನಡ ಸಾಹಿತ್ಯ",
    "authorUrl": "https://archive.org/search.php?query=creator%3A",
    "url": "https://archive.org/details/unset0000unse_y2l9",
    "cover": "https://archive.org/services/img/unset0000unse_y2l9"
  },
  {
    "author": "Sri Kemanu Narayanappaya",
    "info": "‌ಈ ಪುಸ್ತಕವನ್ನು  ಸಂಚಿ ಫೌಂಡೇಶನ್ (https://sanchifoundation.org) ಹಾಗೂ ಸಂಚಯದ (https://sanchaya.org) ವತಿಯಿಂದ ಇಂಡಿಯನ್ ಅಕಾಡೆಮಿ ಆಫ್ ಸೈನ್ಸ್ಸ್, ಬೆಂಗಳೂರಿನಲ್ಲಿ ಜ್ಞಾನದ ಸೇವಕರು (Servants Of Knowledge) ಸಮುದಾಯ ಸಹಭಾಗಿತ್ವದ ಕೆಲಸದಡಿಯಲ್ಲಿ ಡಿಜಿಟಲೀಕರಿಸಲಾಗಿರುತ್ತದೆ.",
    "identifier": "unset0000unse_u0d2",
    "title": "ಗಯಾಸುರ ಚರಿತ್ರೆ",
    "publisher": "Lakshmi Narayana Trust",
    "tags": "",
    "level": "Yakshagana;Yakshagana Prasanga;ಯಕ್ಷಗಾನ;ಯಕ್ಷಗಾನ ಪ್ರಸಂಗ;ಕನ್ನಡ ಸಾಹಿತ್ಯ",
    "authorUrl": "https://archive.org/search.php?query=creator%3ASri Kemanu Narayanappaya",
    "url": "https://archive.org/details/unset0000unse_u0d2",
    "cover": "https://archive.org/services/img/unset0000unse_u0d2"
  },
  {
    "author": "Anatharam Bangaddi",
    "info": "‌ಈ ಪುಸ್ತಕವನ್ನು  ಸಂಚಿ ಫೌಂಡೇಶನ್ (https://sanchifoundation.org) ಹಾಗೂ ಸಂಚಯದ (https://sanchaya.org) ವತಿಯಿಂದ ಇಂಡಿಯನ್ ಅಕಾಡೆಮಿ ಆಫ್ ಸೈನ್ಸ್ಸ್, ಬೆಂಗಳೂರಿನಲ್ಲಿ ಜ್ಞಾನದ ಸೇವಕರು (Servants Of Knowledge) ಸಮುದಾಯ ಸಹಭಾಗಿತ್ವದ ಕೆಲಸದಡಿಯಲ್ಲಿ ಡಿಜಿಟಲೀಕರಿಸಲಾಗಿರುತ್ತದೆ.",
    "identifier": "unset0000unse_k5z7",
    "title": "ಗಾಂಧಾರಿ",
    "publisher": "ಶ್ರೀ ನಿತ್ಯಾನಂದ ಗ್ರಂಥಾಲಯ",
    "tags": "",
    "level": "Yakshagana;Yakshagana Prasanga;ಯಕ್ಷಗಾನ;ಯಕ್ಷಗಾನ ಪ್ರಸಂಗ;ಕನ್ನಡ ಸಾಹಿತ್ಯ",
    "authorUrl": "https://archive.org/search.php?query=creator%3AAnatharam Bangaddi",
    "url": "https://archive.org/details/unset0000unse_k5z7",
    "cover": "https://archive.org/services/img/unset0000unse_k5z7"
  },
  {
    "author": "",
    "info": "‌ಈ ಪುಸ್ತಕವನ್ನು  ಸಂಚಿ ಫೌಂಡೇಶನ್ (https://sanchifoundation.org) ಹಾಗೂ ಸಂಚಯದ (https://sanchaya.org) ವತಿಯಿಂದ ಇಂಡಿಯನ್ ಅಕಾಡೆಮಿ ಆಫ್ ಸೈನ್ಸ್ಸ್, ಬೆಂಗಳೂರಿನಲ್ಲಿ ಜ್ಞಾನದ ಸೇವಕರು (Servants Of Knowledge) ಸಮುದಾಯ ಸಹಭಾಗಿತ್ವದ ಕೆಲಸದಡಿಯಲ್ಲಿ ಡಿಜಿಟಲೀಕರಿಸಲಾಗಿರುತ್ತದೆ.",
    "identifier": "unset0000unse_e4r9",
    "title": "ಗಿರಿಜಾ ಕಲ್ಯಾಣ",
    "publisher": "ಪಾವಂಜೆ ಗುರುರಾವ್",
    "tags": "",
    "level": "Yakshagana;Yakshagana Prasanga;ಯಕ್ಷಗಾನ;ಯಕ್ಷಗಾನ ಪ್ರಸಂಗ;ಕನ್ನಡ ಸಾಹಿತ್ಯ",
    "authorUrl": "https://archive.org/search.php?query=creator%3A",
    "url": "https://archive.org/details/unset0000unse_e4r9",
    "cover": "https://archive.org/services/img/unset0000unse_e4r9"
  },
  {
    "author": "ಎಂ. ಜಿ. ಬರವಣಿ",
    "info": "‌ಈ ಪುಸ್ತಕವನ್ನು  ಸಂಚಿ ಫೌಂಡೇಶನ್ (https://sanchifoundation.org) ಹಾಗೂ ಸಂಚಯದ (https://sanchaya.org) ವತಿಯಿಂದ ಇಂಡಿಯನ್ ಅಕಾಡೆಮಿ ಆಫ್ ಸೈನ್ಸ್ಸ್, ಬೆಂಗಳೂರಿನಲ್ಲಿ ಜ್ಞಾನದ ಸೇವಕರು (Servants Of Knowledge) ಸಮುದಾಯ ಸಹಭಾಗಿತ್ವದ ಕೆಲಸದಡಿಯಲ್ಲಿ ಡಿಜಿಟಲೀಕರಿಸಲಾಗಿರುತ್ತದೆ.",
    "identifier": "unset0000unse_u8n0",
    "title": "ಘಟೋಧ್ಗಜ ಜನ್ಮ ಮತ್ತು ಸಾಹಸೀ ಸಾಂಬ",
    "publisher": "ಎಂ. ಜಿ. ಬರವಣಿ, ಯಕ್ಷಗಾನ ಕಲಾವಿದರು, ಗೋಕರ್ಣ",
    "tags": "",
    "level": "Yakshagana;Yakshagana Prasanga;ಯಕ್ಷಗಾನ;ಯಕ್ಷಗಾನ ಪ್ರಸಂಗ;ಕನ್ನಡ ಸಾಹಿತ್ಯ",
    "authorUrl": "https://archive.org/search.php?query=creator%3Aಎಂ. ಜಿ. ಬರವಣಿ",
    "url": "https://archive.org/details/unset0000unse_u8n0",
    "cover": "https://archive.org/services/img/unset0000unse_u8n0"
  },
  {
    "author": "ಅಮೃತ್ ಸೋಮೇಶ್ವರ",
    "info": "‌ಈ ಪುಸ್ತಕವನ್ನು  ಸಂಚಿ ಫೌಂಡೇಶನ್ (https://sanchifoundation.org) ಹಾಗೂ ಸಂಚಯದ (https://sanchaya.org) ವತಿಯಿಂದ ಇಂಡಿಯನ್ ಅಕಾಡೆಮಿ ಆಫ್ ಸೈನ್ಸ್ಸ್, ಬೆಂಗಳೂರಿನಲ್ಲಿ ಜ್ಞಾನದ ಸೇವಕರು (Servants Of Knowledge) ಸಮುದಾಯ ಸಹಭಾಗಿತ್ವದ ಕೆಲಸದಡಿಯಲ್ಲಿ ಡಿಜಿಟಲೀಕರಿಸಲಾಗಿರುತ್ತದೆ.",
    "identifier": "unset0000unse_t2r4",
    "title": "ಘೋರ ಮಾರಕ",
    "publisher": "ಪ್ರಾಕ್ರಿತಿ ಪ್ರಕಾಶನ",
    "tags": "",
    "level": "Yakshagana;Yakshagana Prasanga;ಯಕ್ಷಗಾನ;ಯಕ್ಷಗಾನ ಪ್ರಸಂಗ;ಕನ್ನಡ ಸಾಹಿತ್ಯ",
    "authorUrl": "https://archive.org/search.php?query=creator%3Aಅಮೃತ್ ಸೋಮೇಶ್ವರ",
    "url": "https://archive.org/details/unset0000unse_t2r4",
    "cover": "https://archive.org/services/img/unset0000unse_t2r4"
  },
  {
    "author": "ಎಂ. ಜಿ. ಬರವಣಿ",
    "info": "‌ಈ ಪುಸ್ತಕವನ್ನು  ಸಂಚಿ ಫೌಂಡೇಶನ್ (https://sanchifoundation.org) ಹಾಗೂ ಸಂಚಯದ (https://sanchaya.org) ವತಿಯಿಂದ ಇಂಡಿಯನ್ ಅಕಾಡೆಮಿ ಆಫ್ ಸೈನ್ಸ್ಸ್, ಬೆಂಗಳೂರಿನಲ್ಲಿ ಜ್ಞಾನದ ಸೇವಕರು (Servants Of Knowledge) ಸಮುದಾಯ ಸಹಭಾಗಿತ್ವದ ಕೆಲಸದಡಿಯಲ್ಲಿ ಡಿಜಿಟಲೀಕರಿಸಲಾಗಿರುತ್ತದೆ.",
    "identifier": "unset0000unse_t1m6",
    "title": "ಚಂದ್ರಮುಖಿ ಸ್ವಯಂವರ",
    "publisher": "Vijaya Vinayaka Yuvaka Sanga, Gokarna",
    "tags": "",
    "level": "Yakshagana;Yakshagana Prasanga;ಯಕ್ಷಗಾನ;ಯಕ್ಷಗಾನ ಪ್ರಸಂಗ;ಕನ್ನಡ ಸಾಹಿತ್ಯ",
    "authorUrl": "https://archive.org/search.php?query=creator%3Aಎಂ. ಜಿ. ಬರವಣಿ",
    "url": "https://archive.org/details/unset0000unse_t1m6",
    "cover": "https://archive.org/services/img/unset0000unse_t1m6"
  },
  {
    "author": "ಎಂ. ಜಿ. ಬರವಣಿ",
    "info": "‌ಈ ಪುಸ್ತಕವನ್ನು  ಸಂಚಿ ಫೌಂಡೇಶನ್ (https://sanchifoundation.org) ಹಾಗೂ ಸಂಚಯದ (https://sanchaya.org) ವತಿಯಿಂದ ಇಂಡಿಯನ್ ಅಕಾಡೆಮಿ ಆಫ್ ಸೈನ್ಸ್ಸ್, ಬೆಂಗಳೂರಿನಲ್ಲಿ ಜ್ಞಾನದ ಸೇವಕರು (Servants Of Knowledge) ಸಮುದಾಯ ಸಹಭಾಗಿತ್ವದ ಕೆಲಸದಡಿಯಲ್ಲಿ ಡಿಜಿಟಲೀಕರಿಸಲಾಗಿರುತ್ತದೆ.",
    "identifier": "unset0000unse_k4x7",
    "title": "ಚಂದ್ರರೇಖಾ ಪರಿಣಯ",
    "publisher": "ಎಂ. ಜಿ. ಬರವಣಿ, ಯಕ್ಷಗಾನ ಕಲಾವಿದರು, ಗೋಕರ್ಣ",
    "tags": "",
    "level": "Yakshagana;Yakshagana Prasanga;ಯಕ್ಷಗಾನ;ಯಕ್ಷಗಾನ ಪ್ರಸಂಗ;ಕನ್ನಡ ಸಾಹಿತ್ಯ",
    "authorUrl": "https://archive.org/search.php?query=creator%3Aಎಂ. ಜಿ. ಬರವಣಿ",
    "url": "https://archive.org/details/unset0000unse_k4x7",
    "cover": "https://archive.org/services/img/unset0000unse_k4x7"
  },
  {
    "author": "ವಾಜಪೇಯಂ, ವಿ ಗೋವಿಂದಯ್ಯ",
    "info": "‌ಈ ಪುಸ್ತಕವನ್ನು  ಸಂಚಿ ಫೌಂಡೇಶನ್ (https://sanchifoundation.org) ಹಾಗೂ ಸಂಚಯದ (https://sanchaya.org) ವತಿಯಿಂದ ಇಂಡಿಯನ್ ಅಕಾಡೆಮಿ ಆಫ್ ಸೈನ್ಸ್ಸ್, ಬೆಂಗಳೂರಿನಲ್ಲಿ ಜ್ಞಾನದ ಸೇವಕರು (Servants Of Knowledge) ಸಮುದಾಯ ಸಹಭಾಗಿತ್ವದ ಕೆಲಸದಡಿಯಲ್ಲಿ ಡಿಜಿಟಲೀಕರಿಸಲಾಗಿರುತ್ತದೆ.",
    "identifier": "unset0000unse_o2o8",
    "title": "ಚಂದ್ರಾವಳೀ ಪ್ರಸಂಗ",
    "publisher": "ಟ್ರೌ ಮುದ್ರಾಕ್ಷರಶಾಲೆ",
    "tags": "",
    "level": "Yakshagana;Yakshagana Prasanga;ಯಕ್ಷಗಾನ;ಯಕ್ಷಗಾನ ಪ್ರಸಂಗ;ಕನ್ನಡ ಸಾಹಿತ್ಯ",
    "authorUrl": "https://archive.org/search.php?query=creator%3Aವಾಜಪೇಯಂ, ವಿ ಗೋವಿಂದಯ್ಯ",
    "url": "https://archive.org/details/unset0000unse_o2o8",
    "cover": "https://archive.org/services/img/unset0000unse_o2o8"
  },
  {
    "author": "ಬಿ. ಪುತ್ತೂರು ನಾರಾಯಣ ಹೆಗ್ಡೆ",
    "info": "‌ಈ ಪುಸ್ತಕವನ್ನು  ಸಂಚಿ ಫೌಂಡೇಶನ್ (https://sanchifoundation.org) ಹಾಗೂ ಸಂಚಯದ (https://sanchaya.org) ವತಿಯಿಂದ ಇಂಡಿಯನ್ ಅಕಾಡೆಮಿ ಆಫ್ ಸೈನ್ಸ್ಸ್, ಬೆಂಗಳೂರಿನಲ್ಲಿ ಜ್ಞಾನದ ಸೇವಕರು (Servants Of Knowledge) ಸಮುದಾಯ ಸಹಭಾಗಿತ್ವದ ಕೆಲಸದಡಿಯಲ್ಲಿ ಡಿಜಿಟಲೀಕರಿಸಲಾಗಿರುತ್ತದೆ.",
    "identifier": "unset0000unse_l7y7",
    "title": "ಚಾಣಾಕ್ಷ ವಿಕ್ರಮ",
    "publisher": "",
    "tags": "",
    "level": "Yakshagana;Yakshagana Prasanga;ಯಕ್ಷಗಾನ;ಯಕ್ಷಗಾನ ಪ್ರಸಂಗ;ಕನ್ನಡ ಸಾಹಿತ್ಯ",
    "authorUrl": "https://archive.org/search.php?query=creator%3Aಬಿ. ಪುತ್ತೂರು ನಾರಾಯಣ ಹೆಗ್ಡೆ",
    "url": "https://archive.org/details/unset0000unse_l7y7",
    "cover": "https://archive.org/services/img/unset0000unse_l7y7"
  },
  {
    "author": "Kumbale Parthisubba",
    "info": "‌ಈ ಪುಸ್ತಕವನ್ನು  ಸಂಚಿ ಫೌಂಡೇಶನ್ (https://sanchifoundation.org) ಹಾಗೂ ಸಂಚಯದ (https://sanchaya.org) ವತಿಯಿಂದ ಇಂಡಿಯನ್ ಅಕಾಡೆಮಿ ಆಫ್ ಸೈನ್ಸ್ಸ್, ಬೆಂಗಳೂರಿನಲ್ಲಿ ಜ್ಞಾನದ ಸೇವಕರು (Servants Of Knowledge) ಸಮುದಾಯ ಸಹಭಾಗಿತ್ವದ ಕೆಲಸದಡಿಯಲ್ಲಿ ಡಿಜಿಟಲೀಕರಿಸಲಾಗಿರುತ್ತದೆ.",
    "identifier": "unset0000unse_j9g3",
    "title": "ಚೂಡಾಮಣಿ ಪ್ರಸಂಗ",
    "publisher": "ನಿತ್ಯಾನಂದ ಗ್ರಂಥಾಲಯ",
    "tags": "",
    "level": "Yakshagana;Yakshagana Prasanga;ಯಕ್ಷಗಾನ;ಯಕ್ಷಗಾನ ಪ್ರಸಂಗ;ಕನ್ನಡ ಸಾಹಿತ್ಯ",
    "authorUrl": "https://archive.org/search.php?query=creator%3AKumbale Parthisubba",
    "url": "https://archive.org/details/unset0000unse_j9g3",
    "cover": "https://archive.org/services/img/unset0000unse_j9g3"
  },
  {
    "author": "Gavananda Kerodi Sujarao",
    "info": "‌ಈ ಪುಸ್ತಕವನ್ನು  ಸಂಚಿ ಫೌಂಡೇಶನ್ (https://sanchifoundation.org) ಹಾಗೂ ಸಂಚಯದ (https://sanchaya.org) ವತಿಯಿಂದ ಇಂಡಿಯನ್ ಅಕಾಡೆಮಿ ಆಫ್ ಸೈನ್ಸ್ಸ್, ಬೆಂಗಳೂರಿನಲ್ಲಿ ಜ್ಞಾನದ ಸೇವಕರು (Servants Of Knowledge) ಸಮುದಾಯ ಸಹಭಾಗಿತ್ವದ ಕೆಲಸದಡಿಯಲ್ಲಿ ಡಿಜಿಟಲೀಕರಿಸಲಾಗಿರುತ್ತದೆ.",
    "identifier": "unset0000unse_a8z7",
    "title": "ಜರಾಸಂಧ ವಧೆ",
    "publisher": "ಪಾವಂಜೆ ಗುರುರಾವ್",
    "tags": "",
    "level": "Yakshagana;Yakshagana Prasanga;ಯಕ್ಷಗಾನ;ಯಕ್ಷಗಾನ ಪ್ರಸಂಗ;ಕನ್ನಡ ಸಾಹಿತ್ಯ",
    "authorUrl": "https://archive.org/search.php?query=creator%3AGavananda Kerodi Sujarao",
    "url": "https://archive.org/details/unset0000unse_a8z7",
    "cover": "https://archive.org/services/img/unset0000unse_a8z7"
  },
  {
    "author": "",
    "info": "‌ಈ ಪುಸ್ತಕವನ್ನು  ಸಂಚಿ ಫೌಂಡೇಶನ್ (https://sanchifoundation.org) ಹಾಗೂ ಸಂಚಯದ (https://sanchaya.org) ವತಿಯಿಂದ ಇಂಡಿಯನ್ ಅಕಾಡೆಮಿ ಆಫ್ ಸೈನ್ಸ್ಸ್, ಬೆಂಗಳೂರಿನಲ್ಲಿ ಜ್ಞಾನದ ಸೇವಕರು (Servants Of Knowledge) ಸಮುದಾಯ ಸಹಭಾಗಿತ್ವದ ಕೆಲಸದಡಿಯಲ್ಲಿ ಡಿಜಿಟಲೀಕರಿಸಲಾಗಿರುತ್ತದೆ.",
    "identifier": "unset0000unse_t0x4",
    "title": "ಜಲಂಧರನ ಕಾಳಗ",
    "publisher": "",
    "tags": "",
    "level": "Yakshagana;Yakshagana Prasanga;ಯಕ್ಷಗಾನ;ಯಕ್ಷಗಾನ ಪ್ರಸಂಗ;ಕನ್ನಡ ಸಾಹಿತ್ಯ",
    "authorUrl": "https://archive.org/search.php?query=creator%3A",
    "url": "https://archive.org/details/unset0000unse_t0x4",
    "cover": "https://archive.org/services/img/unset0000unse_t0x4"
  },
  {
    "author": "ಶ್ರೀ ಆಲೆಟ್ಟಿ ರಾಮಣ್ಣ ಶಗ್ರಿತ್ತಾಯರು",
    "info": "‌ಈ ಪುಸ್ತಕವನ್ನು  ಸಂಚಿ ಫೌಂಡೇಶನ್ (https://sanchifoundation.org) ಹಾಗೂ ಸಂಚಯದ (https://sanchaya.org) ವತಿಯಿಂದ ಇಂಡಿಯನ್ ಅಕಾಡೆಮಿ ಆಫ್ ಸೈನ್ಸ್ಸ್, ಬೆಂಗಳೂರಿನಲ್ಲಿ ಜ್ಞಾನದ ಸೇವಕರು (Servants Of Knowledge) ಸಮುದಾಯ ಸಹಭಾಗಿತ್ವದ ಕೆಲಸದಡಿಯಲ್ಲಿ ಡಿಜಿಟಲೀಕರಿಸಲಾಗಿರುತ್ತದೆ.",
    "identifier": "unset0000unse_f4d3",
    "title": "ತರಣಿಸೇನಾಕಾಳಗ",
    "publisher": "ಪಾವಂಜೆ ಗುರುರಾವ್ & ಸನ್ಸ್",
    "tags": "",
    "level": "Yakshagana;Yakshagana Prasanga;ಯಕ್ಷಗಾನ;ಯಕ್ಷಗಾನ ಪ್ರಸಂಗ;ಕನ್ನಡ ಸಾಹಿತ್ಯ",
    "authorUrl": "https://archive.org/search.php?query=creator%3Aಶ್ರೀ ಆಲೆಟ್ಟಿ ರಾಮಣ್ಣ ಶಗ್ರಿತ್ತಾಯರು",
    "url": "https://archive.org/details/unset0000unse_f4d3",
    "cover": "https://archive.org/services/img/unset0000unse_f4d3"
  },
  {
    "author": "Pavanje",
    "info": "‌ಈ ಪುಸ್ತಕವನ್ನು  ಸಂಚಿ ಫೌಂಡೇಶನ್ (https://sanchifoundation.org) ಹಾಗೂ ಸಂಚಯದ (https://sanchaya.org) ವತಿಯಿಂದ ಇಂಡಿಯನ್ ಅಕಾಡೆಮಿ ಆಫ್ ಸೈನ್ಸ್ಸ್, ಬೆಂಗಳೂರಿನಲ್ಲಿ ಜ್ಞಾನದ ಸೇವಕರು (Servants Of Knowledge) ಸಮುದಾಯ ಸಹಭಾಗಿತ್ವದ ಕೆಲಸದಡಿಯಲ್ಲಿ ಡಿಜಿಟಲೀಕರಿಸಲಾಗಿರುತ್ತದೆ.",
    "identifier": "unset0000unse_b9q5",
    "title": "ತಾಮ್ರಧ್ವಜನ ಕಾಳಗ",
    "publisher": "ಪಾವಂಜೆ ಗುರುರಾವ್ & ಸನ್ಸ್",
    "tags": "",
    "level": "Yakshagana;Yakshagana Prasanga;ಯಕ್ಷಗಾನ;ಯಕ್ಷಗಾನ ಪ್ರಸಂಗ;ಕನ್ನಡ ಸಾಹಿತ್ಯ",
    "authorUrl": "https://archive.org/search.php?query=creator%3APavanje",
    "url": "https://archive.org/details/unset0000unse_b9q5",
    "cover": "https://archive.org/services/img/unset0000unse_b9q5"
  },
  {
    "author": "ಎಂ. ಜಿ. ಬರವಣಿ",
    "info": "‌ಈ ಪುಸ್ತಕವನ್ನು  ಸಂಚಿ ಫೌಂಡೇಶನ್ (https://sanchifoundation.org) ಹಾಗೂ ಸಂಚಯದ (https://sanchaya.org) ವತಿಯಿಂದ ಇಂಡಿಯನ್ ಅಕಾಡೆಮಿ ಆಫ್ ಸೈನ್ಸ್ಸ್, ಬೆಂಗಳೂರಿನಲ್ಲಿ ಜ್ಞಾನದ ಸೇವಕರು (Servants Of Knowledge) ಸಮುದಾಯ ಸಹಭಾಗಿತ್ವದ ಕೆಲಸದಡಿಯಲ್ಲಿ ಡಿಜಿಟಲೀಕರಿಸಲಾಗಿರುತ್ತದೆ.",
    "identifier": "unset0000unse_u7a6",
    "title": "ತ್ರಿಪದ ದಾನ",
    "publisher": "ಎಂ. ಜಿ. ಬರವಣಿ, ಯಕ್ಷಗಾನ ಕಲಾವಿದರು, ಗೋಕರ್ಣ",
    "tags": "",
    "level": "Yakshagana;Yakshagana Prasanga;ಯಕ್ಷಗಾನ;ಯಕ್ಷಗಾನ ಪ್ರಸಂಗ;ಕನ್ನಡ ಸಾಹಿತ್ಯ",
    "authorUrl": "https://archive.org/search.php?query=creator%3Aಎಂ. ಜಿ. ಬರವಣಿ",
    "url": "https://archive.org/details/unset0000unse_u7a6",
    "cover": "https://archive.org/services/img/unset0000unse_u7a6"
  },
  {
    "author": "Rajesh",
    "info": "‌ಈ ಪುಸ್ತಕವನ್ನು  ಸಂಚಿ ಫೌಂಡೇಶನ್ (https://sanchifoundation.org) ಹಾಗೂ ಸಂಚಯದ (https://sanchaya.org) ವತಿಯಿಂದ ಇಂಡಿಯನ್ ಅಕಾಡೆಮಿ ಆಫ್ ಸೈನ್ಸ್ಸ್, ಬೆಂಗಳೂರಿನಲ್ಲಿ ಜ್ಞಾನದ ಸೇವಕರು (Servants Of Knowledge) ಸಮುದಾಯ ಸಹಭಾಗಿತ್ವದ ಕೆಲಸದಡಿಯಲ್ಲಿ ಡಿಜಿಟಲೀಕರಿಸಲಾಗಿರುತ್ತದೆ.",
    "identifier": "unset0000unse_a3z8",
    "title": "ದಾನಾಸುರ ಕರ್ಣ",
    "publisher": "ಆರ್. ವೆಂಕಟಪ್ಪ ಶಣೈ & ಸನ್ಸ್",
    "tags": "",
    "level": "Yakshagana;Yakshagana Prasanga;ಯಕ್ಷಗಾನ;ಯಕ್ಷಗಾನ ಪ್ರಸಂಗ;ಕನ್ನಡ ಸಾಹಿತ್ಯ",
    "authorUrl": "https://archive.org/search.php?query=creator%3ARajesh",
    "url": "https://archive.org/details/unset0000unse_a3z8",
    "cover": "https://archive.org/services/img/unset0000unse_a3z8"
  },
  {
    "author": "",
    "info": "‌ಈ ಪುಸ್ತಕವನ್ನು  ಸಂಚಿ ಫೌಂಡೇಶನ್ (https://sanchifoundation.org) ಹಾಗೂ ಸಂಚಯದ (https://sanchaya.org) ವತಿಯಿಂದ ಇಂಡಿಯನ್ ಅಕಾಡೆಮಿ ಆಫ್ ಸೈನ್ಸ್ಸ್, ಬೆಂಗಳೂರಿನಲ್ಲಿ ಜ್ಞಾನದ ಸೇವಕರು (Servants Of Knowledge) ಸಮುದಾಯ ಸಹಭಾಗಿತ್ವದ ಕೆಲಸದಡಿಯಲ್ಲಿ ಡಿಜಿಟಲೀಕರಿಸಲಾಗಿರುತ್ತದೆ.",
    "identifier": "unset0000unse_t9c4",
    "title": "ದ್ರೌಪತಿ ಪ್ರತಾಪ",
    "publisher": "ಪಾವಂಜೆ ಗುರುರಾವ್",
    "tags": "",
    "level": "Yakshagana;Yakshagana Prasanga;ಯಕ್ಷಗಾನ;ಯಕ್ಷಗಾನ ಪ್ರಸಂಗ;ಕನ್ನಡ ಸಾಹಿತ್ಯ",
    "authorUrl": "https://archive.org/search.php?query=creator%3A",
    "url": "https://archive.org/details/unset0000unse_t9c4",
    "cover": "https://archive.org/services/img/unset0000unse_t9c4"
  },
  {
    "author": "ಡಿ. ವಿ. ಹೊಳ್ಳ, ವಿದ್ವಾನ್",
    "info": "‌ಈ ಪುಸ್ತಕವನ್ನು  ಸಂಚಿ ಫೌಂಡೇಶನ್ (https://sanchifoundation.org) ಹಾಗೂ ಸಂಚಯದ (https://sanchaya.org) ವತಿಯಿಂದ ಇಂಡಿಯನ್ ಅಕಾಡೆಮಿ ಆಫ್ ಸೈನ್ಸ್ಸ್, ಬೆಂಗಳೂರಿನಲ್ಲಿ ಜ್ಞಾನದ ಸೇವಕರು (Servants Of Knowledge) ಸಮುದಾಯ ಸಹಭಾಗಿತ್ವದ ಕೆಲಸದಡಿಯಲ್ಲಿ ಡಿಜಿಟಲೀಕರಿಸಲಾಗಿರುತ್ತದೆ.",
    "identifier": "unset0000unse_f5o6",
    "title": "ದ್ರೌಪದಿ ವಸ್ತ್ರಾಪಹಾರ",
    "publisher": "ಪಾವಂಜೆ ಗುರುರಾವ್",
    "tags": "",
    "level": "Yakshagana;Yakshagana Prasanga;ಯಕ್ಷಗಾನ;ಯಕ್ಷಗಾನ ಪ್ರಸಂಗ;ಕನ್ನಡ ಸಾಹಿತ್ಯ",
    "authorUrl": "https://archive.org/search.php?query=creator%3Aಡಿ. ವಿ. ಹೊಳ್ಳ, ವಿದ್ವಾನ್",
    "url": "https://archive.org/details/unset0000unse_f5o6",
    "cover": "https://archive.org/services/img/unset0000unse_f5o6"
  },
  {
    "author": "ವಾಜಪೇಯಂ, ವಿ ಗೋವಿಂದಯ್ಯ",
    "info": "‌ಈ ಪುಸ್ತಕವನ್ನು  ಸಂಚಿ ಫೌಂಡೇಶನ್ (https://sanchifoundation.org) ಹಾಗೂ ಸಂಚಯದ (https://sanchaya.org) ವತಿಯಿಂದ ಇಂಡಿಯನ್ ಅಕಾಡೆಮಿ ಆಫ್ ಸೈನ್ಸ್ಸ್, ಬೆಂಗಳೂರಿನಲ್ಲಿ ಜ್ಞಾನದ ಸೇವಕರು (Servants Of Knowledge) ಸಮುದಾಯ ಸಹಭಾಗಿತ್ವದ ಕೆಲಸದಡಿಯಲ್ಲಿ ಡಿಜಿಟಲೀಕರಿಸಲಾಗಿರುತ್ತದೆ.",
    "identifier": "unset0000unse_a6i1",
    "title": "ದ್ರೌಪದಿ ಸ್ವಯಂವರ",
    "publisher": "Sri Chowdeshwari Mudrakshara Shale",
    "tags": "",
    "level": "Yakshagana;Yakshagana Prasanga;ಯಕ್ಷಗಾನ;ಯಕ್ಷಗಾನ ಪ್ರಸಂಗ;ಕನ್ನಡ ಸಾಹಿತ್ಯ",
    "authorUrl": "https://archive.org/search.php?query=creator%3Aವಾಜಪೇಯಂ, ವಿ ಗೋವಿಂದಯ್ಯ",
    "url": "https://archive.org/details/unset0000unse_a6i1",
    "cover": "https://archive.org/services/img/unset0000unse_a6i1"
  },
  {
    "author": "Lakshminarayana Upadhya",
    "info": "‌ಈ ಪುಸ್ತಕವನ್ನು  ಸಂಚಿ ಫೌಂಡೇಶನ್ (https://sanchifoundation.org) ಹಾಗೂ ಸಂಚಯದ (https://sanchaya.org) ವತಿಯಿಂದ ಇಂಡಿಯನ್ ಅಕಾಡೆಮಿ ಆಫ್ ಸೈನ್ಸ್ಸ್, ಬೆಂಗಳೂರಿನಲ್ಲಿ ಜ್ಞಾನದ ಸೇವಕರು (Servants Of Knowledge) ಸಮುದಾಯ ಸಹಭಾಗಿತ್ವದ ಕೆಲಸದಡಿಯಲ್ಲಿ ಡಿಜಿಟಲೀಕರಿಸಲಾಗಿರುತ್ತದೆ.",
    "identifier": "unset0000unse_b4e6",
    "title": "ಧರಣಿಮೋಹಿನಿ ಕಲ್ಯಾಣ ಎಂಬ ಭಟ್ಟಿ ವಿಕ್ರಮಾರ್ಕ ಚರಿತ್ರೆ",
    "publisher": "Kudapura Lakshminarashima Mudra Shale",
    "tags": "",
    "level": "Yakshagana;Yakshagana Prasanga;ಯಕ್ಷಗಾನ;ಯಕ್ಷಗಾನ ಪ್ರಸಂಗ;ಕನ್ನಡ ಸಾಹಿತ್ಯ",
    "authorUrl": "https://archive.org/search.php?query=creator%3ALakshminarayana Upadhya",
    "url": "https://archive.org/details/unset0000unse_b4e6",
    "cover": "https://archive.org/services/img/unset0000unse_b4e6"
  },
  {
    "author": "ಎಂ. ಜಿ. ಬರವಣಿ",
    "info": "‌ಈ ಪುಸ್ತಕವನ್ನು  ಸಂಚಿ ಫೌಂಡೇಶನ್ (https://sanchifoundation.org) ಹಾಗೂ ಸಂಚಯದ (https://sanchaya.org) ವತಿಯಿಂದ ಇಂಡಿಯನ್ ಅಕಾಡೆಮಿ ಆಫ್ ಸೈನ್ಸ್ಸ್, ಬೆಂಗಳೂರಿನಲ್ಲಿ ಜ್ಞಾನದ ಸೇವಕರು (Servants Of Knowledge) ಸಮುದಾಯ ಸಹಭಾಗಿತ್ವದ ಕೆಲಸದಡಿಯಲ್ಲಿ ಡಿಜಿಟಲೀಕರಿಸಲಾಗಿರುತ್ತದೆ.",
    "identifier": "unset0000unse_i9b7",
    "title": "ಧೃವ ದಿಗ್ವಿಜಯ",
    "publisher": "ಎಂ. ಜಿ. ಬರವಣಿ, ಯಕ್ಷಗಾನ ಕಲಾವಿದರು, ಗೋಕರ್ಣ",
    "tags": "",
    "level": "Yakshagana;Yakshagana Prasanga;ಯಕ್ಷಗಾನ;ಯಕ್ಷಗಾನ ಪ್ರಸಂಗ;ಕನ್ನಡ ಸಾಹಿತ್ಯ",
    "authorUrl": "https://archive.org/search.php?query=creator%3Aಎಂ. ಜಿ. ಬರವಣಿ",
    "url": "https://archive.org/details/unset0000unse_i9b7",
    "cover": "https://archive.org/services/img/unset0000unse_i9b7"
  },
  {
    "author": "ಚಿ. ಬಲಿಪ ನಾರಾಯಣ ಭಾಗವತ",
    "info": "‌ಈ ಪುಸ್ತಕವನ್ನು  ಸಂಚಿ ಫೌಂಡೇಶನ್ (https://sanchifoundation.org) ಹಾಗೂ ಸಂಚಯದ (https://sanchaya.org) ವತಿಯಿಂದ ಇಂಡಿಯನ್ ಅಕಾಡೆಮಿ ಆಫ್ ಸೈನ್ಸ್ಸ್, ಬೆಂಗಳೂರಿನಲ್ಲಿ ಜ್ಞಾನದ ಸೇವಕರು (Servants Of Knowledge) ಸಮುದಾಯ ಸಹಭಾಗಿತ್ವದ ಕೆಲಸದಡಿಯಲ್ಲಿ ಡಿಜಿಟಲೀಕರಿಸಲಾಗಿರುತ್ತದೆ.",
    "identifier": "unset0000unse_x7i6",
    "title": "ನಟಚರಿತ್ರೆ ಅಥವಾ ಆಟದೊಳಗಣ ಆಟ",
    "publisher": "ಚಿ. ಬಲಿಪ ನಾರಾಯಣ ಭಾಗವತ",
    "tags": "",
    "level": "Yakshagana;Yakshagana Prasanga;ಯಕ್ಷಗಾನ;ಯಕ್ಷಗಾನ ಪ್ರಸಂಗ;ಕನ್ನಡ ಸಾಹಿತ್ಯ",
    "authorUrl": "https://archive.org/search.php?query=creator%3Aಚಿ. ಬಲಿಪ ನಾರಾಯಣ ಭಾಗವತ",
    "url": "https://archive.org/details/unset0000unse_x7i6",
    "cover": "https://archive.org/services/img/unset0000unse_x7i6"
  },
  {
    "author": "Hebrri Kandiga Padmanabha Janne",
    "info": "‌ಈ ಪುಸ್ತಕವನ್ನು  ಸಂಚಿ ಫೌಂಡೇಶನ್ (https://sanchifoundation.org) ಹಾಗೂ ಸಂಚಯದ (https://sanchaya.org) ವತಿಯಿಂದ ಇಂಡಿಯನ್ ಅಕಾಡೆಮಿ ಆಫ್ ಸೈನ್ಸ್ಸ್, ಬೆಂಗಳೂರಿನಲ್ಲಿ ಜ್ಞಾನದ ಸೇವಕರು (Servants Of Knowledge) ಸಮುದಾಯ ಸಹಭಾಗಿತ್ವದ ಕೆಲಸದಡಿಯಲ್ಲಿ ಡಿಜಿಟಲೀಕರಿಸಲಾಗಿರುತ್ತದೆ.",
    "identifier": "unset0000unse_r4o5",
    "title": "ನಾರದ ಪ್ರತಾಪ",
    "publisher": "Udupi Mejestic Press",
    "tags": "",
    "level": "Yakshagana;Yakshagana Prasanga;ಯಕ್ಷಗಾನ;ಯಕ್ಷಗಾನ ಪ್ರಸಂಗ;ಕನ್ನಡ ಸಾಹಿತ್ಯ",
    "authorUrl": "https://archive.org/search.php?query=creator%3AHebrri Kandiga Padmanabha Janne",
    "url": "https://archive.org/details/unset0000unse_r4o5",
    "cover": "https://archive.org/services/img/unset0000unse_r4o5"
  },
  {
    "author": "Hostotta Manjunatha Bhatta",
    "info": "‌ಈ ಪುಸ್ತಕವನ್ನು  ಸಂಚಿ ಫೌಂಡೇಶನ್ (https://sanchifoundation.org) ಹಾಗೂ ಸಂಚಯದ (https://sanchaya.org) ವತಿಯಿಂದ ಇಂಡಿಯನ್ ಅಕಾಡೆಮಿ ಆಫ್ ಸೈನ್ಸ್ಸ್, ಬೆಂಗಳೂರಿನಲ್ಲಿ ಜ್ಞಾನದ ಸೇವಕರು (Servants Of Knowledge) ಸಮುದಾಯ ಸಹಭಾಗಿತ್ವದ ಕೆಲಸದಡಿಯಲ್ಲಿ ಡಿಜಿಟಲೀಕರಿಸಲಾಗಿರುತ್ತದೆ.",
    "identifier": "unset0000unse_a0n5",
    "title": "ನಿಸರ್ಗ ಸಂಧಾನ",
    "publisher": "Shayadri Parisaravardhini",
    "tags": "",
    "level": "Yakshagana;Yakshagana Prasanga;ಯಕ್ಷಗಾನ;ಯಕ್ಷಗಾನ ಪ್ರಸಂಗ;ಕನ್ನಡ ಸಾಹಿತ್ಯ",
    "authorUrl": "https://archive.org/search.php?query=creator%3AHostotta Manjunatha Bhatta",
    "url": "https://archive.org/details/unset0000unse_a0n5",
    "cover": "https://archive.org/services/img/unset0000unse_a0n5"
  },
  {
    "author": "",
    "info": "‌ಈ ಪುಸ್ತಕವನ್ನು  ಸಂಚಿ ಫೌಂಡೇಶನ್ (https://sanchifoundation.org) ಹಾಗೂ ಸಂಚಯದ (https://sanchaya.org) ವತಿಯಿಂದ ಇಂಡಿಯನ್ ಅಕಾಡೆಮಿ ಆಫ್ ಸೈನ್ಸ್ಸ್, ಬೆಂಗಳೂರಿನಲ್ಲಿ ಜ್ಞಾನದ ಸೇವಕರು (Servants Of Knowledge) ಸಮುದಾಯ ಸಹಭಾಗಿತ್ವದ ಕೆಲಸದಡಿಯಲ್ಲಿ ಡಿಜಿಟಲೀಕರಿಸಲಾಗಿರುತ್ತದೆ.",
    "identifier": "unset0000unse_c3y3",
    "title": "ನೀಲ ಧ್ವಜ ಕಾಳಗ",
    "publisher": "ಪಾವಂಜೆ ಗುರುರಾವ್",
    "tags": "",
    "level": "Yakshagana;Yakshagana Prasanga;ಯಕ್ಷಗಾನ;ಯಕ್ಷಗಾನ ಪ್ರಸಂಗ;ಕನ್ನಡ ಸಾಹಿತ್ಯ",
    "authorUrl": "https://archive.org/search.php?query=creator%3A",
    "url": "https://archive.org/details/unset0000unse_c3y3",
    "cover": "https://archive.org/services/img/unset0000unse_c3y3"
  },
  {
    "author": "",
    "info": "‌ಈ ಪುಸ್ತಕವನ್ನು  ಸಂಚಿ ಫೌಂಡೇಶನ್ (https://sanchifoundation.org) ಹಾಗೂ ಸಂಚಯದ (https://sanchaya.org) ವತಿಯಿಂದ ಇಂಡಿಯನ್ ಅಕಾಡೆಮಿ ಆಫ್ ಸೈನ್ಸ್ಸ್, ಬೆಂಗಳೂರಿನಲ್ಲಿ ಜ್ಞಾನದ ಸೇವಕರು (Servants Of Knowledge) ಸಮುದಾಯ ಸಹಭಾಗಿತ್ವದ ಕೆಲಸದಡಿಯಲ್ಲಿ ಡಿಜಿಟಲೀಕರಿಸಲಾಗಿರುತ್ತದೆ.",
    "identifier": "unset0000unse_o3q4",
    "title": "ಪದ್ಮಾವತಿ ಕಲ್ಯಾಣವು",
    "publisher": "ಪಾವಂಜೆ ಗುರುರಾವ್",
    "tags": "",
    "level": "Yakshagana;Yakshagana Prasanga;ಯಕ್ಷಗಾನ;ಯಕ್ಷಗಾನ ಪ್ರಸಂಗ;ಕನ್ನಡ ಸಾಹಿತ್ಯ",
    "authorUrl": "https://archive.org/search.php?query=creator%3A",
    "url": "https://archive.org/details/unset0000unse_o3q4",
    "cover": "https://archive.org/services/img/unset0000unse_o3q4"
  },
  {
    "author": "ಕೀರಿಕ್ಕಾಡು ಮಾಸ್ತರ್ ವಿಷ್ಣು ಭಟ್",
    "info": "‌ಈ ಪುಸ್ತಕವನ್ನು  ಸಂಚಿ ಫೌಂಡೇಶನ್ (https://sanchifoundation.org) ಹಾಗೂ ಸಂಚಯದ (https://sanchaya.org) ವತಿಯಿಂದ ಇಂಡಿಯನ್ ಅಕಾಡೆಮಿ ಆಫ್ ಸೈನ್ಸ್ಸ್, ಬೆಂಗಳೂರಿನಲ್ಲಿ ಜ್ಞಾನದ ಸೇವಕರು (Servants Of Knowledge) ಸಮುದಾಯ ಸಹಭಾಗಿತ್ವದ ಕೆಲಸದಡಿಯಲ್ಲಿ ಡಿಜಿಟಲೀಕರಿಸಲಾಗಿರುತ್ತದೆ.",
    "identifier": "unset0000unse_h9l3",
    "title": "ಪಾಂಚಜನ್ಯ",
    "publisher": "ಶ್ರೀ ಗೋಪಾಲಕೃಷ್ಣ ಪ್ರಕಾಶನ",
    "tags": "",
    "level": "Yakshagana;Yakshagana Prasanga;ಯಕ್ಷಗಾನ;ಯಕ್ಷಗಾನ ಪ್ರಸಂಗ;ಕನ್ನಡ ಸಾಹಿತ್ಯ",
    "authorUrl": "https://archive.org/search.php?query=creator%3Aಕೀರಿಕ್ಕಾಡು ಮಾಸ್ತರ್ ವಿಷ್ಣು ಭಟ್",
    "url": "https://archive.org/details/unset0000unse_h9l3",
    "cover": "https://archive.org/services/img/unset0000unse_h9l3"
  },
  {
    "author": "Kukkila Krishna Bhatta",
    "info": "‌ಈ ಪುಸ್ತಕವನ್ನು  ಸಂಚಿ ಫೌಂಡೇಶನ್ (https://sanchifoundation.org) ಹಾಗೂ ಸಂಚಯದ (https://sanchaya.org) ವತಿಯಿಂದ ಇಂಡಿಯನ್ ಅಕಾಡೆಮಿ ಆಫ್ ಸೈನ್ಸ್ಸ್, ಬೆಂಗಳೂರಿನಲ್ಲಿ ಜ್ಞಾನದ ಸೇವಕರು (Servants Of Knowledge) ಸಮುದಾಯ ಸಹಭಾಗಿತ್ವದ ಕೆಲಸದಡಿಯಲ್ಲಿ ಡಿಜಿಟಲೀಕರಿಸಲಾಗಿರುತ್ತದೆ.",
    "identifier": "unset0000unse_d0v4",
    "title": "ಪಾರ್ತಿಸುಬ್ಬನ ಯಕ್ಷಗಾನಗಳು",
    "publisher": "The Institute Of Kannada Studies, University Of Mysore",
    "tags": "",
    "level": "Yakshagana;Yakshagana Prasanga;ಯಕ್ಷಗಾನ;ಯಕ್ಷಗಾನ ಪ್ರಸಂಗ;ಕನ್ನಡ ಸಾಹಿತ್ಯ",
    "authorUrl": "https://archive.org/search.php?query=creator%3AKukkila Krishna Bhatta",
    "url": "https://archive.org/details/unset0000unse_d0v4",
    "cover": "https://archive.org/services/img/unset0000unse_d0v4"
  },
  {
    "author": "Vajapehi Krishnaya",
    "info": "‌ಈ ಪುಸ್ತಕವನ್ನು  ಸಂಚಿ ಫೌಂಡೇಶನ್ (https://sanchifoundation.org) ಹಾಗೂ ಸಂಚಯದ (https://sanchaya.org) ವತಿಯಿಂದ ಇಂಡಿಯನ್ ಅಕಾಡೆಮಿ ಆಫ್ ಸೈನ್ಸ್ಸ್, ಬೆಂಗಳೂರಿನಲ್ಲಿ ಜ್ಞಾನದ ಸೇವಕರು (Servants Of Knowledge) ಸಮುದಾಯ ಸಹಭಾಗಿತ್ವದ ಕೆಲಸದಡಿಯಲ್ಲಿ ಡಿಜಿಟಲೀಕರಿಸಲಾಗಿರುತ್ತದೆ.",
    "identifier": "unset0000unse_j4u0",
    "title": "ಪುತ್ರಕಾಮೇಷ್ಟಿ",
    "publisher": "Bengalore Depo Mudrakshara Shale",
    "tags": "",
    "level": "Yakshagana;Yakshagana Prasanga;ಯಕ್ಷಗಾನ;ಯಕ್ಷಗಾನ ಪ್ರಸಂಗ;ಕನ್ನಡ ಸಾಹಿತ್ಯ",
    "authorUrl": "https://archive.org/search.php?query=creator%3AVajapehi Krishnaya",
    "url": "https://archive.org/details/unset0000unse_j4u0",
    "cover": "https://archive.org/services/img/unset0000unse_j4u0"
  },
  {
    "author": "",
    "info": "‌ಈ ಪುಸ್ತಕವನ್ನು  ಸಂಚಿ ಫೌಂಡೇಶನ್ (https://sanchifoundation.org) ಹಾಗೂ ಸಂಚಯದ (https://sanchaya.org) ವತಿಯಿಂದ ಇಂಡಿಯನ್ ಅಕಾಡೆಮಿ ಆಫ್ ಸೈನ್ಸ್ಸ್, ಬೆಂಗಳೂರಿನಲ್ಲಿ ಜ್ಞಾನದ ಸೇವಕರು (Servants Of Knowledge) ಸಮುದಾಯ ಸಹಭಾಗಿತ್ವದ ಕೆಲಸದಡಿಯಲ್ಲಿ ಡಿಜಿಟಲೀಕರಿಸಲಾಗಿರುತ್ತದೆ.",
    "identifier": "unset0000unse_u1x9",
    "title": "ಬಬ್ರುವಾಹನ ಕಾಳಗವು",
    "publisher": "",
    "tags": "",
    "level": "Yakshagana;Yakshagana Prasanga;ಯಕ್ಷಗಾನ;ಯಕ್ಷಗಾನ ಪ್ರಸಂಗ;ಕನ್ನಡ ಸಾಹಿತ್ಯ",
    "authorUrl": "https://archive.org/search.php?query=creator%3A",
    "url": "https://archive.org/details/unset0000unse_u1x9",
    "cover": "https://archive.org/services/img/unset0000unse_u1x9"
  },
  {
    "author": "Sri Kanyana Venkataramana Bhataru",
    "info": "‌ಈ ಪುಸ್ತಕವನ್ನು  ಸಂಚಿ ಫೌಂಡೇಶನ್ (https://sanchifoundation.org) ಹಾಗೂ ಸಂಚಯದ (https://sanchaya.org) ವತಿಯಿಂದ ಇಂಡಿಯನ್ ಅಕಾಡೆಮಿ ಆಫ್ ಸೈನ್ಸ್ಸ್, ಬೆಂಗಳೂರಿನಲ್ಲಿ ಜ್ಞಾನದ ಸೇವಕರು (Servants Of Knowledge) ಸಮುದಾಯ ಸಹಭಾಗಿತ್ವದ ಕೆಲಸದಡಿಯಲ್ಲಿ ಡಿಜಿಟಲೀಕರಿಸಲಾಗಿರುತ್ತದೆ.",
    "identifier": "unset0000unse_v2b3",
    "title": "ಬಸ್ಮಾಸುರ ಮೋಹಿನಿ",
    "publisher": "ಪಾವಂಜೆ ಗುರುರಾವ್",
    "tags": "",
    "level": "Yakshagana;Yakshagana Prasanga;ಯಕ್ಷಗಾನ;ಯಕ್ಷಗಾನ ಪ್ರಸಂಗ;ಕನ್ನಡ ಸಾಹಿತ್ಯ",
    "authorUrl": "https://archive.org/search.php?query=creator%3ASri Kanyana Venkataramana Bhataru",
    "url": "https://archive.org/details/unset0000unse_v2b3",
    "cover": "https://archive.org/services/img/unset0000unse_v2b3"
  },
  {
    "author": "",
    "info": "‌ಈ ಪುಸ್ತಕವನ್ನು  ಸಂಚಿ ಫೌಂಡೇಶನ್ (https://sanchifoundation.org) ಹಾಗೂ ಸಂಚಯದ (https://sanchaya.org) ವತಿಯಿಂದ ಇಂಡಿಯನ್ ಅಕಾಡೆಮಿ ಆಫ್ ಸೈನ್ಸ್ಸ್, ಬೆಂಗಳೂರಿನಲ್ಲಿ ಜ್ಞಾನದ ಸೇವಕರು (Servants Of Knowledge) ಸಮುದಾಯ ಸಹಭಾಗಿತ್ವದ ಕೆಲಸದಡಿಯಲ್ಲಿ ಡಿಜಿಟಲೀಕರಿಸಲಾಗಿರುತ್ತದೆ.",
    "identifier": "unset0000unse_y8n2",
    "title": "ಬಾಣಾಸುರನ ಕಾಳಗ",
    "publisher": "ಪಾವಂಜೆ ಗುರುರಾವ್",
    "tags": "",
    "level": "Yakshagana;Yakshagana Prasanga;ಯಕ್ಷಗಾನ;ಯಕ್ಷಗಾನ ಪ್ರಸಂಗ;ಕನ್ನಡ ಸಾಹಿತ್ಯ",
    "authorUrl": "https://archive.org/search.php?query=creator%3A",
    "url": "https://archive.org/details/unset0000unse_y8n2",
    "cover": "https://archive.org/services/img/unset0000unse_y8n2"
  },
  {
    "author": "K. N. Eshwar Bhat",
    "info": "‌ಈ ಪುಸ್ತಕವನ್ನು  ಸಂಚಿ ಫೌಂಡೇಶನ್ (https://sanchifoundation.org) ಹಾಗೂ ಸಂಚಯದ (https://sanchaya.org) ವತಿಯಿಂದ ಇಂಡಿಯನ್ ಅಕಾಡೆಮಿ ಆಫ್ ಸೈನ್ಸ್ಸ್, ಬೆಂಗಳೂರಿನಲ್ಲಿ ಜ್ಞಾನದ ಸೇವಕರು (Servants Of Knowledge) ಸಮುದಾಯ ಸಹಭಾಗಿತ್ವದ ಕೆಲಸದಡಿಯಲ್ಲಿ ಡಿಜಿಟಲೀಕರಿಸಲಾಗಿರುತ್ತದೆ.",
    "identifier": "unset0000unse_o8w1",
    "title": "ಬಾನುಮತಿ ಕಾಳಗ",
    "publisher": "Vijaya Mudranalaya, Mangalore",
    "tags": "",
    "level": "Yakshagana;Yakshagana Prasanga;ಯಕ್ಷಗಾನ;ಯಕ್ಷಗಾನ ಪ್ರಸಂಗ;ಕನ್ನಡ ಸಾಹಿತ್ಯ",
    "authorUrl": "https://archive.org/search.php?query=creator%3AK. N. Eshwar Bhat",
    "url": "https://archive.org/details/unset0000unse_o8w1",
    "cover": "https://archive.org/services/img/unset0000unse_o8w1"
  },
  {
    "author": "Venkatesh Uppadaya",
    "info": "‌ಈ ಪುಸ್ತಕವನ್ನು  ಸಂಚಿ ಫೌಂಡೇಶನ್ (https://sanchifoundation.org) ಹಾಗೂ ಸಂಚಯದ (https://sanchaya.org) ವತಿಯಿಂದ ಇಂಡಿಯನ್ ಅಕಾಡೆಮಿ ಆಫ್ ಸೈನ್ಸ್ಸ್, ಬೆಂಗಳೂರಿನಲ್ಲಿ ಜ್ಞಾನದ ಸೇವಕರು (Servants Of Knowledge) ಸಮುದಾಯ ಸಹಭಾಗಿತ್ವದ ಕೆಲಸದಡಿಯಲ್ಲಿ ಡಿಜಿಟಲೀಕರಿಸಲಾಗಿರುತ್ತದೆ.",
    "identifier": "unset0000unse_r4p0",
    "title": "ಬಾಲ ಘಟೋತ್ಘಜ",
    "publisher": "Pragnya Deepthi Prakashana",
    "tags": "",
    "level": "Yakshagana;Yakshagana Prasanga;ಯಕ್ಷಗಾನ;ಯಕ್ಷಗಾನ ಪ್ರಸಂಗ;ಕನ್ನಡ ಸಾಹಿತ್ಯ",
    "authorUrl": "https://archive.org/search.php?query=creator%3AVenkatesh Uppadaya",
    "url": "https://archive.org/details/unset0000unse_r4p0",
    "cover": "https://archive.org/services/img/unset0000unse_r4p0"
  },
  {
    "author": "",
    "info": "‌ಈ ಪುಸ್ತಕವನ್ನು  ಸಂಚಿ ಫೌಂಡೇಶನ್ (https://sanchifoundation.org) ಹಾಗೂ ಸಂಚಯದ (https://sanchaya.org) ವತಿಯಿಂದ ಇಂಡಿಯನ್ ಅಕಾಡೆಮಿ ಆಫ್ ಸೈನ್ಸ್ಸ್, ಬೆಂಗಳೂರಿನಲ್ಲಿ ಜ್ಞಾನದ ಸೇವಕರು (Servants Of Knowledge) ಸಮುದಾಯ ಸಹಭಾಗಿತ್ವದ ಕೆಲಸದಡಿಯಲ್ಲಿ ಡಿಜಿಟಲೀಕರಿಸಲಾಗಿರುತ್ತದೆ.",
    "identifier": "unset0000unse_a5d9",
    "title": "ಬಿಲ್ಲಿ ಹಬ್ಬ ಅಥವಾ ಕಂಸವಧೆ",
    "publisher": "ಪಾವಂಜೆ ಗುರುರಾವ್",
    "tags": "",
    "level": "Yakshagana;Yakshagana Prasanga;ಯಕ್ಷಗಾನ;ಯಕ್ಷಗಾನ ಪ್ರಸಂಗ;ಕನ್ನಡ ಸಾಹಿತ್ಯ",
    "authorUrl": "https://archive.org/search.php?query=creator%3A",
    "url": "https://archive.org/details/unset0000unse_a5d9",
    "cover": "https://archive.org/services/img/unset0000unse_a5d9"
  },
  {
    "author": "ಕೀರಿಕ್ಕಾಡು ಮಾಸ್ತರ್ ವಿಷ್ಣು ಭಟ್",
    "info": "‌ಈ ಪುಸ್ತಕವನ್ನು  ಸಂಚಿ ಫೌಂಡೇಶನ್ (https://sanchifoundation.org) ಹಾಗೂ ಸಂಚಯದ (https://sanchaya.org) ವತಿಯಿಂದ ಇಂಡಿಯನ್ ಅಕಾಡೆಮಿ ಆಫ್ ಸೈನ್ಸ್ಸ್, ಬೆಂಗಳೂರಿನಲ್ಲಿ ಜ್ಞಾನದ ಸೇವಕರು (Servants Of Knowledge) ಸಮುದಾಯ ಸಹಭಾಗಿತ್ವದ ಕೆಲಸದಡಿಯಲ್ಲಿ ಡಿಜಿಟಲೀಕರಿಸಲಾಗಿರುತ್ತದೆ.",
    "identifier": "unset0000unse_h0t6",
    "title": "ಬ್ರಹ್ಮ ಯಜ್ಞ",
    "publisher": "ಶ್ರೀ ಗೋಪಾಲಕೃಷ್ಣ ಪ್ರಕಾಶನ",
    "tags": "",
    "level": "Yakshagana;Yakshagana Prasanga;ಯಕ್ಷಗಾನ;ಯಕ್ಷಗಾನ ಪ್ರಸಂಗ;ಕನ್ನಡ ಸಾಹಿತ್ಯ",
    "authorUrl": "https://archive.org/search.php?query=creator%3Aಕೀರಿಕ್ಕಾಡು ಮಾಸ್ತರ್ ವಿಷ್ಣು ಭಟ್",
    "url": "https://archive.org/details/unset0000unse_h0t6",
    "cover": "https://archive.org/services/img/unset0000unse_h0t6"
  },
  {
    "author": "Kanyana Venkataramanna Bhatta",
    "info": "‌ಈ ಪುಸ್ತಕವನ್ನು  ಸಂಚಿ ಫೌಂಡೇಶನ್ (https://sanchifoundation.org) ಹಾಗೂ ಸಂಚಯದ (https://sanchaya.org) ವತಿಯಿಂದ ಇಂಡಿಯನ್ ಅಕಾಡೆಮಿ ಆಫ್ ಸೈನ್ಸ್ಸ್, ಬೆಂಗಳೂರಿನಲ್ಲಿ ಜ್ಞಾನದ ಸೇವಕರು (Servants Of Knowledge) ಸಮುದಾಯ ಸಹಭಾಗಿತ್ವದ ಕೆಲಸದಡಿಯಲ್ಲಿ ಡಿಜಿಟಲೀಕರಿಸಲಾಗಿರುತ್ತದೆ.",
    "identifier": "unset0000unse_j5s8",
    "title": "ಬ್ರಹ್ಮಕಪಾಲ",
    "publisher": "ಪಾವಂಜೆ ಗುರುರಾವ್",
    "tags": "",
    "level": "Yakshagana;Yakshagana Prasanga;ಯಕ್ಷಗಾನ;ಯಕ್ಷಗಾನ ಪ್ರಸಂಗ;ಕನ್ನಡ ಸಾಹಿತ್ಯ",
    "authorUrl": "https://archive.org/search.php?query=creator%3AKanyana Venkataramanna Bhatta",
    "url": "https://archive.org/details/unset0000unse_j5s8",
    "cover": "https://archive.org/services/img/unset0000unse_j5s8"
  },
  {
    "author": "ಎಂ. ಜಿ. ಬರವಣಿ",
    "info": "‌ಈ ಪುಸ್ತಕವನ್ನು  ಸಂಚಿ ಫೌಂಡೇಶನ್ (https://sanchifoundation.org) ಹಾಗೂ ಸಂಚಯದ (https://sanchaya.org) ವತಿಯಿಂದ ಇಂಡಿಯನ್ ಅಕಾಡೆಮಿ ಆಫ್ ಸೈನ್ಸ್ಸ್, ಬೆಂಗಳೂರಿನಲ್ಲಿ ಜ್ಞಾನದ ಸೇವಕರು (Servants Of Knowledge) ಸಮುದಾಯ ಸಹಭಾಗಿತ್ವದ ಕೆಲಸದಡಿಯಲ್ಲಿ ಡಿಜಿಟಲೀಕರಿಸಲಾಗಿರುತ್ತದೆ.",
    "identifier": "unset0000unse_n8u2",
    "title": "ಬ್ರಹ್ಮಾಸುರ ಮೋಹಿನಿ",
    "publisher": "ಎಂ. ಜಿ. ಬರವಣಿ, ಯಕ್ಷಗಾನ ಕಲಾವಿದರು, ಗೋಕರ್ಣ",
    "tags": "",
    "level": "Yakshagana;Yakshagana Prasanga;ಯಕ್ಷಗಾನ;ಯಕ್ಷಗಾನ ಪ್ರಸಂಗ;ಕನ್ನಡ ಸಾಹಿತ್ಯ",
    "authorUrl": "https://archive.org/search.php?query=creator%3Aಎಂ. ಜಿ. ಬರವಣಿ",
    "url": "https://archive.org/details/unset0000unse_n8u2",
    "cover": "https://archive.org/services/img/unset0000unse_n8u2"
  },
  {
    "author": "",
    "info": "‌ಈ ಪುಸ್ತಕವನ್ನು  ಸಂಚಿ ಫೌಂಡೇಶನ್ (https://sanchifoundation.org) ಹಾಗೂ ಸಂಚಯದ (https://sanchaya.org) ವತಿಯಿಂದ ಇಂಡಿಯನ್ ಅಕಾಡೆಮಿ ಆಫ್ ಸೈನ್ಸ್ಸ್, ಬೆಂಗಳೂರಿನಲ್ಲಿ ಜ್ಞಾನದ ಸೇವಕರು (Servants Of Knowledge) ಸಮುದಾಯ ಸಹಭಾಗಿತ್ವದ ಕೆಲಸದಡಿಯಲ್ಲಿ ಡಿಜಿಟಲೀಕರಿಸಲಾಗಿರುತ್ತದೆ.",
    "identifier": "unset0000unse_w9b0",
    "title": "ಬ್ರಹ್ಮೋತ್ತರಕಾಂಡದೊಳಗಣ ಯಕ್ಷಗಾನ ಭದ್ರಾಯುಚರಿತ್ರೆ",
    "publisher": "ಪಾವಂಜೆ ಗುರುರಾವ್",
    "tags": "",
    "level": "Yakshagana;Yakshagana Prasanga;ಯಕ್ಷಗಾನ;ಯಕ್ಷಗಾನ ಪ್ರಸಂಗ;ಕನ್ನಡ ಸಾಹಿತ್ಯ",
    "authorUrl": "https://archive.org/search.php?query=creator%3A",
    "url": "https://archive.org/details/unset0000unse_w9b0",
    "cover": "https://archive.org/services/img/unset0000unse_w9b0"
  },
  {
    "author": "B. Babu Kudathkadk",
    "info": "‌ಈ ಪುಸ್ತಕವನ್ನು  ಸಂಚಿ ಫೌಂಡೇಶನ್ (https://sanchifoundation.org) ಹಾಗೂ ಸಂಚಯದ (https://sanchaya.org) ವತಿಯಿಂದ ಇಂಡಿಯನ್ ಅಕಾಡೆಮಿ ಆಫ್ ಸೈನ್ಸ್ಸ್, ಬೆಂಗಳೂರಿನಲ್ಲಿ ಜ್ಞಾನದ ಸೇವಕರು (Servants Of Knowledge) ಸಮುದಾಯ ಸಹಭಾಗಿತ್ವದ ಕೆಲಸದಡಿಯಲ್ಲಿ ಡಿಜಿಟಲೀಕರಿಸಲಾಗಿರುತ್ತದೆ.",
    "identifier": "unset0000unse_w7x6",
    "title": "ಭಕ್ತ ಕುಂಬಾರ ಅಥವಾ ಪಾಂಡುರಂಗ ಮಹಾತ್ಮ್ಯೆ",
    "publisher": "B. Babu Kudathkadk Yakshagana Kalavidaru",
    "tags": "",
    "level": "Yakshagana;Yakshagana Prasanga;ಯಕ್ಷಗಾನ;ಯಕ್ಷಗಾನ ಪ್ರಸಂಗ;ಕನ್ನಡ ಸಾಹಿತ್ಯ",
    "authorUrl": "https://archive.org/search.php?query=creator%3AB. Babu Kudathkadk",
    "url": "https://archive.org/details/unset0000unse_w7x6",
    "cover": "https://archive.org/services/img/unset0000unse_w7x6"
  },
  {
    "author": "ಎಂ. ಜಿ. ಬರವಣಿ",
    "info": "‌ಈ ಪುಸ್ತಕವನ್ನು  ಸಂಚಿ ಫೌಂಡೇಶನ್ (https://sanchifoundation.org) ಹಾಗೂ ಸಂಚಯದ (https://sanchaya.org) ವತಿಯಿಂದ ಇಂಡಿಯನ್ ಅಕಾಡೆಮಿ ಆಫ್ ಸೈನ್ಸ್ಸ್, ಬೆಂಗಳೂರಿನಲ್ಲಿ ಜ್ಞಾನದ ಸೇವಕರು (Servants Of Knowledge) ಸಮುದಾಯ ಸಹಭಾಗಿತ್ವದ ಕೆಲಸದಡಿಯಲ್ಲಿ ಡಿಜಿಟಲೀಕರಿಸಲಾಗಿರುತ್ತದೆ.",
    "identifier": "unset0000unse_s5v7",
    "title": "ಭಾನುಮತು ಪರಿಣಯ",
    "publisher": "ಎಂ. ಜಿ. ಬರವಣಿ, ಯಕ್ಷಗಾನ ಕಲಾವಿದರು, ಗೋಕರ್ಣ",
    "tags": "",
    "level": "Yakshagana;Yakshagana Prasanga;ಯಕ್ಷಗಾನ;ಯಕ್ಷಗಾನ ಪ್ರಸಂಗ;ಕನ್ನಡ ಸಾಹಿತ್ಯ",
    "authorUrl": "https://archive.org/search.php?query=creator%3Aಎಂ. ಜಿ. ಬರವಣಿ",
    "url": "https://archive.org/details/unset0000unse_s5v7",
    "cover": "https://archive.org/services/img/unset0000unse_s5v7"
  },
  {
    "author": "Bhadekila Veenkataramana Bhat",
    "info": "‌ಈ ಪುಸ್ತಕವನ್ನು  ಸಂಚಿ ಫೌಂಡೇಶನ್ (https://sanchifoundation.org) ಹಾಗೂ ಸಂಚಯದ (https://sanchaya.org) ವತಿಯಿಂದ ಇಂಡಿಯನ್ ಅಕಾಡೆಮಿ ಆಫ್ ಸೈನ್ಸ್ಸ್, ಬೆಂಗಳೂರಿನಲ್ಲಿ ಜ್ಞಾನದ ಸೇವಕರು (Servants Of Knowledge) ಸಮುದಾಯ ಸಹಭಾಗಿತ್ವದ ಕೆಲಸದಡಿಯಲ್ಲಿ ಡಿಜಿಟಲೀಕರಿಸಲಾಗಿರುತ್ತದೆ.",
    "identifier": "unset0000unse_m8k1",
    "title": "ಭೀಮ ವಿಜಯ",
    "publisher": "Vani Printare, Puthuru.",
    "tags": "",
    "level": "Yakshagana;Yakshagana Prasanga;ಯಕ್ಷಗಾನ;ಯಕ್ಷಗಾನ ಪ್ರಸಂಗ;ಕನ್ನಡ ಸಾಹಿತ್ಯ",
    "authorUrl": "https://archive.org/search.php?query=creator%3ABhadekila Veenkataramana Bhat",
    "url": "https://archive.org/details/unset0000unse_m8k1",
    "cover": "https://archive.org/services/img/unset0000unse_m8k1"
  },
  {
    "author": "ಹಲಸಿನಹಳ್ಳಿ ನರಸಿಂಹಶಾಸ್ತ್ರಿಗಳು",
    "info": "‌ಈ ಪುಸ್ತಕವನ್ನು  ಸಂಚಿ ಫೌಂಡೇಶನ್ (https://sanchifoundation.org) ಹಾಗೂ ಸಂಚಯದ (https://sanchaya.org) ವತಿಯಿಂದ ಇಂಡಿಯನ್ ಅಕಾಡೆಮಿ ಆಫ್ ಸೈನ್ಸ್ಸ್, ಬೆಂಗಳೂರಿನಲ್ಲಿ ಜ್ಞಾನದ ಸೇವಕರು (Servants Of Knowledge) ಸಮುದಾಯ ಸಹಭಾಗಿತ್ವದ ಕೆಲಸದಡಿಯಲ್ಲಿ ಡಿಜಿಟಲೀಕರಿಸಲಾಗಿರುತ್ತದೆ.",
    "identifier": "unset0000unse_g6v8",
    "title": "ಭೀಷ್ಮೋತ್ಪತ್ತಿ",
    "publisher": "ರಾಧಾಕೃಷ್ಣ ಪ್ರಿಂಟಿಂಗ್ ಪ್ರೆಸ್",
    "tags": "",
    "level": "Yakshagana;Yakshagana Prasanga;ಯಕ್ಷಗಾನ;ಯಕ್ಷಗಾನ ಪ್ರಸಂಗ;ಕನ್ನಡ ಸಾಹಿತ್ಯ",
    "authorUrl": "https://archive.org/search.php?query=creator%3Aಹಲಸಿನಹಳ್ಳಿ ನರಸಿಂಹಶಾಸ್ತ್ರಿಗಳು",
    "url": "https://archive.org/details/unset0000unse_g6v8",
    "cover": "https://archive.org/services/img/unset0000unse_g6v8"
  },
  {
    "author": "ಮುದ್ರಾಡಿ ವೆಂಕಪ್ಪಯ್ಯ",
    "info": "‌ಈ ಪುಸ್ತಕವನ್ನು  ಸಂಚಿ ಫೌಂಡೇಶನ್ (https://sanchifoundation.org) ಹಾಗೂ ಸಂಚಯದ (https://sanchaya.org) ವತಿಯಿಂದ ಇಂಡಿಯನ್ ಅಕಾಡೆಮಿ ಆಫ್ ಸೈನ್ಸ್ಸ್, ಬೆಂಗಳೂರಿನಲ್ಲಿ ಜ್ಞಾನದ ಸೇವಕರು (Servants Of Knowledge) ಸಮುದಾಯ ಸಹಭಾಗಿತ್ವದ ಕೆಲಸದಡಿಯಲ್ಲಿ ಡಿಜಿಟಲೀಕರಿಸಲಾಗಿರುತ್ತದೆ.",
    "identifier": "unset0000unse_z3u2",
    "title": "ಭೂ-ಕೈಲಾಸ ಅಥವಾ ಮಂಡೋದರಿ ಪರಿಣಯ",
    "publisher": "ಆರ್. ವೆಂಕಟಪ್ಪ ಶಣೈ & ಸನ್ಸ್",
    "tags": "",
    "level": "Yakshagana;Yakshagana Prasanga;ಯಕ್ಷಗಾನ;ಯಕ್ಷಗಾನ ಪ್ರಸಂಗ;ಕನ್ನಡ ಸಾಹಿತ್ಯ",
    "authorUrl": "https://archive.org/search.php?query=creator%3Aಮುದ್ರಾಡಿ ವೆಂಕಪ್ಪಯ್ಯ",
    "url": "https://archive.org/details/unset0000unse_z3u2",
    "cover": "https://archive.org/services/img/unset0000unse_z3u2"
  },
  {
    "author": "Jankai Thimappa Venkappa Hegade",
    "info": "‌ಈ ಪುಸ್ತಕವನ್ನು  ಸಂಚಿ ಫೌಂಡೇಶನ್ (https://sanchifoundation.org) ಹಾಗೂ ಸಂಚಯದ (https://sanchaya.org) ವತಿಯಿಂದ ಇಂಡಿಯನ್ ಅಕಾಡೆಮಿ ಆಫ್ ಸೈನ್ಸ್ಸ್, ಬೆಂಗಳೂರಿನಲ್ಲಿ ಜ್ಞಾನದ ಸೇವಕರು (Servants Of Knowledge) ಸಮುದಾಯ ಸಹಭಾಗಿತ್ವದ ಕೆಲಸದಡಿಯಲ್ಲಿ ಡಿಜಿಟಲೀಕರಿಸಲಾಗಿರುತ್ತದೆ.",
    "identifier": "unset0000unse_q0z1",
    "title": "ಮಧನ ಸುಂದರಿ ಸ್ವಯಂವರ",
    "publisher": "Udupi Prabhakara Press",
    "tags": "",
    "level": "Yakshagana;Yakshagana Prasanga;ಯಕ್ಷಗಾನ;ಯಕ್ಷಗಾನ ಪ್ರಸಂಗ;ಕನ್ನಡ ಸಾಹಿತ್ಯ",
    "authorUrl": "https://archive.org/search.php?query=creator%3AJankai Thimappa Venkappa Hegade",
    "url": "https://archive.org/details/unset0000unse_q0z1",
    "cover": "https://archive.org/services/img/unset0000unse_q0z1"
  },
  {
    "author": "Vidhavan Thalthaje Krishna Bhatta",
    "info": "‌ಈ ಪುಸ್ತಕವನ್ನು  ಸಂಚಿ ಫೌಂಡೇಶನ್ (https://sanchifoundation.org) ಹಾಗೂ ಸಂಚಯದ (https://sanchaya.org) ವತಿಯಿಂದ ಇಂಡಿಯನ್ ಅಕಾಡೆಮಿ ಆಫ್ ಸೈನ್ಸ್ಸ್, ಬೆಂಗಳೂರಿನಲ್ಲಿ ಜ್ಞಾನದ ಸೇವಕರು (Servants Of Knowledge) ಸಮುದಾಯ ಸಹಭಾಗಿತ್ವದ ಕೆಲಸದಡಿಯಲ್ಲಿ ಡಿಜಿಟಲೀಕರಿಸಲಾಗಿರುತ್ತದೆ.",
    "identifier": "unset0000unse_k8x5",
    "title": "ಮಯೂರವರ್ಮ ವಿಲಾಸ",
    "publisher": "Prathima Prakashana",
    "tags": "",
    "level": "Yakshagana;Yakshagana Prasanga;ಯಕ್ಷಗಾನ;ಯಕ್ಷಗಾನ ಪ್ರಸಂಗ;ಕನ್ನಡ ಸಾಹಿತ್ಯ",
    "authorUrl": "https://archive.org/search.php?query=creator%3AVidhavan Thalthaje Krishna Bhatta",
    "url": "https://archive.org/details/unset0000unse_k8x5",
    "cover": "https://archive.org/services/img/unset0000unse_k8x5"
  },
  {
    "author": "ಶ್ರೀ ನಾಗೇಶ ಟಿ. ಪೂಜಾರಿ",
    "info": "‌ಈ ಪುಸ್ತಕವನ್ನು  ಸಂಚಿ ಫೌಂಡೇಶನ್ (https://sanchifoundation.org) ಹಾಗೂ ಸಂಚಯದ (https://sanchaya.org) ವತಿಯಿಂದ ಇಂಡಿಯನ್ ಅಕಾಡೆಮಿ ಆಫ್ ಸೈನ್ಸ್ಸ್, ಬೆಂಗಳೂರಿನಲ್ಲಿ ಜ್ಞಾನದ ಸೇವಕರು (Servants Of Knowledge) ಸಮುದಾಯ ಸಹಭಾಗಿತ್ವದ ಕೆಲಸದಡಿಯಲ್ಲಿ ಡಿಜಿಟಲೀಕರಿಸಲಾಗಿರುತ್ತದೆ.",
    "identifier": "unset0000unse_j0a5",
    "title": "ಮಾಣಿಕ್ಯಪ್ರಭಾ ಪರಿಣಯ ಅರ್ಥಾತ್ ಚಂದ್ರಕೇತು ಚರಿತ್ರೆ",
    "publisher": "ಶ್ರೀ ನಾಗೇಶ ಟಿ. ಪೂಜಾರಿ",
    "tags": "",
    "level": "Yakshagana;Yakshagana Prasanga;ಯಕ್ಷಗಾನ;ಯಕ್ಷಗಾನ ಪ್ರಸಂಗ;ಕನ್ನಡ ಸಾಹಿತ್ಯ",
    "authorUrl": "https://archive.org/search.php?query=creator%3Aಶ್ರೀ ನಾಗೇಶ ಟಿ. ಪೂಜಾರಿ",
    "url": "https://archive.org/details/unset0000unse_j0a5",
    "cover": "https://archive.org/services/img/unset0000unse_j0a5"
  },
  {
    "author": "ಎಂ. ಜಿ. ಬರವಣಿ",
    "info": "‌ಈ ಪುಸ್ತಕವನ್ನು  ಸಂಚಿ ಫೌಂಡೇಶನ್ (https://sanchifoundation.org) ಹಾಗೂ ಸಂಚಯದ (https://sanchaya.org) ವತಿಯಿಂದ ಇಂಡಿಯನ್ ಅಕಾಡೆಮಿ ಆಫ್ ಸೈನ್ಸ್ಸ್, ಬೆಂಗಳೂರಿನಲ್ಲಿ ಜ್ಞಾನದ ಸೇವಕರು (Servants Of Knowledge) ಸಮುದಾಯ ಸಹಭಾಗಿತ್ವದ ಕೆಲಸದಡಿಯಲ್ಲಿ ಡಿಜಿಟಲೀಕರಿಸಲಾಗಿರುತ್ತದೆ.",
    "identifier": "unset0000unse_g8q0",
    "title": "ಮಾಯಾ - ಮಹಿಮೆ",
    "publisher": "ಎಂ. ಜಿ. ಬರವಣಿ, ಯಕ್ಷಗಾನ ಕಲಾವಿದರು, ಗೋಕರ್ಣ",
    "tags": "",
    "level": "Yakshagana;Yakshagana Prasanga;ಯಕ್ಷಗಾನ;ಯಕ್ಷಗಾನ ಪ್ರಸಂಗ;ಕನ್ನಡ ಸಾಹಿತ್ಯ",
    "authorUrl": "https://archive.org/search.php?query=creator%3Aಎಂ. ಜಿ. ಬರವಣಿ",
    "url": "https://archive.org/details/unset0000unse_g8q0",
    "cover": "https://archive.org/services/img/unset0000unse_g8q0"
  },
  {
    "author": "ಕೀರಿಕ್ಕಾಡು ಮಾಸ್ತರ್ ವಿಷ್ಣು ಭಟ್",
    "info": "‌ಈ ಪುಸ್ತಕವನ್ನು  ಸಂಚಿ ಫೌಂಡೇಶನ್ (https://sanchifoundation.org) ಹಾಗೂ ಸಂಚಯದ (https://sanchaya.org) ವತಿಯಿಂದ ಇಂಡಿಯನ್ ಅಕಾಡೆಮಿ ಆಫ್ ಸೈನ್ಸ್ಸ್, ಬೆಂಗಳೂರಿನಲ್ಲಿ ಜ್ಞಾನದ ಸೇವಕರು (Servants Of Knowledge) ಸಮುದಾಯ ಸಹಭಾಗಿತ್ವದ ಕೆಲಸದಡಿಯಲ್ಲಿ ಡಿಜಿಟಲೀಕರಿಸಲಾಗಿರುತ್ತದೆ.",
    "identifier": "unset0000unse_j6m2",
    "title": "ಮಿತ್ರಗುಪ್ತ ವಿಜಯ",
    "publisher": "ಶ್ರೀ ಗೋಪಾಲಕೃಷ್ಣ ಪ್ರಕಾಶನ",
    "tags": "",
    "level": "Yakshagana;Yakshagana Prasanga;ಯಕ್ಷಗಾನ;ಯಕ್ಷಗಾನ ಪ್ರಸಂಗ;ಕನ್ನಡ ಸಾಹಿತ್ಯ",
    "authorUrl": "https://archive.org/search.php?query=creator%3Aಕೀರಿಕ್ಕಾಡು ಮಾಸ್ತರ್ ವಿಷ್ಣು ಭಟ್",
    "url": "https://archive.org/details/unset0000unse_j6m2",
    "cover": "https://archive.org/services/img/unset0000unse_j6m2"
  },
  {
    "author": "Pavanje",
    "info": "‌ಈ ಪುಸ್ತಕವನ್ನು  ಸಂಚಿ ಫೌಂಡೇಶನ್ (https://sanchifoundation.org) ಹಾಗೂ ಸಂಚಯದ (https://sanchaya.org) ವತಿಯಿಂದ ಇಂಡಿಯನ್ ಅಕಾಡೆಮಿ ಆಫ್ ಸೈನ್ಸ್ಸ್, ಬೆಂಗಳೂರಿನಲ್ಲಿ ಜ್ಞಾನದ ಸೇವಕರು (Servants Of Knowledge) ಸಮುದಾಯ ಸಹಭಾಗಿತ್ವದ ಕೆಲಸದಡಿಯಲ್ಲಿ ಡಿಜಿಟಲೀಕರಿಸಲಾಗಿರುತ್ತದೆ.",
    "identifier": "unset0000unse_k7d5",
    "title": "ಮೀನಾಕ್ಷಿ ಕಲ್ಯಾಣ",
    "publisher": "ಪಾವಂಜೆ ಗುರುರಾವ್",
    "tags": "",
    "level": "Yakshagana;Yakshagana Prasanga;ಯಕ್ಷಗಾನ;ಯಕ್ಷಗಾನ ಪ್ರಸಂಗ;ಕನ್ನಡ ಸಾಹಿತ್ಯ",
    "authorUrl": "https://archive.org/search.php?query=creator%3APavanje",
    "url": "https://archive.org/details/unset0000unse_k7d5",
    "cover": "https://archive.org/services/img/unset0000unse_k7d5"
  },
  {
    "author": "",
    "info": "‌ಈ ಪುಸ್ತಕವನ್ನು  ಸಂಚಿ ಫೌಂಡೇಶನ್ (https://sanchifoundation.org) ಹಾಗೂ ಸಂಚಯದ (https://sanchaya.org) ವತಿಯಿಂದ ಇಂಡಿಯನ್ ಅಕಾಡೆಮಿ ಆಫ್ ಸೈನ್ಸ್ಸ್, ಬೆಂಗಳೂರಿನಲ್ಲಿ ಜ್ಞಾನದ ಸೇವಕರು (Servants Of Knowledge) ಸಮುದಾಯ ಸಹಭಾಗಿತ್ವದ ಕೆಲಸದಡಿಯಲ್ಲಿ ಡಿಜಿಟಲೀಕರಿಸಲಾಗಿರುತ್ತದೆ.",
    "identifier": "unset0000unse_e3f9",
    "title": "ಮೈರಾವಣನ ಚರಿತ್ರೆ",
    "publisher": "",
    "tags": "",
    "level": "Yakshagana;Yakshagana Prasanga;ಯಕ್ಷಗಾನ;ಯಕ್ಷಗಾನ ಪ್ರಸಂಗ;ಕನ್ನಡ ಸಾಹಿತ್ಯ",
    "authorUrl": "https://archive.org/search.php?query=creator%3A",
    "url": "https://archive.org/details/unset0000unse_e3f9",
    "cover": "https://archive.org/services/img/unset0000unse_e3f9"
  },
  {
    "author": "ಪಾವಂಡೇಶ್ವರ ವೆಂಕಟ",
    "info": "‌ಈ ಪುಸ್ತಕವನ್ನು  ಸಂಚಿ ಫೌಂಡೇಶನ್ (https://sanchifoundation.org) ಹಾಗೂ ಸಂಚಯದ (https://sanchaya.org) ವತಿಯಿಂದ ಇಂಡಿಯನ್ ಅಕಾಡೆಮಿ ಆಫ್ ಸೈನ್ಸ್ಸ್, ಬೆಂಗಳೂರಿನಲ್ಲಿ ಜ್ಞಾನದ ಸೇವಕರು (Servants Of Knowledge) ಸಮುದಾಯ ಸಹಭಾಗಿತ್ವದ ಕೆಲಸದಡಿಯಲ್ಲಿ ಡಿಜಿಟಲೀಕರಿಸಲಾಗಿರುತ್ತದೆ.",
    "identifier": "unset0000unse_p7i6",
    "title": "ಯಕ್ಷಗಾನ ಕರ್ಣಾರ್ಜುನರ ಕಾಳಗ (ಬಡಗುಮಟ್ಟು)",
    "publisher": "ಪಾವಂಜೆ ಗುರುರಾವ್ & ಸನ್ಸ್",
    "tags": "",
    "level": "Yakshagana;Yakshagana Prasanga;ಯಕ್ಷಗಾನ;ಯಕ್ಷಗಾನ ಪ್ರಸಂಗ;ಕನ್ನಡ ಸಾಹಿತ್ಯ",
    "authorUrl": "https://archive.org/search.php?query=creator%3Aಪಾವಂಡೇಶ್ವರ ವೆಂಕಟ",
    "url": "https://archive.org/details/unset0000unse_p7i6",
    "cover": "https://archive.org/services/img/unset0000unse_p7i6"
  },
  {
    "author": "Pavanjaya Sethu Madhava Rao",
    "info": "‌ಈ ಪುಸ್ತಕವನ್ನು  ಸಂಚಿ ಫೌಂಡೇಶನ್ (https://sanchifoundation.org) ಹಾಗೂ ಸಂಚಯದ (https://sanchaya.org) ವತಿಯಿಂದ ಇಂಡಿಯನ್ ಅಕಾಡೆಮಿ ಆಫ್ ಸೈನ್ಸ್ಸ್, ಬೆಂಗಳೂರಿನಲ್ಲಿ ಜ್ಞಾನದ ಸೇವಕರು (Servants Of Knowledge) ಸಮುದಾಯ ಸಹಭಾಗಿತ್ವದ ಕೆಲಸದಡಿಯಲ್ಲಿ ಡಿಜಿಟಲೀಕರಿಸಲಾಗಿರುತ್ತದೆ.",
    "identifier": "unset0000unse_o7k0",
    "title": "ಯಕ್ಷಗಾನ ಸುದನ್ವ ಕಾಳಗ",
    "publisher": "Sri Madhvasidhantha Granthalaya",
    "tags": "",
    "level": "Yakshagana;Yakshagana Prasanga;ಯಕ್ಷಗಾನ;ಯಕ್ಷಗಾನ ಪ್ರಸಂಗ;ಕನ್ನಡ ಸಾಹಿತ್ಯ",
    "authorUrl": "https://archive.org/search.php?query=creator%3APavanjaya Sethu Madhava Rao",
    "url": "https://archive.org/details/unset0000unse_o7k0",
    "cover": "https://archive.org/services/img/unset0000unse_o7k0"
  },
  {
    "author": "ಎಂ. ಜಿ. ಬರವಣಿ",
    "info": "‌ಈ ಪುಸ್ತಕವನ್ನು  ಸಂಚಿ ಫೌಂಡೇಶನ್ (https://sanchifoundation.org) ಹಾಗೂ ಸಂಚಯದ (https://sanchaya.org) ವತಿಯಿಂದ ಇಂಡಿಯನ್ ಅಕಾಡೆಮಿ ಆಫ್ ಸೈನ್ಸ್ಸ್, ಬೆಂಗಳೂರಿನಲ್ಲಿ ಜ್ಞಾನದ ಸೇವಕರು (Servants Of Knowledge) ಸಮುದಾಯ ಸಹಭಾಗಿತ್ವದ ಕೆಲಸದಡಿಯಲ್ಲಿ ಡಿಜಿಟಲೀಕರಿಸಲಾಗಿರುತ್ತದೆ.",
    "identifier": "unset0000unse_k6r0",
    "title": "ಯಾದವೇಶ್ವರ ರಾಜಸೂಯ ಭಾಗ ೧",
    "publisher": "Vijaya Vinayaka Yuvaka Sanga, Gokarna",
    "tags": "",
    "level": "Yakshagana;Yakshagana Prasanga;ಯಕ್ಷಗಾನ;ಯಕ್ಷಗಾನ ಪ್ರಸಂಗ;ಕನ್ನಡ ಸಾಹಿತ್ಯ",
    "authorUrl": "https://archive.org/search.php?query=creator%3Aಎಂ. ಜಿ. ಬರವಣಿ",
    "url": "https://archive.org/details/unset0000unse_k6r0",
    "cover": "https://archive.org/services/img/unset0000unse_k6r0"
  },
  {
    "author": "ಎಂ. ಜಿ. ಬರವಣಿ",
    "info": "‌ಈ ಪುಸ್ತಕವನ್ನು  ಸಂಚಿ ಫೌಂಡೇಶನ್ (https://sanchifoundation.org) ಹಾಗೂ ಸಂಚಯದ (https://sanchaya.org) ವತಿಯಿಂದ ಇಂಡಿಯನ್ ಅಕಾಡೆಮಿ ಆಫ್ ಸೈನ್ಸ್ಸ್, ಬೆಂಗಳೂರಿನಲ್ಲಿ ಜ್ಞಾನದ ಸೇವಕರು (Servants Of Knowledge) ಸಮುದಾಯ ಸಹಭಾಗಿತ್ವದ ಕೆಲಸದಡಿಯಲ್ಲಿ ಡಿಜಿಟಲೀಕರಿಸಲಾಗಿರುತ್ತದೆ.",
    "identifier": "unset0000unse_i3n6",
    "title": "ಯಾದವೇಶ್ವರ ರಾಜಸೂಯ ಭಾಗ ೨",
    "publisher": "ಎಂ. ಜಿ. ಬರವಣಿ, ಯಕ್ಷಗಾನ ಕಲಾವಿದರು, ಗೋಕರ್ಣ",
    "tags": "",
    "level": "Yakshagana;Yakshagana Prasanga;ಯಕ್ಷಗಾನ;ಯಕ್ಷಗಾನ ಪ್ರಸಂಗ;ಕನ್ನಡ ಸಾಹಿತ್ಯ",
    "authorUrl": "https://archive.org/search.php?query=creator%3Aಎಂ. ಜಿ. ಬರವಣಿ",
    "url": "https://archive.org/details/unset0000unse_i3n6",
    "cover": "https://archive.org/services/img/unset0000unse_i3n6"
  },
  {
    "author": "M. V. Rao",
    "info": "‌ಈ ಪುಸ್ತಕವನ್ನು  ಸಂಚಿ ಫೌಂಡೇಶನ್ (https://sanchifoundation.org) ಹಾಗೂ ಸಂಚಯದ (https://sanchaya.org) ವತಿಯಿಂದ ಇಂಡಿಯನ್ ಅಕಾಡೆಮಿ ಆಫ್ ಸೈನ್ಸ್ಸ್, ಬೆಂಗಳೂರಿನಲ್ಲಿ ಜ್ಞಾನದ ಸೇವಕರು (Servants Of Knowledge) ಸಮುದಾಯ ಸಹಭಾಗಿತ್ವದ ಕೆಲಸದಡಿಯಲ್ಲಿ ಡಿಜಿಟಲೀಕರಿಸಲಾಗಿರುತ್ತದೆ.",
    "identifier": "unset0000unse_o4j9",
    "title": "ರತಿ ಕಲ್ಯಾಣ",
    "publisher": "ನಿತ್ಯಾನಂದ ಗ್ರಂಥಾಲಯ",
    "tags": "",
    "level": "Yakshagana;Yakshagana Prasanga;ಯಕ್ಷಗಾನ;ಯಕ್ಷಗಾನ ಪ್ರಸಂಗ;ಕನ್ನಡ ಸಾಹಿತ್ಯ",
    "authorUrl": "https://archive.org/search.php?query=creator%3AM. V. Rao",
    "url": "https://archive.org/details/unset0000unse_o4j9",
    "cover": "https://archive.org/services/img/unset0000unse_o4j9"
  },
  {
    "author": "Shivaramapa",
    "info": "‌ಈ ಪುಸ್ತಕವನ್ನು  ಸಂಚಿ ಫೌಂಡೇಶನ್ (https://sanchifoundation.org) ಹಾಗೂ ಸಂಚಯದ (https://sanchaya.org) ವತಿಯಿಂದ ಇಂಡಿಯನ್ ಅಕಾಡೆಮಿ ಆಫ್ ಸೈನ್ಸ್ಸ್, ಬೆಂಗಳೂರಿನಲ್ಲಿ ಜ್ಞಾನದ ಸೇವಕರು (Servants Of Knowledge) ಸಮುದಾಯ ಸಹಭಾಗಿತ್ವದ ಕೆಲಸದಡಿಯಲ್ಲಿ ಡಿಜಿಟಲೀಕರಿಸಲಾಗಿರುತ್ತದೆ.",
    "identifier": "unset0000unse_a8m1",
    "title": "ರತ್ನಾಂಗಧನ ಚರಿತ್ರೆ",
    "publisher": "Bangalore Depo Power Press",
    "tags": "",
    "level": "Yakshagana;Yakshagana Prasanga;ಯಕ್ಷಗಾನ;ಯಕ್ಷಗಾನ ಪ್ರಸಂಗ;ಕನ್ನಡ ಸಾಹಿತ್ಯ",
    "authorUrl": "https://archive.org/search.php?query=creator%3AShivaramapa",
    "url": "https://archive.org/details/unset0000unse_a8m1",
    "cover": "https://archive.org/services/img/unset0000unse_a8m1"
  },
  {
    "author": "Nandavali. K. LAkshminarayanappa",
    "info": "‌ಈ ಪುಸ್ತಕವನ್ನು  ಸಂಚಿ ಫೌಂಡೇಶನ್ (https://sanchifoundation.org) ಹಾಗೂ ಸಂಚಯದ (https://sanchaya.org) ವತಿಯಿಂದ ಇಂಡಿಯನ್ ಅಕಾಡೆಮಿ ಆಫ್ ಸೈನ್ಸ್ಸ್, ಬೆಂಗಳೂರಿನಲ್ಲಿ ಜ್ಞಾನದ ಸೇವಕರು (Servants Of Knowledge) ಸಮುದಾಯ ಸಹಭಾಗಿತ್ವದ ಕೆಲಸದಡಿಯಲ್ಲಿ ಡಿಜಿಟಲೀಕರಿಸಲಾಗಿರುತ್ತದೆ.",
    "identifier": "unset0000unse_k5a2",
    "title": "ರತ್ನಾವತೀ ಕಲ್ಯಾಣ",
    "publisher": "ಪಾವಂಜೆ ಗುರುರಾವ್",
    "tags": "",
    "level": "Yakshagana;Yakshagana Prasanga;ಯಕ್ಷಗಾನ;ಯಕ್ಷಗಾನ ಪ್ರಸಂಗ;ಕನ್ನಡ ಸಾಹಿತ್ಯ",
    "authorUrl": "https://archive.org/search.php?query=creator%3ANandavali. K. LAkshminarayanappa",
    "url": "https://archive.org/details/unset0000unse_k5a2",
    "cover": "https://archive.org/services/img/unset0000unse_k5a2"
  },
  {
    "author": "ಎಂ. ಜಿ. ಬರವಣಿ",
    "info": "‌ಈ ಪುಸ್ತಕವನ್ನು  ಸಂಚಿ ಫೌಂಡೇಶನ್ (https://sanchifoundation.org) ಹಾಗೂ ಸಂಚಯದ (https://sanchaya.org) ವತಿಯಿಂದ ಇಂಡಿಯನ್ ಅಕಾಡೆಮಿ ಆಫ್ ಸೈನ್ಸ್ಸ್, ಬೆಂಗಳೂರಿನಲ್ಲಿ ಜ್ಞಾನದ ಸೇವಕರು (Servants Of Knowledge) ಸಮುದಾಯ ಸಹಭಾಗಿತ್ವದ ಕೆಲಸದಡಿಯಲ್ಲಿ ಡಿಜಿಟಲೀಕರಿಸಲಾಗಿರುತ್ತದೆ.",
    "identifier": "unset0000unse_h8d6",
    "title": "ರಾಜಾ ಹೃತ ಧ್ವಜ",
    "publisher": "Sri G.G. Hegade Vardhan",
    "tags": "",
    "level": "Yakshagana;Yakshagana Prasanga;ಯಕ್ಷಗಾನ;ಯಕ್ಷಗಾನ ಪ್ರಸಂಗ;ಕನ್ನಡ ಸಾಹಿತ್ಯ",
    "authorUrl": "https://archive.org/search.php?query=creator%3Aಎಂ. ಜಿ. ಬರವಣಿ",
    "url": "https://archive.org/details/unset0000unse_h8d6",
    "cover": "https://archive.org/services/img/unset0000unse_h8d6"
  },
  {
    "author": "Vajapehi Krishnaya",
    "info": "‌ಈ ಪುಸ್ತಕವನ್ನು  ಸಂಚಿ ಫೌಂಡೇಶನ್ (https://sanchifoundation.org) ಹಾಗೂ ಸಂಚಯದ (https://sanchaya.org) ವತಿಯಿಂದ ಇಂಡಿಯನ್ ಅಕಾಡೆಮಿ ಆಫ್ ಸೈನ್ಸ್ಸ್, ಬೆಂಗಳೂರಿನಲ್ಲಿ ಜ್ಞಾನದ ಸೇವಕರು (Servants Of Knowledge) ಸಮುದಾಯ ಸಹಭಾಗಿತ್ವದ ಕೆಲಸದಡಿಯಲ್ಲಿ ಡಿಜಿಟಲೀಕರಿಸಲಾಗಿರುತ್ತದೆ.",
    "identifier": "unset0000unse_r1n1",
    "title": "ರಾಮಾಶ್ವಮೇಧ ಯಾಗ",
    "publisher": "Sri Venkatadri Mudranalaya",
    "tags": "",
    "level": "Yakshagana;Yakshagana Prasanga;ಯಕ್ಷಗಾನ;ಯಕ್ಷಗಾನ ಪ್ರಸಂಗ;ಕನ್ನಡ ಸಾಹಿತ್ಯ",
    "authorUrl": "https://archive.org/search.php?query=creator%3AVajapehi Krishnaya",
    "url": "https://archive.org/details/unset0000unse_r1n1",
    "cover": "https://archive.org/services/img/unset0000unse_r1n1"
  },
  {
    "author": "",
    "info": "‌ಈ ಪುಸ್ತಕವನ್ನು  ಸಂಚಿ ಫೌಂಡೇಶನ್ (https://sanchifoundation.org) ಹಾಗೂ ಸಂಚಯದ (https://sanchaya.org) ವತಿಯಿಂದ ಇಂಡಿಯನ್ ಅಕಾಡೆಮಿ ಆಫ್ ಸೈನ್ಸ್ಸ್, ಬೆಂಗಳೂರಿನಲ್ಲಿ ಜ್ಞಾನದ ಸೇವಕರು (Servants Of Knowledge) ಸಮುದಾಯ ಸಹಭಾಗಿತ್ವದ ಕೆಲಸದಡಿಯಲ್ಲಿ ಡಿಜಿಟಲೀಕರಿಸಲಾಗಿರುತ್ತದೆ.",
    "identifier": "unset0000unse_j9l0",
    "title": "ರುಕ್ಮಾಂಗದ ಚರಿತ್ರೆ",
    "publisher": "Subhodha Sahitya Bandara",
    "tags": "",
    "level": "Yakshagana;Yakshagana Prasanga;ಯಕ್ಷಗಾನ;ಯಕ್ಷಗಾನ ಪ್ರಸಂಗ;ಕನ್ನಡ ಸಾಹಿತ್ಯ",
    "authorUrl": "https://archive.org/search.php?query=creator%3A",
    "url": "https://archive.org/details/unset0000unse_j9l0",
    "cover": "https://archive.org/services/img/unset0000unse_j9l0"
  },
  {
    "author": "ಎಂ. ಜಿ. ಬರವಣಿ",
    "info": "‌ಈ ಪುಸ್ತಕವನ್ನು  ಸಂಚಿ ಫೌಂಡೇಶನ್ (https://sanchifoundation.org) ಹಾಗೂ ಸಂಚಯದ (https://sanchaya.org) ವತಿಯಿಂದ ಇಂಡಿಯನ್ ಅಕಾಡೆಮಿ ಆಫ್ ಸೈನ್ಸ್ಸ್, ಬೆಂಗಳೂರಿನಲ್ಲಿ ಜ್ಞಾನದ ಸೇವಕರು (Servants Of Knowledge) ಸಮುದಾಯ ಸಹಭಾಗಿತ್ವದ ಕೆಲಸದಡಿಯಲ್ಲಿ ಡಿಜಿಟಲೀಕರಿಸಲಾಗಿರುತ್ತದೆ.",
    "identifier": "unset0000unse_i4w7",
    "title": "ರುಂಡ ಭೈರವ ಕಾಳಗ",
    "publisher": "ನವೀನ ಯಕ್ಷಗಾನ ಕಲಾಸಂಘ, ಗೋಕರ್ಣ",
    "tags": "",
    "level": "Yakshagana;Yakshagana Prasanga;ಯಕ್ಷಗಾನ;ಯಕ್ಷಗಾನ ಪ್ರಸಂಗ;ಕನ್ನಡ ಸಾಹಿತ್ಯ",
    "authorUrl": "https://archive.org/search.php?query=creator%3Aಎಂ. ಜಿ. ಬರವಣಿ",
    "url": "https://archive.org/details/unset0000unse_i4w7",
    "cover": "https://archive.org/services/img/unset0000unse_i4w7"
  },
  {
    "author": "K. Lakshmi Narayana Bhatta",
    "info": "‌ಈ ಪುಸ್ತಕವನ್ನು  ಸಂಚಿ ಫೌಂಡೇಶನ್ (https://sanchifoundation.org) ಹಾಗೂ ಸಂಚಯದ (https://sanchaya.org) ವತಿಯಿಂದ ಇಂಡಿಯನ್ ಅಕಾಡೆಮಿ ಆಫ್ ಸೈನ್ಸ್ಸ್, ಬೆಂಗಳೂರಿನಲ್ಲಿ ಜ್ಞಾನದ ಸೇವಕರು (Servants Of Knowledge) ಸಮುದಾಯ ಸಹಭಾಗಿತ್ವದ ಕೆಲಸದಡಿಯಲ್ಲಿ ಡಿಜಿಟಲೀಕರಿಸಲಾಗಿರುತ್ತದೆ.",
    "identifier": "unset0000unse_o5l3",
    "title": "ರೇವತಿ ಕಲ್ಯಾಣವು",
    "publisher": "ಪಾವಂಜೆ ಗುರುರಾವ್",
    "tags": "",
    "level": "Yakshagana;Yakshagana Prasanga;ಯಕ್ಷಗಾನ;ಯಕ್ಷಗಾನ ಪ್ರಸಂಗ;ಕನ್ನಡ ಸಾಹಿತ್ಯ",
    "authorUrl": "https://archive.org/search.php?query=creator%3AK. Lakshmi Narayana Bhatta",
    "url": "https://archive.org/details/unset0000unse_o5l3",
    "cover": "https://archive.org/services/img/unset0000unse_o5l3"
  },
  {
    "author": "ಪಂಡಿತ ಶ್ರೀ ರೇವಣ್ಣ ಕವಿ",
    "info": "‌ಈ ಪುಸ್ತಕವನ್ನು  ಸಂಚಿ ಫೌಂಡೇಶನ್ (https://sanchifoundation.org) ಹಾಗೂ ಸಂಚಯದ (https://sanchaya.org) ವತಿಯಿಂದ ಇಂಡಿಯನ್ ಅಕಾಡೆಮಿ ಆಫ್ ಸೈನ್ಸ್ಸ್, ಬೆಂಗಳೂರಿನಲ್ಲಿ ಜ್ಞಾನದ ಸೇವಕರು (Servants Of Knowledge) ಸಮುದಾಯ ಸಹಭಾಗಿತ್ವದ ಕೆಲಸದಡಿಯಲ್ಲಿ ಡಿಜಿಟಲೀಕರಿಸಲಾಗಿರುತ್ತದೆ.",
    "identifier": "unset0000unse_k3h3",
    "title": "ರೋಹಿಣಿ ಶಕಟ ಶನಿ ಮಹಾ ಪುರಾಣ ಅರ್ಥಾತ್ ಮಹಾಂದಾತ ಚರಿತ್ರೆ",
    "publisher": "ಶ್ರೀ ಮೃತ್ಯುಂಜಯ ಪ್ರಕಾಶನ",
    "tags": "",
    "level": "Yakshagana;Yakshagana Prasanga;ಯಕ್ಷಗಾನ;ಯಕ್ಷಗಾನ ಪ್ರಸಂಗ;ಕನ್ನಡ ಸಾಹಿತ್ಯ",
    "authorUrl": "https://archive.org/search.php?query=creator%3Aಪಂಡಿತ ಶ್ರೀ ರೇವಣ್ಣ ಕವಿ",
    "url": "https://archive.org/details/unset0000unse_k3h3",
    "cover": "https://archive.org/services/img/unset0000unse_k3h3"
  },
  {
    "author": "",
    "info": "‌ಈ ಪುಸ್ತಕವನ್ನು  ಸಂಚಿ ಫೌಂಡೇಶನ್ (https://sanchifoundation.org) ಹಾಗೂ ಸಂಚಯದ (https://sanchaya.org) ವತಿಯಿಂದ ಇಂಡಿಯನ್ ಅಕಾಡೆಮಿ ಆಫ್ ಸೈನ್ಸ್ಸ್, ಬೆಂಗಳೂರಿನಲ್ಲಿ ಜ್ಞಾನದ ಸೇವಕರು (Servants Of Knowledge) ಸಮುದಾಯ ಸಹಭಾಗಿತ್ವದ ಕೆಲಸದಡಿಯಲ್ಲಿ ಡಿಜಿಟಲೀಕರಿಸಲಾಗಿರುತ್ತದೆ.",
    "identifier": "unset0000unse_h5i6",
    "title": "ಲಕ್ಷ್ಮಣ ಕಲ್ಯಾಣ",
    "publisher": "ಪಾವಂಜೆ ಗುರುರಾವ್",
    "tags": "",
    "level": "Yakshagana;Yakshagana Prasanga;ಯಕ್ಷಗಾನ;ಯಕ್ಷಗಾನ ಪ್ರಸಂಗ;ಕನ್ನಡ ಸಾಹಿತ್ಯ",
    "authorUrl": "https://archive.org/search.php?query=creator%3A",
    "url": "https://archive.org/details/unset0000unse_h5i6",
    "cover": "https://archive.org/services/img/unset0000unse_h5i6"
  },
  {
    "author": "ಎಂ. ಜಿ. ಬರವಣಿ",
    "info": "‌ಈ ಪುಸ್ತಕವನ್ನು  ಸಂಚಿ ಫೌಂಡೇಶನ್ (https://sanchifoundation.org) ಹಾಗೂ ಸಂಚಯದ (https://sanchaya.org) ವತಿಯಿಂದ ಇಂಡಿಯನ್ ಅಕಾಡೆಮಿ ಆಫ್ ಸೈನ್ಸ್ಸ್, ಬೆಂಗಳೂರಿನಲ್ಲಿ ಜ್ಞಾನದ ಸೇವಕರು (Servants Of Knowledge) ಸಮುದಾಯ ಸಹಭಾಗಿತ್ವದ ಕೆಲಸದಡಿಯಲ್ಲಿ ಡಿಜಿಟಲೀಕರಿಸಲಾಗಿರುತ್ತದೆ.",
    "identifier": "unset0000unse_l7w6",
    "title": "ವಜ್ರಿ ವಿಜಯ",
    "publisher": "ಎಂ. ಜಿ. ಬರವಣಿ, ಯಕ್ಷಗಾನ ಕಲಾವಿದರು, ಗೋಕರ್ಣ",
    "tags": "",
    "level": "Yakshagana;Yakshagana Prasanga;ಯಕ್ಷಗಾನ;ಯಕ್ಷಗಾನ ಪ್ರಸಂಗ;ಕನ್ನಡ ಸಾಹಿತ್ಯ",
    "authorUrl": "https://archive.org/search.php?query=creator%3Aಎಂ. ಜಿ. ಬರವಣಿ",
    "url": "https://archive.org/details/unset0000unse_l7w6",
    "cover": "https://archive.org/services/img/unset0000unse_l7w6"
  },
  {
    "author": "K. P. Venkappa Shetty",
    "info": "‌ಈ ಪುಸ್ತಕವನ್ನು  ಸಂಚಿ ಫೌಂಡೇಶನ್ (https://sanchifoundation.org) ಹಾಗೂ ಸಂಚಯದ (https://sanchaya.org) ವತಿಯಿಂದ ಇಂಡಿಯನ್ ಅಕಾಡೆಮಿ ಆಫ್ ಸೈನ್ಸ್ಸ್, ಬೆಂಗಳೂರಿನಲ್ಲಿ ಜ್ಞಾನದ ಸೇವಕರು (Servants Of Knowledge) ಸಮುದಾಯ ಸಹಭಾಗಿತ್ವದ ಕೆಲಸದಡಿಯಲ್ಲಿ ಡಿಜಿಟಲೀಕರಿಸಲಾಗಿರುತ್ತದೆ.",
    "identifier": "unset0000unse_g3b9",
    "title": "ವಾಲಿ ಸುಗ್ರೀವ",
    "publisher": "Antharanga Karyalaya, Udupi.",
    "tags": "",
    "level": "Yakshagana;Yakshagana Prasanga;ಯಕ್ಷಗಾನ;ಯಕ್ಷಗಾನ ಪ್ರಸಂಗ;ಕನ್ನಡ ಸಾಹಿತ್ಯ",
    "authorUrl": "https://archive.org/search.php?query=creator%3AK. P. Venkappa Shetty",
    "url": "https://archive.org/details/unset0000unse_g3b9",
    "cover": "https://archive.org/services/img/unset0000unse_g3b9"
  },
  {
    "author": "",
    "info": "‌ಈ ಪುಸ್ತಕವನ್ನು  ಸಂಚಿ ಫೌಂಡೇಶನ್ (https://sanchifoundation.org) ಹಾಗೂ ಸಂಚಯದ (https://sanchaya.org) ವತಿಯಿಂದ ಇಂಡಿಯನ್ ಅಕಾಡೆಮಿ ಆಫ್ ಸೈನ್ಸ್ಸ್, ಬೆಂಗಳೂರಿನಲ್ಲಿ ಜ್ಞಾನದ ಸೇವಕರು (Servants Of Knowledge) ಸಮುದಾಯ ಸಹಭಾಗಿತ್ವದ ಕೆಲಸದಡಿಯಲ್ಲಿ ಡಿಜಿಟಲೀಕರಿಸಲಾಗಿರುತ್ತದೆ.",
    "identifier": "unset0000unse_z9w0",
    "title": "ವಾಲೀ ಸುಗ್ರೀವ ಕಾಳಗ",
    "publisher": "ಪಾವಂಜೆ ಗುರುರಾವ್",
    "tags": "",
    "level": "Yakshagana;Yakshagana Prasanga;ಯಕ್ಷಗಾನ;ಯಕ್ಷಗಾನ ಪ್ರಸಂಗ;ಕನ್ನಡ ಸಾಹಿತ್ಯ",
    "authorUrl": "https://archive.org/search.php?query=creator%3A",
    "url": "https://archive.org/details/unset0000unse_z9w0",
    "cover": "https://archive.org/services/img/unset0000unse_z9w0"
  },
  {
    "author": "T. Ramakrishna Bhat, Vidhvan",
    "info": "‌ಈ ಪುಸ್ತಕವನ್ನು  ಸಂಚಿ ಫೌಂಡೇಶನ್ (https://sanchifoundation.org) ಹಾಗೂ ಸಂಚಯದ (https://sanchaya.org) ವತಿಯಿಂದ ಇಂಡಿಯನ್ ಅಕಾಡೆಮಿ ಆಫ್ ಸೈನ್ಸ್ಸ್, ಬೆಂಗಳೂರಿನಲ್ಲಿ ಜ್ಞಾನದ ಸೇವಕರು (Servants Of Knowledge) ಸಮುದಾಯ ಸಹಭಾಗಿತ್ವದ ಕೆಲಸದಡಿಯಲ್ಲಿ ಡಿಜಿಟಲೀಕರಿಸಲಾಗಿರುತ್ತದೆ.",
    "identifier": "unset0000unse_v9d4",
    "title": "ವಾಸವದತ್ತ ರತ್ನಾವಳಿ",
    "publisher": "Sahitya Kuteera, Bayaru",
    "tags": "",
    "level": "Yakshagana;Yakshagana Prasanga;ಯಕ್ಷಗಾನ;ಯಕ್ಷಗಾನ ಪ್ರಸಂಗ;ಕನ್ನಡ ಸಾಹಿತ್ಯ",
    "authorUrl": "https://archive.org/search.php?query=creator%3AT. Ramakrishna Bhat, Vidhvan",
    "url": "https://archive.org/details/unset0000unse_v9d4",
    "cover": "https://archive.org/services/img/unset0000unse_v9d4"
  },
  {
    "author": "ಎಂ. ಜಿ. ಬರವಣಿ",
    "info": "‌ಈ ಪುಸ್ತಕವನ್ನು  ಸಂಚಿ ಫೌಂಡೇಶನ್ (https://sanchifoundation.org) ಹಾಗೂ ಸಂಚಯದ (https://sanchaya.org) ವತಿಯಿಂದ ಇಂಡಿಯನ್ ಅಕಾಡೆಮಿ ಆಫ್ ಸೈನ್ಸ್ಸ್, ಬೆಂಗಳೂರಿನಲ್ಲಿ ಜ್ಞಾನದ ಸೇವಕರು (Servants Of Knowledge) ಸಮುದಾಯ ಸಹಭಾಗಿತ್ವದ ಕೆಲಸದಡಿಯಲ್ಲಿ ಡಿಜಿಟಲೀಕರಿಸಲಾಗಿರುತ್ತದೆ.",
    "identifier": "unset0000unse_l4s3",
    "title": "ವಿದ್ರೂಪ - ವಿಜಯ",
    "publisher": "Vijaya Vinayaka Yuvaka Sanga, Gokarna",
    "tags": "",
    "level": "Yakshagana;Yakshagana Prasanga;ಯಕ್ಷಗಾನ;ಯಕ್ಷಗಾನ ಪ್ರಸಂಗ;ಕನ್ನಡ ಸಾಹಿತ್ಯ",
    "authorUrl": "https://archive.org/search.php?query=creator%3Aಎಂ. ಜಿ. ಬರವಣಿ",
    "url": "https://archive.org/details/unset0000unse_l4s3",
    "cover": "https://archive.org/services/img/unset0000unse_l4s3"
  },
  {
    "author": "ಪಾವಂಜೆ ಗುರುರಾಯರು",
    "info": "‌ಈ ಪುಸ್ತಕವನ್ನು  ಸಂಚಿ ಫೌಂಡೇಶನ್ (https://sanchifoundation.org) ಹಾಗೂ ಸಂಚಯದ (https://sanchaya.org) ವತಿಯಿಂದ ಇಂಡಿಯನ್ ಅಕಾಡೆಮಿ ಆಫ್ ಸೈನ್ಸ್ಸ್, ಬೆಂಗಳೂರಿನಲ್ಲಿ ಜ್ಞಾನದ ಸೇವಕರು (Servants Of Knowledge) ಸಮುದಾಯ ಸಹಭಾಗಿತ್ವದ ಕೆಲಸದಡಿಯಲ್ಲಿ ಡಿಜಿಟಲೀಕರಿಸಲಾಗಿರುತ್ತದೆ.",
    "identifier": "unset0000unse_v4j7",
    "title": "ವಿಶ್ವಾಮಿತ್ರ ಪ್ರತಾಪ",
    "publisher": "ಪಾವಂಜೆ ಗುರುರಾವ್",
    "tags": "",
    "level": "Yakshagana;Yakshagana Prasanga;ಯಕ್ಷಗಾನ;ಯಕ್ಷಗಾನ ಪ್ರಸಂಗ;ಕನ್ನಡ ಸಾಹಿತ್ಯ",
    "authorUrl": "https://archive.org/search.php?query=creator%3Aಪಾವಂಜೆ ಗುರುರಾಯರು",
    "url": "https://archive.org/details/unset0000unse_v4j7",
    "cover": "https://archive.org/services/img/unset0000unse_v4j7"
  },
  {
    "author": "ಎಂ. ಜಿ. ಬರವಣಿ",
    "info": "‌ಈ ಪುಸ್ತಕವನ್ನು  ಸಂಚಿ ಫೌಂಡೇಶನ್ (https://sanchifoundation.org) ಹಾಗೂ ಸಂಚಯದ (https://sanchaya.org) ವತಿಯಿಂದ ಇಂಡಿಯನ್ ಅಕಾಡೆಮಿ ಆಫ್ ಸೈನ್ಸ್ಸ್, ಬೆಂಗಳೂರಿನಲ್ಲಿ ಜ್ಞಾನದ ಸೇವಕರು (Servants Of Knowledge) ಸಮುದಾಯ ಸಹಭಾಗಿತ್ವದ ಕೆಲಸದಡಿಯಲ್ಲಿ ಡಿಜಿಟಲೀಕರಿಸಲಾಗಿರುತ್ತದೆ.",
    "identifier": "unset0000unse_q3q8",
    "title": "ವೀರ ಯೂಪಧ್ವಜ",
    "publisher": "ಎಂ. ಜಿ. ಬರವಣಿ, ಯಕ್ಷಗಾನ ಕಲಾವಿದರು, ಗೋಕರ್ಣ",
    "tags": "",
    "level": "Yakshagana;Yakshagana Prasanga;ಯಕ್ಷಗಾನ;ಯಕ್ಷಗಾನ ಪ್ರಸಂಗ;ಕನ್ನಡ ಸಾಹಿತ್ಯ",
    "authorUrl": "https://archive.org/search.php?query=creator%3Aಎಂ. ಜಿ. ಬರವಣಿ",
    "url": "https://archive.org/details/unset0000unse_q3q8",
    "cover": "https://archive.org/services/img/unset0000unse_q3q8"
  },
  {
    "author": "K. H. Ovaya Acharya",
    "info": "‌ಈ ಪುಸ್ತಕವನ್ನು  ಸಂಚಿ ಫೌಂಡೇಶನ್ (https://sanchifoundation.org) ಹಾಗೂ ಸಂಚಯದ (https://sanchaya.org) ವತಿಯಿಂದ ಇಂಡಿಯನ್ ಅಕಾಡೆಮಿ ಆಫ್ ಸೈನ್ಸ್ಸ್, ಬೆಂಗಳೂರಿನಲ್ಲಿ ಜ್ಞಾನದ ಸೇವಕರು (Servants Of Knowledge) ಸಮುದಾಯ ಸಹಭಾಗಿತ್ವದ ಕೆಲಸದಡಿಯಲ್ಲಿ ಡಿಜಿಟಲೀಕರಿಸಲಾಗಿರುತ್ತದೆ.",
    "identifier": "unset0000unse_l9z9",
    "title": "ವೀರವರ್ಮ ವಿಜಯ",
    "publisher": "Sri Kalikamba Prakashana",
    "tags": "",
    "level": "Yakshagana;Yakshagana Prasanga;ಯಕ್ಷಗಾನ;ಯಕ್ಷಗಾನ ಪ್ರಸಂಗ;ಕನ್ನಡ ಸಾಹಿತ್ಯ",
    "authorUrl": "https://archive.org/search.php?query=creator%3AK. H. Ovaya Acharya",
    "url": "https://archive.org/details/unset0000unse_l9z9",
    "cover": "https://archive.org/services/img/unset0000unse_l9z9"
  },
  {
    "author": "Kodrell Venkant Rao",
    "info": "‌ಈ ಪುಸ್ತಕವನ್ನು  ಸಂಚಿ ಫೌಂಡೇಶನ್ (https://sanchifoundation.org) ಹಾಗೂ ಸಂಚಯದ (https://sanchaya.org) ವತಿಯಿಂದ ಇಂಡಿಯನ್ ಅಕಾಡೆಮಿ ಆಫ್ ಸೈನ್ಸ್ಸ್, ಬೆಂಗಳೂರಿನಲ್ಲಿ ಜ್ಞಾನದ ಸೇವಕರು (Servants Of Knowledge) ಸಮುದಾಯ ಸಹಭಾಗಿತ್ವದ ಕೆಲಸದಡಿಯಲ್ಲಿ ಡಿಜಿಟಲೀಕರಿಸಲಾಗಿರುತ್ತದೆ.",
    "identifier": "unset0000unse_n6z0",
    "title": "ಶಕುಂತರಾಜ ಚರಿತ್ರೆ ರಾಮಾಂಜನೇಯ ಕಾಳಗವು",
    "publisher": "ಪಾವಂಜೆ ಗುರುರಾವ್",
    "tags": "",
    "level": "Yakshagana;Yakshagana Prasanga;ಯಕ್ಷಗಾನ;ಯಕ್ಷಗಾನ ಪ್ರಸಂಗ;ಕನ್ನಡ ಸಾಹಿತ್ಯ",
    "authorUrl": "https://archive.org/search.php?query=creator%3AKodrell Venkant Rao",
    "url": "https://archive.org/details/unset0000unse_n6z0",
    "cover": "https://archive.org/services/img/unset0000unse_n6z0"
  },
  {
    "author": "Chinmayadasa",
    "info": "‌ಈ ಪುಸ್ತಕವನ್ನು  ಸಂಚಿ ಫೌಂಡೇಶನ್ (https://sanchifoundation.org) ಹಾಗೂ ಸಂಚಯದ (https://sanchaya.org) ವತಿಯಿಂದ ಇಂಡಿಯನ್ ಅಕಾಡೆಮಿ ಆಫ್ ಸೈನ್ಸ್ಸ್, ಬೆಂಗಳೂರಿನಲ್ಲಿ ಜ್ಞಾನದ ಸೇವಕರು (Servants Of Knowledge) ಸಮುದಾಯ ಸಹಭಾಗಿತ್ವದ ಕೆಲಸದಡಿಯಲ್ಲಿ ಡಿಜಿಟಲೀಕರಿಸಲಾಗಿರುತ್ತದೆ.",
    "identifier": "unset0000unse_h8r8",
    "title": "ಶನಿ ದೇವರ ಮಹಾತ್ಮೆ",
    "publisher": "Ve.B. Subhaya And Sons",
    "tags": "",
    "level": "Yakshagana;Yakshagana Prasanga;ಯಕ್ಷಗಾನ;ಯಕ್ಷಗಾನ ಪ್ರಸಂಗ;ಕನ್ನಡ ಸಾಹಿತ್ಯ",
    "authorUrl": "https://archive.org/search.php?query=creator%3AChinmayadasa",
    "url": "https://archive.org/details/unset0000unse_h8r8",
    "cover": "https://archive.org/services/img/unset0000unse_h8r8"
  },
  {
    "author": "",
    "info": "‌ಈ ಪುಸ್ತಕವನ್ನು  ಸಂಚಿ ಫೌಂಡೇಶನ್ (https://sanchifoundation.org) ಹಾಗೂ ಸಂಚಯದ (https://sanchaya.org) ವತಿಯಿಂದ ಇಂಡಿಯನ್ ಅಕಾಡೆಮಿ ಆಫ್ ಸೈನ್ಸ್ಸ್, ಬೆಂಗಳೂರಿನಲ್ಲಿ ಜ್ಞಾನದ ಸೇವಕರು (Servants Of Knowledge) ಸಮುದಾಯ ಸಹಭಾಗಿತ್ವದ ಕೆಲಸದಡಿಯಲ್ಲಿ ಡಿಜಿಟಲೀಕರಿಸಲಾಗಿರುತ್ತದೆ.",
    "identifier": "unset0000unse_u3u9",
    "title": "ಶಂಬರಾಸುರನ ಕಾಳಗವು",
    "publisher": "",
    "tags": "",
    "level": "Yakshagana;Yakshagana Prasanga;ಯಕ್ಷಗಾನ;ಯಕ್ಷಗಾನ ಪ್ರಸಂಗ;ಕನ್ನಡ ಸಾಹಿತ್ಯ",
    "authorUrl": "https://archive.org/search.php?query=creator%3A",
    "url": "https://archive.org/details/unset0000unse_u3u9",
    "cover": "https://archive.org/services/img/unset0000unse_u3u9"
  },
  {
    "author": "ಹಲಸಿನಹಳ್ಳಿ ನರಸಿಂಹಶಾಸ್ತ್ರಿಗಳು",
    "info": "‌ಈ ಪುಸ್ತಕವನ್ನು  ಸಂಚಿ ಫೌಂಡೇಶನ್ (https://sanchifoundation.org) ಹಾಗೂ ಸಂಚಯದ (https://sanchaya.org) ವತಿಯಿಂದ ಇಂಡಿಯನ್ ಅಕಾಡೆಮಿ ಆಫ್ ಸೈನ್ಸ್ಸ್, ಬೆಂಗಳೂರಿನಲ್ಲಿ ಜ್ಞಾನದ ಸೇವಕರು (Servants Of Knowledge) ಸಮುದಾಯ ಸಹಭಾಗಿತ್ವದ ಕೆಲಸದಡಿಯಲ್ಲಿ ಡಿಜಿಟಲೀಕರಿಸಲಾಗಿರುತ್ತದೆ.",
    "identifier": "unset0000unse_p1m3",
    "title": "ಶಶಿಕಲಾಸ್ವಯಂವರ",
    "publisher": "Sri Chowdeshwari Printing Press",
    "tags": "",
    "level": "Yakshagana;Yakshagana Prasanga;ಯಕ್ಷಗಾನ;ಯಕ್ಷಗಾನ ಪ್ರಸಂಗ;ಕನ್ನಡ ಸಾಹಿತ್ಯ",
    "authorUrl": "https://archive.org/search.php?query=creator%3Aಹಲಸಿನಹಳ್ಳಿ ನರಸಿಂಹಶಾಸ್ತ್ರಿಗಳು",
    "url": "https://archive.org/details/unset0000unse_p1m3",
    "cover": "https://archive.org/services/img/unset0000unse_p1m3"
  },
  {
    "author": "ಎಸ್. ಗಣಪಯ್ಯ ಶೆಟ್ಟಿ",
    "info": "‌ಈ ಪುಸ್ತಕವನ್ನು  ಸಂಚಿ ಫೌಂಡೇಶನ್ (https://sanchifoundation.org) ಹಾಗೂ ಸಂಚಯದ (https://sanchaya.org) ವತಿಯಿಂದ ಇಂಡಿಯನ್ ಅಕಾಡೆಮಿ ಆಫ್ ಸೈನ್ಸ್ಸ್, ಬೆಂಗಳೂರಿನಲ್ಲಿ ಜ್ಞಾನದ ಸೇವಕರು (Servants Of Knowledge) ಸಮುದಾಯ ಸಹಭಾಗಿತ್ವದ ಕೆಲಸದಡಿಯಲ್ಲಿ ಡಿಜಿಟಲೀಕರಿಸಲಾಗಿರುತ್ತದೆ.",
    "identifier": "unset0000unse_p7x5",
    "title": "ಶಾಕುಂತಲಾ ಪರಿಣಯ",
    "publisher": "Thulunadu Chapakane, Udupi",
    "tags": "",
    "level": "Yakshagana;Yakshagana Prasanga;ಯಕ್ಷಗಾನ;ಯಕ್ಷಗಾನ ಪ್ರಸಂಗ;ಕನ್ನಡ ಸಾಹಿತ್ಯ",
    "authorUrl": "https://archive.org/search.php?query=creator%3Aಎಸ್. ಗಣಪಯ್ಯ ಶೆಟ್ಟಿ",
    "url": "https://archive.org/details/unset0000unse_p7x5",
    "cover": "https://archive.org/services/img/unset0000unse_p7x5"
  },
  {
    "author": "Pulincha Ramayya Shetty",
    "info": "‌ಈ ಪುಸ್ತಕವನ್ನು  ಸಂಚಿ ಫೌಂಡೇಶನ್ (https://sanchifoundation.org) ಹಾಗೂ ಸಂಚಯದ (https://sanchaya.org) ವತಿಯಿಂದ ಇಂಡಿಯನ್ ಅಕಾಡೆಮಿ ಆಫ್ ಸೈನ್ಸ್ಸ್, ಬೆಂಗಳೂರಿನಲ್ಲಿ ಜ್ಞಾನದ ಸೇವಕರು (Servants Of Knowledge) ಸಮುದಾಯ ಸಹಭಾಗಿತ್ವದ ಕೆಲಸದಡಿಯಲ್ಲಿ ಡಿಜಿಟಲೀಕರಿಸಲಾಗಿರುತ್ತದೆ.",
    "identifier": "unset0000unse_v2x2",
    "title": "ಶಾಂತಲ ಸ್ವಯಂವರ ಅಥವಾ ವೀರಸೇನ ಕಾಳಗ",
    "publisher": "",
    "tags": "",
    "level": "Yakshagana;Yakshagana Prasanga;ಯಕ್ಷಗಾನ;ಯಕ್ಷಗಾನ ಪ್ರಸಂಗ;ಕನ್ನಡ ಸಾಹಿತ್ಯ",
    "authorUrl": "https://archive.org/search.php?query=creator%3APulincha Ramayya Shetty",
    "url": "https://archive.org/details/unset0000unse_v2x2",
    "cover": "https://archive.org/services/img/unset0000unse_v2x2"
  },
  {
    "author": "Badragiri Neelaya Bangera",
    "info": "‌ಈ ಪುಸ್ತಕವನ್ನು  ಸಂಚಿ ಫೌಂಡೇಶನ್ (https://sanchifoundation.org) ಹಾಗೂ ಸಂಚಯದ (https://sanchaya.org) ವತಿಯಿಂದ ಇಂಡಿಯನ್ ಅಕಾಡೆಮಿ ಆಫ್ ಸೈನ್ಸ್ಸ್, ಬೆಂಗಳೂರಿನಲ್ಲಿ ಜ್ಞಾನದ ಸೇವಕರು (Servants Of Knowledge) ಸಮುದಾಯ ಸಹಭಾಗಿತ್ವದ ಕೆಲಸದಡಿಯಲ್ಲಿ ಡಿಜಿಟಲೀಕರಿಸಲಾಗಿರುತ್ತದೆ.",
    "identifier": "unset0000unse_s7e8",
    "title": "ಶಿಕಂಡಿ ಸ್ವಯಂವರ",
    "publisher": "Dinesh Printers, Brahmavara",
    "tags": "",
    "level": "Yakshagana;Yakshagana Prasanga;ಯಕ್ಷಗಾನ;ಯಕ್ಷಗಾನ ಪ್ರಸಂಗ;ಕನ್ನಡ ಸಾಹಿತ್ಯ",
    "authorUrl": "https://archive.org/search.php?query=creator%3ABadragiri Neelaya Bangera",
    "url": "https://archive.org/details/unset0000unse_s7e8",
    "cover": "https://archive.org/services/img/unset0000unse_s7e8"
  },
  {
    "author": "ಮಯ್ಯವಟಿ ವೆಂಕಟರಮಣಯ್ಯ",
    "info": "‌ಈ ಪುಸ್ತಕವನ್ನು  ಸಂಚಿ ಫೌಂಡೇಶನ್ (https://sanchifoundation.org) ಹಾಗೂ ಸಂಚಯದ (https://sanchaya.org) ವತಿಯಿಂದ ಇಂಡಿಯನ್ ಅಕಾಡೆಮಿ ಆಫ್ ಸೈನ್ಸ್ಸ್, ಬೆಂಗಳೂರಿನಲ್ಲಿ ಜ್ಞಾನದ ಸೇವಕರು (Servants Of Knowledge) ಸಮುದಾಯ ಸಹಭಾಗಿತ್ವದ ಕೆಲಸದಡಿಯಲ್ಲಿ ಡಿಜಿಟಲೀಕರಿಸಲಾಗಿರುತ್ತದೆ.",
    "identifier": "unset0000unse_k7s1",
    "title": "ಶೂರಪದ್ಮಾಸುರಕಾಳಗ ಮತ್ತು ಶೂರಪದ್ಮವಧೆ",
    "publisher": "ಲಕ್ಷ್ಮೀನಾರಾಯಣ ಟ್ರಸ್ಟ್",
    "tags": "",
    "level": "Yakshagana;Yakshagana Prasanga;ಯಕ್ಷಗಾನ;ಯಕ್ಷಗಾನ ಪ್ರಸಂಗ;ಕನ್ನಡ ಸಾಹಿತ್ಯ",
    "authorUrl": "https://archive.org/search.php?query=creator%3Aಮಯ್ಯವಟಿ ವೆಂಕಟರಮಣಯ್ಯ",
    "url": "https://archive.org/details/unset0000unse_k7s1",
    "cover": "https://archive.org/services/img/unset0000unse_k7s1"
  },
  {
    "author": "ಹಲಸಿನಹಳ್ಳಿ ನರಸಿಂಹಶಾಸ್ತ್ರಿಗಳು",
    "info": "‌ಈ ಪುಸ್ತಕವನ್ನು  ಸಂಚಿ ಫೌಂಡೇಶನ್ (https://sanchifoundation.org) ಹಾಗೂ ಸಂಚಯದ (https://sanchaya.org) ವತಿಯಿಂದ ಇಂಡಿಯನ್ ಅಕಾಡೆಮಿ ಆಫ್ ಸೈನ್ಸ್ಸ್, ಬೆಂಗಳೂರಿನಲ್ಲಿ ಜ್ಞಾನದ ಸೇವಕರು (Servants Of Knowledge) ಸಮುದಾಯ ಸಹಭಾಗಿತ್ವದ ಕೆಲಸದಡಿಯಲ್ಲಿ ಡಿಜಿಟಲೀಕರಿಸಲಾಗಿರುತ್ತದೆ.",
    "identifier": "unset0000unse_n2u9",
    "title": "ಶ್ರೀ ರುಗ್ಮವತೀ ಕಲ್ಯಾಣ",
    "publisher": "ರಾಧಾಕೃಷ್ಣ ಮುದ್ರಾಮಂದಿರ",
    "tags": "",
    "level": "Yakshagana;Yakshagana Prasanga;ಯಕ್ಷಗಾನ;ಯಕ್ಷಗಾನ ಪ್ರಸಂಗ;ಕನ್ನಡ ಸಾಹಿತ್ಯ",
    "authorUrl": "https://archive.org/search.php?query=creator%3Aಹಲಸಿನಹಳ್ಳಿ ನರಸಿಂಹಶಾಸ್ತ್ರಿಗಳು",
    "url": "https://archive.org/details/unset0000unse_n2u9",
    "cover": "https://archive.org/services/img/unset0000unse_n2u9"
  },
  {
    "author": "ಜಿ. ನಂಜುಂಡಯ್ಯ",
    "info": "‌ಈ ಪುಸ್ತಕವನ್ನು  ಸಂಚಿ ಫೌಂಡೇಶನ್ (https://sanchifoundation.org) ಹಾಗೂ ಸಂಚಯದ (https://sanchaya.org) ವತಿಯಿಂದ ಇಂಡಿಯನ್ ಅಕಾಡೆಮಿ ಆಫ್ ಸೈನ್ಸ್ಸ್, ಬೆಂಗಳೂರಿನಲ್ಲಿ ಜ್ಞಾನದ ಸೇವಕರು (Servants Of Knowledge) ಸಮುದಾಯ ಸಹಭಾಗಿತ್ವದ ಕೆಲಸದಡಿಯಲ್ಲಿ ಡಿಜಿಟಲೀಕರಿಸಲಾಗಿರುತ್ತದೆ.",
    "identifier": "unset0000unse_c1q2",
    "title": "ಶ್ರೀ ಶನಿದೇವರ ಪ್ರಭಾವ ಪುರುರವನ ಪರಾಭವ",
    "publisher": "ಶ್ರೀ ಶಾರದಾ ಸಾಹಿತ್ಯ ಭಂಡಾರ",
    "tags": "",
    "level": "Yakshagana;Yakshagana Prasanga;ಯಕ್ಷಗಾನ;ಯಕ್ಷಗಾನ ಪ್ರಸಂಗ;ಕನ್ನಡ ಸಾಹಿತ್ಯ",
    "authorUrl": "https://archive.org/search.php?query=creator%3Aಜಿ. ನಂಜುಂಡಯ್ಯ",
    "url": "https://archive.org/details/unset0000unse_c1q2",
    "cover": "https://archive.org/services/img/unset0000unse_c1q2"
  },
  {
    "author": "ಸೀತಾನದಿ ಗಣಪಯ್ಯ ಶೆಟ್ಟಿ",
    "info": "‌ಈ ಪುಸ್ತಕವನ್ನು  ಸಂಚಿ ಫೌಂಡೇಶನ್ (https://sanchifoundation.org) ಹಾಗೂ ಸಂಚಯದ (https://sanchaya.org) ವತಿಯಿಂದ ಇಂಡಿಯನ್ ಅಕಾಡೆಮಿ ಆಫ್ ಸೈನ್ಸ್ಸ್, ಬೆಂಗಳೂರಿನಲ್ಲಿ ಜ್ಞಾನದ ಸೇವಕರು (Servants Of Knowledge) ಸಮುದಾಯ ಸಹಭಾಗಿತ್ವದ ಕೆಲಸದಡಿಯಲ್ಲಿ ಡಿಜಿಟಲೀಕರಿಸಲಾಗಿರುತ್ತದೆ.",
    "identifier": "unset0000unse_o2r4",
    "title": "ಶ್ರೀ ಹಿರಿಯಡಕಕ್ಷೇತ್ರ ಮಹಾತ್ಮೆ",
    "publisher": "ಸುಭೋಧ ಸಾಹಿತ್ಯ ಭಂಡಾರ",
    "tags": "",
    "level": "Yakshagana;Yakshagana Prasanga;ಯಕ್ಷಗಾನ;ಯಕ್ಷಗಾನ ಪ್ರಸಂಗ;ಕನ್ನಡ ಸಾಹಿತ್ಯ",
    "authorUrl": "https://archive.org/search.php?query=creator%3Aಸೀತಾನದಿ ಗಣಪಯ್ಯ ಶೆಟ್ಟಿ",
    "url": "https://archive.org/details/unset0000unse_o2r4",
    "cover": "https://archive.org/services/img/unset0000unse_o2r4"
  },
  {
    "author": "ರಾಜಗೋಪಾಲಾಚಾರ್ಯ",
    "info": "‌ಈ ಪುಸ್ತಕವನ್ನು  ಸಂಚಿ ಫೌಂಡೇಶನ್ (https://sanchifoundation.org) ಹಾಗೂ ಸಂಚಯದ (https://sanchaya.org) ವತಿಯಿಂದ ಇಂಡಿಯನ್ ಅಕಾಡೆಮಿ ಆಫ್ ಸೈನ್ಸ್ಸ್, ಬೆಂಗಳೂರಿನಲ್ಲಿ ಜ್ಞಾನದ ಸೇವಕರು (Servants Of Knowledge) ಸಮುದಾಯ ಸಹಭಾಗಿತ್ವದ ಕೆಲಸದಡಿಯಲ್ಲಿ ಡಿಜಿಟಲೀಕರಿಸಲಾಗಿರುತ್ತದೆ.",
    "identifier": "unset0000unse_p1t4",
    "title": "ಶ್ರೀಕೃಷ್ಣದಿನಾಶ್ವಮೆಧ",
    "publisher": "ಪಾವಂಜೆ ಗುರುರಾವ್",
    "tags": "",
    "level": "Yakshagana;Yakshagana Prasanga;ಯಕ್ಷಗಾನ;ಯಕ್ಷಗಾನ ಪ್ರಸಂಗ;ಕನ್ನಡ ಸಾಹಿತ್ಯ",
    "authorUrl": "https://archive.org/search.php?query=creator%3Aರಾಜಗೋಪಾಲಾಚಾರ್ಯ",
    "url": "https://archive.org/details/unset0000unse_p1t4",
    "cover": "https://archive.org/services/img/unset0000unse_p1t4"
  },
  {
    "author": "Haridasa Sheni Gopalakrishna Bhat.",
    "info": "‌ಈ ಪುಸ್ತಕವನ್ನು  ಸಂಚಿ ಫೌಂಡೇಶನ್ (https://sanchifoundation.org) ಹಾಗೂ ಸಂಚಯದ (https://sanchaya.org) ವತಿಯಿಂದ ಇಂಡಿಯನ್ ಅಕಾಡೆಮಿ ಆಫ್ ಸೈನ್ಸ್ಸ್, ಬೆಂಗಳೂರಿನಲ್ಲಿ ಜ್ಞಾನದ ಸೇವಕರು (Servants Of Knowledge) ಸಮುದಾಯ ಸಹಭಾಗಿತ್ವದ ಕೆಲಸದಡಿಯಲ್ಲಿ ಡಿಜಿಟಲೀಕರಿಸಲಾಗಿರುತ್ತದೆ.",
    "identifier": "unset0000unse_e9f4",
    "title": "ಶ್ರೀಮತಿ ಪರಿಣಯ ಮತ್ತು ಮಧ್ಯಮವ್ಯಾಯೋಗ",
    "publisher": "Gurukula Mudranalaya, Pelra",
    "tags": "",
    "level": "Yakshagana;Yakshagana Prasanga;ಯಕ್ಷಗಾನ;ಯಕ್ಷಗಾನ ಪ್ರಸಂಗ;ಕನ್ನಡ ಸಾಹಿತ್ಯ",
    "authorUrl": "https://archive.org/search.php?query=creator%3AHaridasa Sheni Gopalakrishna Bhat.",
    "url": "https://archive.org/details/unset0000unse_e9f4",
    "cover": "https://archive.org/services/img/unset0000unse_e9f4"
  },
  {
    "author": "ಪಾವಂಜೆ ಗುರುರಾಯರು",
    "info": "‌ಈ ಪುಸ್ತಕವನ್ನು  ಸಂಚಿ ಫೌಂಡೇಶನ್ (https://sanchifoundation.org) ಹಾಗೂ ಸಂಚಯದ (https://sanchaya.org) ವತಿಯಿಂದ ಇಂಡಿಯನ್ ಅಕಾಡೆಮಿ ಆಫ್ ಸೈನ್ಸ್ಸ್, ಬೆಂಗಳೂರಿನಲ್ಲಿ ಜ್ಞಾನದ ಸೇವಕರು (Servants Of Knowledge) ಸಮುದಾಯ ಸಹಭಾಗಿತ್ವದ ಕೆಲಸದಡಿಯಲ್ಲಿ ಡಿಜಿಟಲೀಕರಿಸಲಾಗಿರುತ್ತದೆ.",
    "identifier": "unset0000unse_s7h0",
    "title": "ಸಮುದ್ರ ಮಂಥನ",
    "publisher": "ಪಾವಂಜೆ ಗುರುರಾವ್",
    "tags": "",
    "level": "Yakshagana;Yakshagana Prasanga;ಯಕ್ಷಗಾನ;ಯಕ್ಷಗಾನ ಪ್ರಸಂಗ;ಕನ್ನಡ ಸಾಹಿತ್ಯ",
    "authorUrl": "https://archive.org/search.php?query=creator%3Aಪಾವಂಜೆ ಗುರುರಾಯರು",
    "url": "https://archive.org/details/unset0000unse_s7h0",
    "cover": "https://archive.org/services/img/unset0000unse_s7h0"
  },
  {
    "author": "ಎಸ್. ಗಣಪಯ್ಯ ಶೆಟ್ಟಿ",
    "info": "‌ಈ ಪುಸ್ತಕವನ್ನು  ಸಂಚಿ ಫೌಂಡೇಶನ್ (https://sanchifoundation.org) ಹಾಗೂ ಸಂಚಯದ (https://sanchaya.org) ವತಿಯಿಂದ ಇಂಡಿಯನ್ ಅಕಾಡೆಮಿ ಆಫ್ ಸೈನ್ಸ್ಸ್, ಬೆಂಗಳೂರಿನಲ್ಲಿ ಜ್ಞಾನದ ಸೇವಕರು (Servants Of Knowledge) ಸಮುದಾಯ ಸಹಭಾಗಿತ್ವದ ಕೆಲಸದಡಿಯಲ್ಲಿ ಡಿಜಿಟಲೀಕರಿಸಲಾಗಿರುತ್ತದೆ.",
    "identifier": "unset0000unse_d7k5",
    "title": "ಸಹದೇವ್ ದಿಗ್ವಿಜಯ",
    "publisher": "ಆರ್. ವೆಂಕಟಪ್ಪ ಶಣೈ & ಸನ್ಸ್",
    "tags": "",
    "level": "Yakshagana;Yakshagana Prasanga;ಯಕ್ಷಗಾನ;ಯಕ್ಷಗಾನ ಪ್ರಸಂಗ;ಕನ್ನಡ ಸಾಹಿತ್ಯ",
    "authorUrl": "https://archive.org/search.php?query=creator%3Aಎಸ್. ಗಣಪಯ್ಯ ಶೆಟ್ಟಿ",
    "url": "https://archive.org/details/unset0000unse_d7k5",
    "cover": "https://archive.org/services/img/unset0000unse_d7k5"
  },
  {
    "author": "ಕೀರಿಕ್ಕಾಡು ಮಾಸ್ತರ್ ವಿಷ್ಣು ಭಟ್",
    "info": "‌ಈ ಪುಸ್ತಕವನ್ನು  ಸಂಚಿ ಫೌಂಡೇಶನ್ (https://sanchifoundation.org) ಹಾಗೂ ಸಂಚಯದ (https://sanchaya.org) ವತಿಯಿಂದ ಇಂಡಿಯನ್ ಅಕಾಡೆಮಿ ಆಫ್ ಸೈನ್ಸ್ಸ್, ಬೆಂಗಳೂರಿನಲ್ಲಿ ಜ್ಞಾನದ ಸೇವಕರು (Servants Of Knowledge) ಸಮುದಾಯ ಸಹಭಾಗಿತ್ವದ ಕೆಲಸದಡಿಯಲ್ಲಿ ಡಿಜಿಟಲೀಕರಿಸಲಾಗಿರುತ್ತದೆ.",
    "identifier": "unset0000unse_t3r5",
    "title": "ಸೀತಾ ಪರಿತ್ಯಾಗ",
    "publisher": "ಶ್ರೀ ಗೋಪಾಲಕೃಷ್ಣ ಪ್ರಕಾಶನ",
    "tags": "",
    "level": "Yakshagana;Yakshagana Prasanga;ಯಕ್ಷಗಾನ;ಯಕ್ಷಗಾನ ಪ್ರಸಂಗ;ಕನ್ನಡ ಸಾಹಿತ್ಯ",
    "authorUrl": "https://archive.org/search.php?query=creator%3Aಕೀರಿಕ್ಕಾಡು ಮಾಸ್ತರ್ ವಿಷ್ಣು ಭಟ್",
    "url": "https://archive.org/details/unset0000unse_t3r5",
    "cover": "https://archive.org/services/img/unset0000unse_t3r5"
  },
  {
    "author": "",
    "info": "‌ಈ ಪುಸ್ತಕವನ್ನು  ಸಂಚಿ ಫೌಂಡೇಶನ್ (https://sanchifoundation.org) ಹಾಗೂ ಸಂಚಯದ (https://sanchaya.org) ವತಿಯಿಂದ ಇಂಡಿಯನ್ ಅಕಾಡೆಮಿ ಆಫ್ ಸೈನ್ಸ್ಸ್, ಬೆಂಗಳೂರಿನಲ್ಲಿ ಜ್ಞಾನದ ಸೇವಕರು (Servants Of Knowledge) ಸಮುದಾಯ ಸಹಭಾಗಿತ್ವದ ಕೆಲಸದಡಿಯಲ್ಲಿ ಡಿಜಿಟಲೀಕರಿಸಲಾಗಿರುತ್ತದೆ.",
    "identifier": "unset0000unse_n3n3",
    "title": "ಸೀತಾ ಸ್ವಯಂವರ",
    "publisher": "",
    "tags": "",
    "level": "Yakshagana;Yakshagana Prasanga;ಯಕ್ಷಗಾನ;ಯಕ್ಷಗಾನ ಪ್ರಸಂಗ;ಕನ್ನಡ ಸಾಹಿತ್ಯ",
    "authorUrl": "https://archive.org/search.php?query=creator%3A",
    "url": "https://archive.org/details/unset0000unse_n3n3",
    "cover": "https://archive.org/services/img/unset0000unse_n3n3"
  },
  {
    "author": "D.V. Holsa Vidhvan",
    "info": "‌ಈ ಪುಸ್ತಕವನ್ನು  ಸಂಚಿ ಫೌಂಡೇಶನ್ (https://sanchifoundation.org) ಹಾಗೂ ಸಂಚಯದ (https://sanchaya.org) ವತಿಯಿಂದ ಇಂಡಿಯನ್ ಅಕಾಡೆಮಿ ಆಫ್ ಸೈನ್ಸ್ಸ್, ಬೆಂಗಳೂರಿನಲ್ಲಿ ಜ್ಞಾನದ ಸೇವಕರು (Servants Of Knowledge) ಸಮುದಾಯ ಸಹಭಾಗಿತ್ವದ ಕೆಲಸದಡಿಯಲ್ಲಿ ಡಿಜಿಟಲೀಕರಿಸಲಾಗಿರುತ್ತದೆ.",
    "identifier": "unset0000unse_k1r0",
    "title": "ಸೀಮಂತಿನೀ ಪರಿಣಯ",
    "publisher": "Dinesh Printers, Brahmavara",
    "tags": "",
    "level": "Yakshagana;Yakshagana Prasanga;ಯಕ್ಷಗಾನ;ಯಕ್ಷಗಾನ ಪ್ರಸಂಗ;ಕನ್ನಡ ಸಾಹಿತ್ಯ",
    "authorUrl": "https://archive.org/search.php?query=creator%3AD.V. Holsa Vidhvan",
    "url": "https://archive.org/details/unset0000unse_k1r0",
    "cover": "https://archive.org/services/img/unset0000unse_k1r0"
  },
  {
    "author": "ಎಂ. ಜಿ. ಬರವಣಿ",
    "info": "‌ಈ ಪುಸ್ತಕವನ್ನು  ಸಂಚಿ ಫೌಂಡೇಶನ್ (https://sanchifoundation.org) ಹಾಗೂ ಸಂಚಯದ (https://sanchaya.org) ವತಿಯಿಂದ ಇಂಡಿಯನ್ ಅಕಾಡೆಮಿ ಆಫ್ ಸೈನ್ಸ್ಸ್, ಬೆಂಗಳೂರಿನಲ್ಲಿ ಜ್ಞಾನದ ಸೇವಕರು (Servants Of Knowledge) ಸಮುದಾಯ ಸಹಭಾಗಿತ್ವದ ಕೆಲಸದಡಿಯಲ್ಲಿ ಡಿಜಿಟಲೀಕರಿಸಲಾಗಿರುತ್ತದೆ.",
    "identifier": "unset0000unse_b5s4",
    "title": "ಸುಂದೋಪ ಸುಂದರ ಕಾಳಗ",
    "publisher": "ಎಂ. ಜಿ. ಬರವಣಿ, ಯಕ್ಷಗಾನ ಕಲಾವಿದರು, ಗೋಕರ್ಣ",
    "tags": "",
    "level": "Yakshagana;Yakshagana Prasanga;ಯಕ್ಷಗಾನ;ಯಕ್ಷಗಾನ ಪ್ರಸಂಗ;ಕನ್ನಡ ಸಾಹಿತ್ಯ",
    "authorUrl": "https://archive.org/search.php?query=creator%3Aಎಂ. ಜಿ. ಬರವಣಿ",
    "url": "https://archive.org/details/unset0000unse_b5s4",
    "cover": "https://archive.org/services/img/unset0000unse_b5s4"
  },
  {
    "author": "ಎಂ. ಜಿ. ಬರವಣಿ",
    "info": "‌ಈ ಪುಸ್ತಕವನ್ನು  ಸಂಚಿ ಫೌಂಡೇಶನ್ (https://sanchifoundation.org) ಹಾಗೂ ಸಂಚಯದ (https://sanchaya.org) ವತಿಯಿಂದ ಇಂಡಿಯನ್ ಅಕಾಡೆಮಿ ಆಫ್ ಸೈನ್ಸ್ಸ್, ಬೆಂಗಳೂರಿನಲ್ಲಿ ಜ್ಞಾನದ ಸೇವಕರು (Servants Of Knowledge) ಸಮುದಾಯ ಸಹಭಾಗಿತ್ವದ ಕೆಲಸದಡಿಯಲ್ಲಿ ಡಿಜಿಟಲೀಕರಿಸಲಾಗಿರುತ್ತದೆ.",
    "identifier": "unset0000unse_u6y8",
    "title": "ಸುನಂದಾ ಸ್ವಯಂವರ",
    "publisher": "ಎಂ. ಜಿ. ಬರವಣಿ, ಯಕ್ಷಗಾನ ಕಲಾವಿದರು, ಗೋಕರ್ಣ",
    "tags": "",
    "level": "Yakshagana;Yakshagana Prasanga;ಯಕ್ಷಗಾನ;ಯಕ್ಷಗಾನ ಪ್ರಸಂಗ;ಕನ್ನಡ ಸಾಹಿತ್ಯ",
    "authorUrl": "https://archive.org/search.php?query=creator%3Aಎಂ. ಜಿ. ಬರವಣಿ",
    "url": "https://archive.org/details/unset0000unse_u6y8",
    "cover": "https://archive.org/services/img/unset0000unse_u6y8"
  },
  {
    "author": "ಎಂ. ಜಿ. ಬರವಣಿ",
    "info": "‌ಈ ಪುಸ್ತಕವನ್ನು  ಸಂಚಿ ಫೌಂಡೇಶನ್ (https://sanchifoundation.org) ಹಾಗೂ ಸಂಚಯದ (https://sanchaya.org) ವತಿಯಿಂದ ಇಂಡಿಯನ್ ಅಕಾಡೆಮಿ ಆಫ್ ಸೈನ್ಸ್ಸ್, ಬೆಂಗಳೂರಿನಲ್ಲಿ ಜ್ಞಾನದ ಸೇವಕರು (Servants Of Knowledge) ಸಮುದಾಯ ಸಹಭಾಗಿತ್ವದ ಕೆಲಸದಡಿಯಲ್ಲಿ ಡಿಜಿಟಲೀಕರಿಸಲಾಗಿರುತ್ತದೆ.",
    "identifier": "unset0000unse_l7e6",
    "title": "ಸುಪ್ರತಪಿ ಸುದರ್ಶನ",
    "publisher": "ಎಂ. ಜಿ. ಬರವಣಿ, ಯಕ್ಷಗಾನ ಕಲಾವಿದರು, ಗೋಕರ್ಣ",
    "tags": "",
    "level": "Yakshagana;Yakshagana Prasanga;ಯಕ್ಷಗಾನ;ಯಕ್ಷಗಾನ ಪ್ರಸಂಗ;ಕನ್ನಡ ಸಾಹಿತ್ಯ",
    "authorUrl": "https://archive.org/search.php?query=creator%3Aಎಂ. ಜಿ. ಬರವಣಿ",
    "url": "https://archive.org/details/unset0000unse_l7e6",
    "cover": "https://archive.org/services/img/unset0000unse_l7e6"
  },
  {
    "author": "ಉಡುಪಿ ಲಕ್ಷ್ಮೀನಾರಯಣಾಚಾರ್ಯ",
    "info": "‌ಈ ಪುಸ್ತಕವನ್ನು  ಸಂಚಿ ಫೌಂಡೇಶನ್ (https://sanchifoundation.org) ಹಾಗೂ ಸಂಚಯದ (https://sanchaya.org) ವತಿಯಿಂದ ಇಂಡಿಯನ್ ಅಕಾಡೆಮಿ ಆಫ್ ಸೈನ್ಸ್ಸ್, ಬೆಂಗಳೂರಿನಲ್ಲಿ ಜ್ಞಾನದ ಸೇವಕರು (Servants Of Knowledge) ಸಮುದಾಯ ಸಹಭಾಗಿತ್ವದ ಕೆಲಸದಡಿಯಲ್ಲಿ ಡಿಜಿಟಲೀಕರಿಸಲಾಗಿರುತ್ತದೆ.",
    "identifier": "unset0000unse_w9z4",
    "title": "ಸುಬಾಹುಕಾಳಗ",
    "publisher": "ಪಾವಂಜೆ ಗುರುರಾವ್",
    "tags": "",
    "level": "Yakshagana;Yakshagana Prasanga;ಯಕ್ಷಗಾನ;ಯಕ್ಷಗಾನ ಪ್ರಸಂಗ;ಕನ್ನಡ ಸಾಹಿತ್ಯ",
    "authorUrl": "https://archive.org/search.php?query=creator%3Aಉಡುಪಿ ಲಕ್ಷ್ಮೀನಾರಯಣಾಚಾರ್ಯ",
    "url": "https://archive.org/details/unset0000unse_w9z4",
    "cover": "https://archive.org/services/img/unset0000unse_w9z4"
  },
  {
    "author": "",
    "info": "‌ಈ ಪುಸ್ತಕವನ್ನು  ಸಂಚಿ ಫೌಂಡೇಶನ್ (https://sanchifoundation.org) ಹಾಗೂ ಸಂಚಯದ (https://sanchaya.org) ವತಿಯಿಂದ ಇಂಡಿಯನ್ ಅಕಾಡೆಮಿ ಆಫ್ ಸೈನ್ಸ್ಸ್, ಬೆಂಗಳೂರಿನಲ್ಲಿ ಜ್ಞಾನದ ಸೇವಕರು (Servants Of Knowledge) ಸಮುದಾಯ ಸಹಭಾಗಿತ್ವದ ಕೆಲಸದಡಿಯಲ್ಲಿ ಡಿಜಿಟಲೀಕರಿಸಲಾಗಿರುತ್ತದೆ.",
    "identifier": "unset0000unse_j7l1",
    "title": "ಸುಭದ್ರ ಕಲ್ಯಾಣ",
    "publisher": "ಪಾವಂಜೆ ಗುರುರಾವ್",
    "tags": "",
    "level": "Yakshagana;Yakshagana Prasanga;ಯಕ್ಷಗಾನ;ಯಕ್ಷಗಾನ ಪ್ರಸಂಗ;ಕನ್ನಡ ಸಾಹಿತ್ಯ",
    "authorUrl": "https://archive.org/search.php?query=creator%3A",
    "url": "https://archive.org/details/unset0000unse_j7l1",
    "cover": "https://archive.org/services/img/unset0000unse_j7l1"
  },
  {
    "author": "ಎಂ. ಜಿ. ಬರವಣಿ",
    "info": "‌ಈ ಪುಸ್ತಕವನ್ನು  ಸಂಚಿ ಫೌಂಡೇಶನ್ (https://sanchifoundation.org) ಹಾಗೂ ಸಂಚಯದ (https://sanchaya.org) ವತಿಯಿಂದ ಇಂಡಿಯನ್ ಅಕಾಡೆಮಿ ಆಫ್ ಸೈನ್ಸ್ಸ್, ಬೆಂಗಳೂರಿನಲ್ಲಿ ಜ್ಞಾನದ ಸೇವಕರು (Servants Of Knowledge) ಸಮುದಾಯ ಸಹಭಾಗಿತ್ವದ ಕೆಲಸದಡಿಯಲ್ಲಿ ಡಿಜಿಟಲೀಕರಿಸಲಾಗಿರುತ್ತದೆ.",
    "identifier": "unset0000unse_u4c3",
    "title": "ಸೌಗಂಧಿಕ ಪುಷ್ಪಾಪಹಾರ",
    "publisher": "ನವೀನ ಯಕ್ಷಗಾನ ಕಲಾಸಂಘ, ಗೋಕರ್ಣ",
    "tags": "",
    "level": "Yakshagana;Yakshagana Prasanga;ಯಕ್ಷಗಾನ;ಯಕ್ಷಗಾನ ಪ್ರಸಂಗ;ಕನ್ನಡ ಸಾಹಿತ್ಯ",
    "authorUrl": "https://archive.org/search.php?query=creator%3Aಎಂ. ಜಿ. ಬರವಣಿ",
    "url": "https://archive.org/details/unset0000unse_u4c3",
    "cover": "https://archive.org/services/img/unset0000unse_u4c3"
  },
  {
    "author": "",
    "info": "‌ಈ ಪುಸ್ತಕವನ್ನು  ಸಂಚಿ ಫೌಂಡೇಶನ್ (https://sanchifoundation.org) ಹಾಗೂ ಸಂಚಯದ (https://sanchaya.org) ವತಿಯಿಂದ ಇಂಡಿಯನ್ ಅಕಾಡೆಮಿ ಆಫ್ ಸೈನ್ಸ್ಸ್, ಬೆಂಗಳೂರಿನಲ್ಲಿ ಜ್ಞಾನದ ಸೇವಕರು (Servants Of Knowledge) ಸಮುದಾಯ ಸಹಭಾಗಿತ್ವದ ಕೆಲಸದಡಿಯಲ್ಲಿ ಡಿಜಿಟಲೀಕರಿಸಲಾಗಿರುತ್ತದೆ.",
    "identifier": "unset0000unse_n6x7",
    "title": "ಸೌಗಂಧಿಕಾಹರಣ ಮತ್ತೂ ಜಟಾಸುರವಧೆ",
    "publisher": "ಪಾವಂಜೆ ಗುರುರಾವ್",
    "tags": "",
    "level": "Yakshagana;Yakshagana Prasanga;ಯಕ್ಷಗಾನ;ಯಕ್ಷಗಾನ ಪ್ರಸಂಗ;ಕನ್ನಡ ಸಾಹಿತ್ಯ",
    "authorUrl": "https://archive.org/search.php?query=creator%3A",
    "url": "https://archive.org/details/unset0000unse_n6x7",
    "cover": "https://archive.org/services/img/unset0000unse_n6x7"
  },
  {
    "author": "ಎಂ. ಜಿ. ಬರವಣಿ",
    "info": "‌ಈ ಪುಸ್ತಕವನ್ನು  ಸಂಚಿ ಫೌಂಡೇಶನ್ (https://sanchifoundation.org) ಹಾಗೂ ಸಂಚಯದ (https://sanchaya.org) ವತಿಯಿಂದ ಇಂಡಿಯನ್ ಅಕಾಡೆಮಿ ಆಫ್ ಸೈನ್ಸ್ಸ್, ಬೆಂಗಳೂರಿನಲ್ಲಿ ಜ್ಞಾನದ ಸೇವಕರು (Servants Of Knowledge) ಸಮುದಾಯ ಸಹಭಾಗಿತ್ವದ ಕೆಲಸದಡಿಯಲ್ಲಿ ಡಿಜಿಟಲೀಕರಿಸಲಾಗಿರುತ್ತದೆ.",
    "identifier": "unset0000unse_k0o5",
    "title": "ಸ್ವರ್ಣ - ಲಾವಣ್ಯ",
    "publisher": "ಎಂ. ಜಿ. ಬರವಣಿ, ಯಕ್ಷಗಾನ ಕಲಾವಿದರು, ಗೋಕರ್ಣ",
    "tags": "",
    "level": "Yakshagana;Yakshagana Prasanga;ಯಕ್ಷಗಾನ;ಯಕ್ಷಗಾನ ಪ್ರಸಂಗ;ಕನ್ನಡ ಸಾಹಿತ್ಯ",
    "authorUrl": "https://archive.org/search.php?query=creator%3Aಎಂ. ಜಿ. ಬರವಣಿ",
    "url": "https://archive.org/details/unset0000unse_k0o5",
    "cover": "https://archive.org/services/img/unset0000unse_k0o5"
  },
  {
    "author": "ಕೊಡ್ರೆಲ್ ವೆಂಕಟ್ರಾವ್",
    "info": "‌ಈ ಪುಸ್ತಕವನ್ನು  ಸಂಚಿ ಫೌಂಡೇಶನ್ (https://sanchifoundation.org) ಹಾಗೂ ಸಂಚಯದ (https://sanchaya.org) ವತಿಯಿಂದ ಇಂಡಿಯನ್ ಅಕಾಡೆಮಿ ಆಫ್ ಸೈನ್ಸ್ಸ್, ಬೆಂಗಳೂರಿನಲ್ಲಿ ಜ್ಞಾನದ ಸೇವಕರು (Servants Of Knowledge) ಸಮುದಾಯ ಸಹಭಾಗಿತ್ವದ ಕೆಲಸದಡಿಯಲ್ಲಿ ಡಿಜಿಟಲೀಕರಿಸಲಾಗಿರುತ್ತದೆ.",
    "identifier": "unset0000unse_j0q6",
    "title": "ಹಂಸಡಿಬಗರ ಕಾಳಗವು",
    "publisher": "ಶ್ರೀ ಲಕ್ಷ್ಮಿ ವಿಲಾಸ ಮುದ್ರಾಶಾಲೆ",
    "tags": "",
    "level": "Yakshagana;Yakshagana Prasanga;ಯಕ್ಷಗಾನ;ಯಕ್ಷಗಾನ ಪ್ರಸಂಗ;ಕನ್ನಡ ಸಾಹಿತ್ಯ",
    "authorUrl": "https://archive.org/search.php?query=creator%3Aಕೊಡ್ರೆಲ್ ವೆಂಕಟ್ರಾವ್",
    "url": "https://archive.org/details/unset0000unse_j0q6",
    "cover": "https://archive.org/services/img/unset0000unse_j0q6"
  },
  {
    "author": "Pavanjaya",
    "info": "‌ಈ ಪುಸ್ತಕವನ್ನು  ಸಂಚಿ ಫೌಂಡೇಶನ್ (https://sanchifoundation.org) ಹಾಗೂ ಸಂಚಯದ (https://sanchaya.org) ವತಿಯಿಂದ ಇಂಡಿಯನ್ ಅಕಾಡೆಮಿ ಆಫ್ ಸೈನ್ಸ್ಸ್, ಬೆಂಗಳೂರಿನಲ್ಲಿ ಜ್ಞಾನದ ಸೇವಕರು (Servants Of Knowledge) ಸಮುದಾಯ ಸಹಭಾಗಿತ್ವದ ಕೆಲಸದಡಿಯಲ್ಲಿ ಡಿಜಿಟಲೀಕರಿಸಲಾಗಿರುತ್ತದೆ.",
    "identifier": "unset0000unse_x5b9",
    "title": "ಹಿರಣ್ಯಾಕ್ಷನ ವಧೆ",
    "publisher": "ಪಾವಂಜೆ ಗುರುರಾವ್",
    "tags": "",
    "level": "Yakshagana;Yakshagana Prasanga;ಯಕ್ಷಗಾನ;ಯಕ್ಷಗಾನ ಪ್ರಸಂಗ;ಕನ್ನಡ ಸಾಹಿತ್ಯ",
    "authorUrl": "https://archive.org/search.php?query=creator%3APavanjaya",
    "url": "https://archive.org/details/unset0000unse_x5b9",
    "cover": "https://archive.org/services/img/unset0000unse_x5b9"
  },
    {
    "author": "ಬವಲಾಡಿ ಹಿರಿಯಣ್ಣ ಹೆಬ್ಬಾರ",
    "info": "ಈ ಪುಸ್ತಕವನ್ನು  ಸಂಚಿ ಫೌಂಡೇಶನ್ (https://sanchifoundation.org) ಹಾಗೂ ಸಂಚಯದ (https://sanchaya.org) ವತಿಯಿಂದ ಇಂಡಿಯನ್ ಅಕಾಡೆಮಿ ಆಫ್ ಸೈನ್ಸ್ಸ್, ಬೆಂಗಳೂರಿನಲ್ಲಿ ಜ್ಞಾನದ ಸೇವಕರು (Servants Of Knowledge) ಸಮುದಾಯ ಸಹಭಾಗಿತ್ವದ ಕೆಲಸದಡಿಯಲ್ಲಿ ಡಿಜಿಟಲೀಕರಿಸಲಾಗಿರುತ್ತದೆ.",
    "identifier": "yakshaloka-bh-hebbar-2023",
    "title": "ಯಕ್ಷಲೋಕ",
    "publisher": "ಪಾವಂಜೆ ಗುರುರಾವ್",
    "tags": "",
    "level": "Yakshagana;Yakshagana Prasanga;ಯಕ್ಷಗಾನ;ಯಕ್ಷಗಾನ ಪ್ರಸಂಗ;ಕನ್ನಡ ಸಾಹಿತ್ಯ",
    "authorUrl": "https://archive.org/search.php?query=creator%3Aಬವಲಾಡಿ ಹಿರಿಯಣ್ಣ ಹೆಬ್ಬಾರ",
    "url": "https://archive.org/details/yakshaloka-bh-hebbar-2023",
    "cover": "https://archive.org/services/img/yakshaloka-bh-hebbar-2023"
  }
]
}
